Workbook
Name \F: #REF!
Name _DAT1: #REF!
Name _DAT10: #REF!
Name _DAT11: #REF!
Name _DAT12: #REF!
Name _DAT13: #REF!
Name _DAT14: #REF!
Name _DAT15: #REF!
Name _DAT16: #REF!
Name _DAT17: #REF!
Name _DAT2: #REF!
Name _DAT3: #REF!
Name _DAT4: #REF!
Name _DAT5: #REF!
Name _DAT6: #REF!
Name _DAT7: #REF!
Name _DAT8: #REF!
Name _DAT9: #REF!
Name BRM_Total: '[1]Reference NLA '!#REF!
Name Controls: '[1]Reference NLA '!#REF!
Name ConversionList: #REF!
Name CPI: #REF!
Name DATA1: #REF!
Name DATA10: #REF!
Name DATA11: #REF!
Name DATA12: #REF!
Name DATA13: #REF!
Name DATA14: #REF!
Name DATA15: #REF!
Name DATA16: #REF!
Name DATA17: #REF!
Name DATA2: #REF!
Name DATA3: #REF!
Name DATA4: #REF!
Name DATA5: #REF!
Name DATA6: #REF!
Name DATA7: #REF!
Name DATA8: #REF!
Name DATA9: #REF!
Name dfhdhdhdhfd: #REF!
Name Display_Week: #REF!
Name IRR_: #REF!
Name IRR_Base: [2]MODEL!$G$4
Name IRR_Base: [3]MODEL!$G$4
Name MMBtu: #REF!
Name Names: #REF!
Name Options: '[1]Reference NLA '!#REF!
Name price_sens: [2]MODEL!$G$157
Name price_sens: [3]MODEL!$G$157
Name Project_Start: #REF!
Name ProjIRR: [4]Model!$D$80
Name s: #REF!
Name sfdsfsfdsfsfsd: #REF!
Name TeCO2: #REF!
Name TEST0: #REF!
Name TESTHKEY: #REF!
Name TESTKEYS: #REF!
Name TESTVKEY: #REF!
Name Unit_Table: #REF!
Name vol_sens: [2]MODEL!$G$156

Sheet INPUTS
L1: Proposal over Proposal Changes
E3: {=INDEX($G3:$N3,1,$E$4)} -> 70/90 Tiered 1250/$2.82 BID 11.21 | G3: =H3 -> 70/90 Tiered 1250/$2.82 BID 11.21 | H3: =I3 -> 70/90 Tiered 1250/$2.82 BID 11.21 | I3: =J3 -> 70/90 Tiered 1250/$2.82 BID 11.21 | J3: =K3 -> 70/90 Tiered 1250/$2.82 BID 11.21 | K3: 70/90 Tiered 1250/$2.82 BID 11.21 | L3: [Open] | M3: [Open]
C4: Scenario Selection --> | E4: 5 | G4: 1 | H4: 2 | I4: 3 | J4: 4 | K4: 5 | L4: 6 | M4: 7
C6: CPI Escalator | E6: 0.025
C8: Year 1 Biogas | D8: scfm | E8: {=INDEX($G8:$N8,1,$E$4)} -> 950 | G8: 950 | H8: 950 | I8: 950 | J8: 950 | K8: 950
C9: Annual CAGR | E9: {=INDEX($G9:$N9,1,$E$4)} -> 0.02434 | G9: 0.02434 | H9: 0.02434 | I9: 0.02434 | J9: 0.02434 | K9: 0.02434
C10: Year 20 (result) | D10: scfm | E10: =Model!AA11 -> 1500.2447
C12: Uptime | E12: {=INDEX($G12:$N12,1,$E$4)} -> 0.98 | G12: 0.98 | H12: 0.98 | I12: 0.98 | J12: 0.98 | K12: 0.98
C13: Capture | E13: {=INDEX($G13:$N13,1,$E$4)} -> 0.97906432 | G13: 0.97906432 | H13: 0.97906432 | I13: 0.97906432 | J13: 0.97906432 | K13: 0.97906432
C14: Btu/scf | E14: {=INDEX($G14:$N14,1,$E$4)} -> 666.68382 | G14: 666.68382 | H14: 666.68382 | I14: 666.68382 | J14: 666.68382 | K14: 666.68382
C16: Use Ares Curve? | E16: {=INDEX($G16:$N16,1,$E$4)} -> 1 | G16: 1 | H16: 1 | I16: 1 | J16: 1 | K16: 1
C17: D3 RIN | D17: $/RIN | E17: {=INDEX($G17:$N17,1,$E$4)} -> 2.39 | G17: 2.39 | H17: 2.39 | I17: 2.39 | J17: 2.39 | K17: 2.39
C18: RIN price escalator | E18: {=INDEX($G18:$N18,1,$E$4)} -> 0.01 | G18: 0.01 | H18: 0.01 | I18: 0.01 | J18: 0.01 | K18: 0.01
C19: Brokerage | E19: {=INDEX($G19:$N19,1,$E$4)} -> 0.2 | G19: 0.2 | H19: 0.2 | I19: 0.2 | J19: 0.2 | K19: 0.2
C21: Used Gas Curve? | E21: {=INDEX($G21:$N21,1,$E$4)} -> 1 | G21: 1 | H21: 1 | I21: 1 | J21: 1 | K21: 1
C22: Nat. Gas Year 1 Price | D22: $/MMBtu | E22: {=INDEX($G22:$N22,1,$E$4)} -> 3.0390412 | G22: 3.0390412 | H22: 3.0390412 | I22: 3.0390412 | J22: 3.0390412 | K22: 3.0390412
C23: Nat. Gas Price escalator | E23: {=INDEX($G23:$N23,1,$E$4)} -> 0.03 | G23: 0.03 | H23: 0.03 | I23: 0.03 | J23: 0.03 | K23: 0.03
C24: Wheel/hub cost | D24: $/MMBtu | E24: 1 | S24: =+E32 -> 36835
S25: =+Model!E38 -> 53083.042
C26: Min. Royalty | D26: $K | E26: {=INDEX($G26:$N26,1,$E$4)} -> 1000 | G26: 1000 | H26: 1000 | I26: 1000 | J26: 1000 | K26: 1000 | S26: =-Model!E59 -> 12369.017
S27: =SUM(S24:S26) -> 102287.06
C28: Base Royalty % | E28: {=INDEX($G28:$N28,1,$E$4)} -> 0.7 | G28: 0.7 | H28: 0.7 | I28: 0.7 | J28: 0.7 | K28: 0.7 | S28: =+S27/20 -> 5114.353
C29: Bonus Royalty % | E29: {=INDEX($G29:$N29,1,$E$4)} -> 0.9 | G29: 0.9 | H29: 0.9 | I29: 0.9 | J29: 0.9 | K29: 0.9
C30: Tier 2 RIN Trigger | E30: {=INDEX($G30:$N30,1,$E$4)} -> 2.82 | G30: 2.82 | H30: 2.82 | I30: 2.82 | J30: 2.82 | K30: 2.82
C31: Tier 2 SCFM Trigger | E31: {=INDEX($G31:$N31,1,$E$4)} -> 1250 | G31: 1250 | H31: 1250 | I31: 1250 | J31: 1250 | K31: 1250
C32: Capital Cost Allowance | E32: {=INDEX($G32:$N32,1,$E$4)} -> 36835 | G32: 36835 | H32: 36835 | I32: 36835 | J32: 36835 | K32: 36835
C33: Capital Cost Financing Fee | E33: {=INDEX($G33:$N33,1,$E$4)} -> 9208.75 | G33: 9208.75 | H33: 9208.75 | I33: 9208.75 | J33: 9208.75 | K33: 9208.75
C34: Opex and Maintenance Allowance | E34: {=INDEX($G34:$N34,1,$E$4)} -> 51911.25 | G34: 51911.25 | H34: 51911.25 | I34: 51911.25 | J34: 51911.25 | K34: 51911.25
C36: NTP Date | E36: 46203
C37: COD Date | D37: =YEAR(E37) -> 2027 | E37: =EOMONTH(E36,16) -> 46691
C38: Mid-construct | E38: =MEDIAN(E36:E37) -> 46447
C41: RIN/MMBtu | E41: 11.727
G43: =+G34-0.25*$E32 -> 42702.5 | H43: =+H34-0.25*$E32 -> 42702.5 | I43: =+I34-0.25*$E32 -> 42702.5 | J43: =+J34-0.25*$E32 -> 42702.5

Sheet Financial Summary
C1: =+INPUTS!E4 -> 5
B3: Nashville, $MM except noted | E3: TOTAL | G3: 1 | H3: 2 | I3: 3 | J3: 4 | K3: 5 | M3: 20
B4: Biogas Production | D4: scfm | G4: =+Model!H11 -> 950 | H4: =+Model!I11 -> 973.123 | I4: =+Model!J11 -> 996.80881 | J4: =+Model!K11 -> 1021.0711 | K4: =+Model!L11 -> 1045.924 | M4: =+Model!AA11 -> 1500.2447
B5: RNG Production | D5: K MMBtu | E5: =Model!E17/10^3 -> 8105 | G5: =+Model!H17/10^3 -> 319.40093 | H5: =+Model!I17/10^3 -> 327.17515 | I5: =+Model!J17/10^3 -> 335.13859 | J5: =+Model!K17/10^3 -> 343.29587 | K5: =+Model!L17/10^3 -> 351.65169 | M5: =+Model!AA17/10^3 -> 504.39955
B7: RIN EAs Value | E7: =+Model!E28/10^3 -> 299.56481 | G7: =+Model!H28/10^3 -> 9.9706695 | H7: =+Model!I28/10^3 -> 10.404666 | I7: =+Model!J28/10^3 -> 10.970997 | J7: =+Model!K28/10^3 -> 11.739648 | K7: =+Model!L28/10^3 -> 12.281462 | M7: =+Model!AA28/10^3 -> 21.754387
B8: (-) RIN Brokerage | E8: =+Model!E29/10^3 -> -59.912961 | G8: =+Model!H29/10^3 -> -1.9941339 | H8: =+Model!I29/10^3 -> -2.0809333 | I8: =+Model!J29/10^3 -> -2.1941993 | J8: =+Model!K29/10^3 -> -2.3479297 | K8: =+Model!L29/10^3 -> -2.4562924 | M8: =+Model!AA29/10^3 -> -4.3508775
B9: (+) Nat. Gas Sales | E9: =+Model!E30/10^3 -> 34.481019 | G9: =+Model!H30/10^3 -> 1.0648827 | H9: =+Model!I30/10^3 -> 1.0695356 | I9: =+Model!J30/10^3 -> 1.1258897 | J9: =+Model!K30/10^3 -> 1.1851301 | K9: =+Model!L30/10^3 -> 1.2474025 | M9: =+Model!AA30/10^3 -> 2.6704954
B10: Total Offtake Revenue | D10: $MM | E10: =SUM(E7:E9) -> 274.13286 | G10: =SUM(G7:G9) -> 9.0414183 | H10: =SUM(H7:H9) -> 9.3932687 | I10: =SUM(I7:I9) -> 9.9026871 | J10: =SUM(J7:J9) -> 10.576849 | K10: =SUM(K7:K9) -> 11.072572 | L10: =SUM(L7:L9) -> 0 | M10: =SUM(M7:M9) -> 20.074005
D11: $/MMBtu | E11: =+E10*10^3/E$5 -> 33.822685 | G11: =+G10*10^3/G$5 -> 28.307426 | H11: =+H10*10^3/H$5 -> 28.710214 | I11: =+I10*10^3/I$5 -> 29.548036 | J11: =+J10*10^3/J$5 -> 30.809718 | K11: =+K10*10^3/K$5 -> 31.487328 | M11: =+M10*10^3/M$5 -> 39.797826
B13: Utilities | E13: =+Model!E34/10^3 -> 17.416658 | G13: =+Model!H34/10^3 -> 0.52701154 | H13: =+Model!I34/10^3 -> 0.55333497 | I13: =+Model!J34/10^3 -> 0.58097323 | J13: =+Model!K34/10^3 -> 0.60999197 | K13: =+Model!L34/10^3 -> 0.64046015 | M13: =+Model!AA34/10^3 -> 1.3304914
B14: (+) Consumables / R&M | E14: =+Model!E35/10^3 -> 8.9722175 | G14: =+Model!H35/10^3 -> 0.27149079 | H14: =+Model!I35/10^3 -> 0.28505135 | I14: =+Model!J35/10^3 -> 0.29928924 | J14: =+Model!K35/10^3 -> 0.31423829 | K14: =+Model!L35/10^3 -> 0.32993402 | M14: =+Model!AA35/10^3 -> 0.68540466
B15: (+) Asset Management | E15: =+Model!E36/10^3 -> 5.1089315 | G15: =+Model!H36/10^3 -> 0.2 | H15: =+Model!I36/10^3 -> 0.205 | I15: =+Model!J36/10^3 -> 0.210125 | J15: =+Model!K36/10^3 -> 0.21537812 | K15: =+Model!L36/10^3 -> 0.22076258 | M15: =+Model!AA36/10^3 -> 0.31973004
B16: (+) Fixed Expenses | E16: =+Model!E37/10^3 -> 21.585236 | G16: =+Model!H37/10^3 -> 0.845 | H16: =+Model!I37/10^3 -> 0.866125 | I16: =+Model!J37/10^3 -> 0.88777812 | J16: =+Model!K37/10^3 -> 0.90997258 | K16: =+Model!L37/10^3 -> 0.93272189 | M16: =+Model!AA37/10^3 -> 1.3508594
B17: Total Operating Expenses | D17: $MM | E17: =+Model!E38/10^3 -> 53.083042 | G17: =SUM(G13:G16) -> 1.8435023 | H17: =SUM(H13:H16) -> 1.9095113 | I17: =SUM(I13:I16) -> 1.9781656 | J17: =SUM(J13:J16) -> 2.049581 | K17: =SUM(K13:K16) -> 2.1238786 | M17: =SUM(M13:M16) -> 3.6864855
D18: $/MMBtu | E18: =+E17*10^3/E$5 -> 6.5494192 | G18: =+G17*10^3/G$5 -> 5.77175 | H18: =+H17*10^3/H$5 -> 5.836358 | I18: =+I17*10^3/I$5 -> 5.90253 | J18: =+J17*10^3/J$5 -> 5.9703048 | K18: =+K17*10^3/K$5 -> 6.0397226 | M18: =+M17*10^3/M$5 -> 7.3086614
B20: Royalty Calculation | D20: MWS Share
B21: Base | D21: =+Model!D46 -> 0.7 | G21: =+Model!H45/10^3 -> 4.1436683 | H21: =+Model!I45/10^3 -> 4.4955187 | I21: =+Model!J45/10^3 -> 5.0049371 | J21: =+Model!K45/10^3 -> 5.6790988 | K21: =+Model!L45/10^3 -> 6.1748221 | M21: =+Model!AA45/10^3 -> 15.176255
B22: Bonus | D22: 0.9 | G22: =+Model!H50/10^3 -> 0 | H22: =+Model!I50/10^3 -> 0 | I22: =+Model!J50/10^3 -> 0 | J22: =+Model!K50/10^3 -> 0 | K22: =+Model!L50/10^3 -> 0 | M22: =+Model!AA50/10^3 -> 0.50628781
B23: Total Royalty to MWS | D23: $MM | E23: =+Model!D52/10^3 -> 125.28608 | G23: =MAX(2,SUMPRODUCT(G21:G22,$D$21:$D$22)) -> 2.9005678 | H23: =MAX(2,SUMPRODUCT(H21:H22,$D$21:$D$22)) -> 3.1468631 | I23: =MAX(2,SUMPRODUCT(I21:I22,$D$21:$D$22)) -> 3.503456 | J23: =MAX(2,SUMPRODUCT(J21:J22,$D$21:$D$22)) -> 3.9753692 | K23: =MAX(2,SUMPRODUCT(K21:K22,$D$21:$D$22)) -> 4.3223754 | M23: =SUMPRODUCT(M21:M22,$D$21:$D$22) -> 11.079038
D24: $/MMBtu | E24: =+E23*10^3/E$5 -> 15.457875 | G24: =+G23*10^3/G$5 -> 9.0812753 | H24: =+H23*10^3/H$5 -> 9.6182826 | I24: =+I23*10^3/I$5 -> 10.453753 | J24: =+J23*10^3/J$5 -> 11.580009 | K24: =+K23*10^3/K$5 -> 12.291639 | M24: =+M23*10^3/M$5 -> 21.964805
B26: EBITDA | E26: =Model!E58/10^3 -> 95.763745 | G26: =+G10-G17-G23 -> 4.2973482 | H26: =+H10-H17-H23 -> 4.3368943 | I26: =+I10-I17-I23 -> 4.4210655 | J26: =+J10-J17-J23 -> 4.5518987 | K26: =+K10-K17-K23 -> 4.626318 | M26: =+Model!AA58/10^3 -> 5.2578533
B27: Capex | E27: =Model!E57/10^3 -> -36.835
B28: ITC Proceeds | E28: =Model!E60/10^3 -> 12.96592
B29: Mtce Capex | E29: =Model!E59/10^3 -> -12.369017
B31: IRR | E31: =+Model!D63 -> 0.1511144
B32: Build Multiple, net of ITC | E32: =-SUM(E27:E28)/I26 -> 5.3989428

Sheet Model
C3: NTP Date | E3: 46203
H6: {=_xlfn.SEQUENCE(1,20,0,1)} -> 0 | I6: 1 | J6: 2 | K6: 3 | L6: 4 | M6: 5 | N6: 6 | O6: 7 | P6: 8 | Q6: 9 | R6: 10 | S6: 11 | T6: 12 | U6: 13 | V6: 14 | W6: 15 | X6: 16 | Y6: 17 | Z6: 18 | AA6: 19
C7: Case | D7: =+INPUTS!E4 -> 5 | H7: =YEAR(H9) -> 2028 | I7: =YEAR(I9) -> 2029 | J7: =YEAR(J9) -> 2030 | K7: =YEAR(K9) -> 2031 | L7: =YEAR(L9) -> 2032 | M7: =YEAR(M9) -> 2033 | N7: =YEAR(N9) -> 2034 | O7: =YEAR(O9) -> 2035 | ... AA7: =YEAR(AA9) -> 2047
C8: IRR | D8: =+D63 -> 0.1511144 | H8: 1 | I8: =H8*(1+INPUTS!$E$6) -> 1.025 | J8: =I8*(1+INPUTS!$E$6) -> 1.050625 | K8: =J8*(1+INPUTS!$E$6) -> 1.0768906 | L8: =K8*(1+INPUTS!$E$6) -> 1.1038129 | M8: =L8*(1+INPUTS!$E$6) -> 1.1314082 | N8: =M8*(1+INPUTS!$E$6) -> 1.1596934 | O8: =N8*(1+INPUTS!$E$6) -> 1.1886858 | P8: =O8*(1+INPUTS!$E$6) -> 1.2184029 | ... AA8: =Z8*(1+INPUTS!$E$6) -> 1.5986502
G9: =+INPUTS!E38 -> 46447 | H9: =EOMONTH(INPUTS!E37,6) -> 46873 | I9: =EOMONTH(H9,12) -> 47238 | J9: =EOMONTH(I9,12) -> 47603 | K9: =EOMONTH(J9,12) -> 47968 | L9: =EOMONTH(K9,12) -> 48334 | M9: =EOMONTH(L9,12) -> 48699 | N9: =EOMONTH(M9,12) -> 49064 | O9: =EOMONTH(N9,12) -> 49429 | P9: =EOMONTH(O9,12) -> 49795 | ... AA9: =EOMONTH(Z9,12) -> 53812
C10: $ in '000, except noted | G10: Year 0 | H10: Year 1 | I10: Year 2 | J10: Year 3 | K10: Year 4 | L10: Year 5 | M10: Year 6 | N10: Year 7 | O10: Year 8 | P10: Year 9 | Q10: Year 10 | R10: Year 11 | S10: Year 12 | T10: Year 13 | U10: Year 14 | V10: Year 15 | W10: Year 16 | X10: Year 17 | Y10: Year 18 | Z10: Year 19 | AA10: Year 20
C11: Biogas | D11: scfm | H11: =INPUTS!E8 -> 950 | I11: =H11*(1+INPUTS!$E$9) -> 973.123 | J11: =I11*(1+INPUTS!$E$9) -> 996.80881 | K11: =J11*(1+INPUTS!$E$9) -> 1021.0711 | L11: =K11*(1+INPUTS!$E$9) -> 1045.924 | M11: =L11*(1+INPUTS!$E$9) -> 1071.3818 | N11: =M11*(1+INPUTS!$E$9) -> 1097.4592 | O11: =N11*(1+INPUTS!$E$9) -> 1124.1714 | P11: =O11*(1+INPUTS!$E$9) -> 1151.5337 | ... AA11: =Z11*(1+INPUTS!$E$9) -> 1500.2447
C12: Biogas | D12: scf/d | H12: =H11*(24*60) -> 1368000 | I12: =I11*(24*60) -> 1401297.1 | J12: =J11*(24*60) -> 1435404.7 | K12: =K11*(24*60) -> 1470342.4 | L12: =L11*(24*60) -> 1506130.6 | M12: =M11*(24*60) -> 1542789.8 | N12: =N11*(24*60) -> 1580341.3 | O12: =O11*(24*60) -> 1618806.8 | ... AA12: =AA11*(24*60) -> 2160352.4
C13: Theor. RNG | D13: MMBtu/d | E13: =INPUTS!$E$14 -> 666.68382 | H13: =$E$13*H12/10^6 -> 912.02347 | I13: =$E$13*I12/10^6 -> 934.22212 | J13: =$E$13*J12/10^6 -> 956.96108 | K13: =$E$13*K12/10^6 -> 980.25352 | L13: =$E$13*L12/10^6 -> 1004.1129 | M13: =$E$13*M12/10^6 -> 1028.553 | N13: =$E$13*N12/10^6 -> 1053.588 | O13: =$E$13*O12/10^6 -> 1079.2323 | ... AA13: =$E$13*AA12/10^6 -> 1440.272
C14: Theor. RNG | D14: MMBtu | E14: =SUM(H14:AA14) -> 8447257.2 | H14: =H13*365 -> 332888.57 | I14: =I13*365 -> 340991.07 | J14: =J13*365 -> 349290.8 | K14: =K13*365 -> 357792.53 | L14: =L13*365 -> 366501.2 | M14: =M13*365 -> 375421.84 | N14: =N13*365 -> 384559.61 | O14: =O13*365 -> 393919.79 | ... AA14: =AA13*365 -> 525699.29
C15: Uptime | H15: =INPUTS!$E$12 -> 0.98 | I15: =H15 -> 0.98 | J15: =I15 -> 0.98 | K15: =J15 -> 0.98 | L15: =K15 -> 0.98 | M15: =L15 -> 0.98 | N15: =M15 -> 0.98 | O15: =N15 -> 0.98 | P15: =O15 -> 0.98 | ... AA15: =Z15 -> 0.98
C16: Capture | D16: mult.--> | E16: 1 | H16: =INPUTS!$E$13 -> 0.97906432 | I16: =H16 -> 0.97906432 | J16: =I16 -> 0.97906432 | K16: =J16 -> 0.97906432 | L16: =K16 -> 0.97906432 | M16: =L16 -> 0.97906432 | N16: =M16 -> 0.97906432 | O16: =N16 -> 0.97906432 | P16: =O16 -> 0.97906432 | ... AA16: =Z16 -> 0.97906432
C17: Net RNG Production | D17: MMBtu | E17: =SUM(H17:AA17) -> 8105000 | H17: =PRODUCT(H14:H16)*$E$16 -> 319400.93 | I17: =PRODUCT(I14:I16)*$E$16 -> 327175.15 | J17: =PRODUCT(J14:J16)*$E$16 -> 335138.59 | K17: =PRODUCT(K14:K16)*$E$16 -> 343295.87 | L17: =PRODUCT(L14:L16)*$E$16 -> 351651.69 | M17: =PRODUCT(M14:M16)*$E$16 -> 360210.89 | N17: =PRODUCT(N14:N16)*$E$16 -> 368978.42 | O17: =PRODUCT(O14:O16)*$E$16 -> 377959.36 | ... AA17: =PRODUCT(AA14:AA16)*$E$16 -> 504399.55
B19: =INPUTS!E16 -> 1 | C19: Ares Curve D3 RIN | D19: adder--> | E19: 0 | H19: =_xlfn.XLOOKUP(H7,'RIN Curves'!$G$18:$G$44,'RIN Curves'!$H$18:$H$44)+$E$19 -> 2.6619581 | I19: =_xlfn.XLOOKUP(I7,'RIN Curves'!$G$18:$G$44,'RIN Curves'!$H$18:$H$44)+$E$19 -> 2.7118204 | J19: =_xlfn.XLOOKUP(J7,'RIN Curves'!$G$18:$G$44,'RIN Curves'!$H$18:$H$44)+$E$19 -> 2.7914813 | K19: =_xlfn.XLOOKUP(K7,'RIN Curves'!$G$18:$G$44,'RIN Curves'!$H$18:$H$44)+$E$19 -> 2.9160811 | L19: =_xlfn.XLOOKUP(L7,'RIN Curves'!$G$18:$G$44,'RIN Curves'!$H$18:$H$44)+$E$19 -> 2.9781765 | M19: =_xlfn.XLOOKUP(M7,'RIN Curves'!$G$18:$G$44,'RIN Curves'!$H$18:$H$44)+$E$19 -> 2.9101359 | N19: =_xlfn.XLOOKUP(N7,'RIN Curves'!$G$18:$G$44,'RIN Curves'!$H$18:$H$44)+$E$19 -> 2.8799224 | O19: =_xlfn.XLOOKUP(O7,'RIN Curves'!$G$18:$G$44,'RIN Curves'!$H$18:$H$44)+$E$19 -> 2.8742294 | ... AA19: =_xlfn.XLOOKUP(AA7,'RIN Curves'!$G$18:$G$44,'RIN Curves'!$H$18:$H$44)+$E$19 -> 3.6777758
C20: D3 RIN | D20: $/RIN | E20: =INPUTS!$E$17+$E$19 -> 2.39 | H20: =IF($B$19=0,E20,H19) -> 2.6619581 | I20: =IF($B$19=0,H20*(1+INPUTS!$E$18),I19) -> 2.7118204 | J20: =IF($B$19=0,I20*(1+INPUTS!$E$18),J19) -> 2.7914813 | K20: =IF($B$19=0,J20*(1+INPUTS!$E$18),K19) -> 2.9160811 | L20: =IF($B$19=0,K20*(1+INPUTS!$E$18),L19) -> 2.9781765 | M20: =IF($B$19=0,L20*(1+INPUTS!$E$18),M19) -> 2.9101359 | N20: =IF($B$19=0,M20*(1+INPUTS!$E$18),N19) -> 2.8799224 | O20: =IF($B$19=0,N20*(1+INPUTS!$E$18),O19) -> 2.8742294 | P20: =IF($B$19=0,O20*(1+INPUTS!$E$18),P19) -> 2.9338872 | ... AA20: =IF($B$19=0,Z20*(1+INPUTS!$E$18),AA19) -> 3.6777758
C21: D3 RIN | D21: $/MMBtu | H21: =H20*INPUTS!$E$41 -> 31.216783 | I21: =I20*INPUTS!$E$41 -> 31.801518 | J21: =J20*INPUTS!$E$41 -> 32.735701 | K21: =K20*INPUTS!$E$41 -> 34.196883 | L21: =L20*INPUTS!$E$41 -> 34.925076 | M21: =M20*INPUTS!$E$41 -> 34.127163 | N21: =N20*INPUTS!$E$41 -> 33.77285 | O21: =O20*INPUTS!$E$41 -> 33.706088 | ... AA21: =AA20*INPUTS!$E$41 -> 43.129276
B23: =+INPUTS!E21 -> 1 | C23: Nat. Gas Curve | H23: =_xlfn.XLOOKUP(H$7,HenryHub!$B$28:$B$52,HenryHub!$E$28:$E$52) -> 4.334 | I23: =_xlfn.XLOOKUP(I$7,HenryHub!$B$28:$B$52,HenryHub!$E$28:$E$52) -> 4.269 | J23: =_xlfn.XLOOKUP(J$7,HenryHub!$B$28:$B$52,HenryHub!$E$28:$E$52) -> 4.359475 | K23: =_xlfn.XLOOKUP(K$7,HenryHub!$B$28:$B$52,HenryHub!$E$28:$E$52) -> 4.4522119 | L23: =_xlfn.XLOOKUP(L$7,HenryHub!$B$28:$B$52,HenryHub!$E$28:$E$52) -> 4.5472672 | M23: =_xlfn.XLOOKUP(M$7,HenryHub!$B$28:$B$52,HenryHub!$E$28:$E$52) -> 4.6446989 | N23: =_xlfn.XLOOKUP(N$7,HenryHub!$B$28:$B$52,HenryHub!$E$28:$E$52) -> 4.7445663 | O23: =_xlfn.XLOOKUP(O$7,HenryHub!$B$28:$B$52,HenryHub!$E$28:$E$52) -> 4.8469305 | ... AA23: =_xlfn.XLOOKUP(AA$7,HenryHub!$B$28:$B$52,HenryHub!$E$28:$E$52) -> 6.2944049
C24: Nat. Gas | D24: $/MMBtu | E24: =INPUTS!E23 -> 0.03 | H24: =IF($B$23=1,H23,INPUTS!$E$22*(1+$E$24)^H6) -> 4.334 | I24: =IF($B$23=1,I23,INPUTS!$E$22*(1+$E$24)^I6) -> 4.269 | J24: =IF($B$23=1,J23,INPUTS!$E$22*(1+$E$24)^J6) -> 4.359475 | K24: =IF($B$23=1,K23,INPUTS!$E$22*(1+$E$24)^K6) -> 4.4522119 | L24: =IF($B$23=1,L23,INPUTS!$E$22*(1+$E$24)^L6) -> 4.5472672 | M24: =IF($B$23=1,M23,INPUTS!$E$22*(1+$E$24)^M6) -> 4.6446989 | N24: =IF($B$23=1,N23,INPUTS!$E$22*(1+$E$24)^N6) -> 4.7445663 | O24: =IF($B$23=1,O23,INPUTS!$E$22*(1+$E$24)^O6) -> 4.8469305 | ... AA24: =IF($B$23=1,AA23,INPUTS!$E$22*(1+$E$24)^AA6) -> 6.2944049
C25: (-) Wheel/hub cost | D25: $/MMBtu | H25: =-INPUTS!$E$24 -> -1 | I25: =H25 -> -1 | J25: =I25 -> -1 | K25: =J25 -> -1 | L25: =K25 -> -1 | M25: =L25 -> -1 | N25: =M25 -> -1 | O25: =N25 -> -1 | P25: =O25 -> -1 | ... AA25: =Z25 -> -1
C27: Offtake Revenue | E27: =E28+E30 -> 334045.83
C28: RIN Value | E28: =+SUM(H28:AA28) -> 299564.81 | H28: =+H21*H$17/10^3 -> 9970.6695 | I28: =+I21*I$17/10^3 -> 10404.666 | J28: =+J21*J$17/10^3 -> 10970.997 | K28: =+K21*K$17/10^3 -> 11739.648 | L28: =+L21*L$17/10^3 -> 12281.462 | M28: =+M21*M$17/10^3 -> 12292.976 | N28: =+N21*N$17/10^3 -> 12461.453 | O28: =+O21*O$17/10^3 -> 12739.531 | ... AA28: =+AA21*AA$17/10^3 -> 21754.387
B29: =INPUTS!E19 -> 0.2 | C29: (-) RIN Brokerage | E29: =+SUM(H29:AA29) -> -59912.961 | H29: =-$B$29*H28 -> -1994.1339 | I29: =-$B$29*I28 -> -2080.9333 | J29: =-$B$29*J28 -> -2194.1993 | K29: =-$B$29*K28 -> -2347.9297 | L29: =-$B$29*L28 -> -2456.2924 | M29: =-$B$29*M28 -> -2458.5952 | N29: =-$B$29*N28 -> -2492.2906 | O29: =-$B$29*O28 -> -2547.9062 | ... AA29: =-$B$29*AA28 -> -4350.8775
C30: (+) Nat Gas Value | E30: =+SUM(H30:AA30) -> 34481.019 | H30: =SUM(H24:H25)*H17/10^3 -> 1064.8827 | I30: =SUM(I24:I25)*I17/10^3 -> 1069.5356 | J30: =SUM(J24:J25)*J17/10^3 -> 1125.8897 | K30: =SUM(K24:K25)*K17/10^3 -> 1185.1301 | L30: =SUM(L24:L25)*L17/10^3 -> 1247.4025 | M30: =SUM(M24:M25)*M17/10^3 -> 1312.8602 | N30: =SUM(N24:N25)*N17/10^3 -> 1381.6642 | O30: =SUM(O24:O25)*O17/10^3 -> 1453.9834 | ... AA30: =SUM(AA24:AA25)*AA17/10^3 -> 2670.4954
C31: Net Offtake Revenue | E31: =+SUM(H31:AA31) -> 274132.86 | H31: =SUM(H28:H30) -> 9041.4183 | I31: =SUM(I28:I30) -> 9393.2687 | J31: =SUM(J28:J30) -> 9902.6871 | K31: =SUM(K28:K30) -> 10576.849 | L31: =SUM(L28:L30) -> 11072.572 | M31: =SUM(M28:M30) -> 11147.241 | N31: =SUM(N28:N30) -> 11350.826 | O31: =SUM(O28:O30) -> 11645.608 | ... AA31: =SUM(AA28:AA30) -> 20074.005
C33: Operating Expenses
B34: 1.65 | C34: Utilities | E34: =SUM(H34:AA34) -> 17416.658 | H34: =+$B34*H$8*H$17/10^3 -> 527.01154 | I34: =+$B$34*I8*I17/10^3 -> 553.33497 | J34: =+$B$34*J8*J17/10^3 -> 580.97323 | K34: =+$B$34*K8*K17/10^3 -> 609.99197 | L34: =+$B$34*L8*L17/10^3 -> 640.46015 | M34: =+$B$34*M8*M17/10^3 -> 672.45017 | N34: =+$B$34*N8*N17/10^3 -> 706.03805 | O34: =+$B$34*O8*O17/10^3 -> 741.30359 | P34: =+$B$34*P8*P17/10^3 -> 778.3306 | ... AA34: =+$B$34*AA8*AA17/10^3 -> 1330.4914
B35: 0.85 | C35: (+) Consumables / R&M | E35: =SUM(H35:AA35) -> 8972.2175 | H35: =+$B35*H$8*H$17/10^3 -> 271.49079 | I35: =+$B35*I$8*I$17/10^3 -> 285.05135 | J35: =+$B35*J$8*J$17/10^3 -> 299.28924 | K35: =+$B35*K$8*K$17/10^3 -> 314.23829 | L35: =+$B35*L$8*L$17/10^3 -> 329.93402 | M35: =+$B35*M$8*M$17/10^3 -> 346.41373 | N35: =+$B35*N$8*N$17/10^3 -> 363.71657 | O35: =+$B35*O$8*O$17/10^3 -> 381.88367 | ... AA35: =+$B35*AA$8*AA$17/10^3 -> 685.40466
B36: 200 | C36: (+) Asset Management | E36: =SUM(H36:AA36) -> 5108.9315 | H36: =+$B36*H$8 -> 200 | I36: =+$B36*I$8 -> 205 | J36: =+$B36*J$8 -> 210.125 | K36: =+$B36*K$8 -> 215.37812 | L36: =+$B36*L$8 -> 220.76258 | M36: =+$B36*M$8 -> 226.28164 | N36: =+$B36*N$8 -> 231.93868 | O36: =+$B36*O$8 -> 237.73715 | ... AA36: =+$B36*AA$8 -> 319.73004
B37: 845 | C37: (+) Fixed Expenses | E37: =SUM(H37:AA37) -> 21585.236 | H37: =+$B37*H$8 -> 845 | I37: =+$B37*I$8 -> 866.125 | J37: =+$B37*J$8 -> 887.77812 | K37: =+$B37*K$8 -> 909.97258 | L37: =+$B37*L$8 -> 932.72189 | M37: =+$B37*M$8 -> 956.03994 | N37: =+$B37*N$8 -> 979.94094 | O37: =+$B37*O$8 -> 1004.4395 | ... AA37: =+$B37*AA$8 -> 1350.8594
C38: TOTAL | E38: =SUM(H38:AA38) -> 53083.042 | H38: =SUM(H34:H37) -> 1843.5023 | I38: =SUM(I34:I37) -> 1909.5113 | J38: =SUM(J34:J37) -> 1978.1656 | K38: =SUM(K34:K37) -> 2049.581 | L38: =SUM(L34:L37) -> 2123.8786 | M38: =SUM(M34:M37) -> 2201.1855 | N38: =SUM(N34:N37) -> 2281.6342 | O38: =SUM(O34:O37) -> 2365.3639 | ... AA38: =SUM(AA34:AA37) -> 3686.4855
E39: =E38*1000/E17 -> 6.5494192 | H39: =H38*1000/H17 -> 5.77175 | I39: =I38*1000/I17 -> 5.836358 | J39: =J38*1000/J17 -> 5.90253 | K39: =K38*1000/K17 -> 5.9703048 | L39: =L38*1000/L17 -> 6.0397226 | M39: =M38*1000/M17 -> 6.1108244 | N39: =N38*1000/N17 -> 6.1836522 | O39: =O38*1000/O17 -> 6.2582493 | ... AA39: =AA38*1000/AA17 -> 7.3086614
C40: Royalty Calculation
C41: Offtake Revenue, net of brokerage | E41: =SUM(H41:AA41) -> 274132.86 | H41: =+H31 -> 9041.4183 | I41: =+I31 -> 9393.2687 | J41: =+J31 -> 9902.6871 | K41: =+K31 -> 10576.849 | L41: =+L31 -> 11072.572 | M41: =+M31 -> 11147.241 | N41: =+N31 -> 11350.826 | O41: =+O31 -> 11645.608 | ... AA41: =+AA31 -> 20074.005
C42: (-) Capex Allowance | D42: =+INPUTS!E32 -> 36835 | H42: =-$D$42/20 -> -1841.75 | I42: =-$D$42/20 -> -1841.75 | J42: =-$D$42/20 -> -1841.75 | K42: =-$D$42/20 -> -1841.75 | L42: =-$D$42/20 -> -1841.75 | M42: =-$D$42/20 -> -1841.75 | N42: =-$D$42/20 -> -1841.75 | O42: =-$D$42/20 -> -1841.75 | ... AA42: =-$D$42/20 -> -1841.75
C43: (-) Capital Cost Financing Fee | D43: =+INPUTS!E33 -> 9208.75 | H43: =-$D$43/20 -> -460.4375 | I43: =-$D$43/20 -> -460.4375 | J43: =-$D$43/20 -> -460.4375 | K43: =-$D$43/20 -> -460.4375 | L43: =-$D$43/20 -> -460.4375 | M43: =-$D$43/20 -> -460.4375 | N43: =-$D$43/20 -> -460.4375 | O43: =-$D$43/20 -> -460.4375 | ... AA43: =-$D$43/20 -> -460.4375
C44: (-) Opex and Maintenance Allowance | D44: =+INPUTS!E34 -> 51911.25 | H44: =-$D$44/20 -> -2595.5625 | I44: =-$D$44/20 -> -2595.5625 | J44: =-$D$44/20 -> -2595.5625 | K44: =-$D$44/20 -> -2595.5625 | L44: =-$D$44/20 -> -2595.5625 | M44: =-$D$44/20 -> -2595.5625 | N44: =-$D$44/20 -> -2595.5625 | O44: =-$D$44/20 -> -2595.5625 | ... AA44: =-$D$44/20 -> -2595.5625
C45: Net Avail. For Royalty | D45: =+SUM(D42:D44) -> 97955 | H45: =SUM(H41:H44) -> 4143.6683 | I45: =SUM(I41:I44) -> 4495.5187 | J45: =SUM(J41:J44) -> 5004.9371 | K45: =SUM(K41:K44) -> 5679.0988 | L45: =SUM(L41:L44) -> 6174.8221 | M45: =SUM(M41:M44) -> 6249.4909 | N45: =SUM(N41:N44) -> 6453.0765 | O45: =SUM(O41:O44) -> 6747.8584 | ... AA45: =SUM(AA41:AA44) -> 15176.255
C46: (x) % Base Royalty | D46: =+INPUTS!$E$28 -> 0.7 | E46: =+INPUTS!E26 -> 1000 | H46: =+$D$46 -> 0.7 | I46: =+$D$46 -> 0.7 | J46: =+$D$46 -> 0.7 | K46: =+$D$46 -> 0.7 | L46: =+$D$46 -> 0.7 | M46: =+$D$46 -> 0.7 | N46: =+$D$46 -> 0.7 | O46: =+$D$46 -> 0.7 | ... AA46: =+$D$46 -> 0.7
C47: Minimum or Base Royalty Amount | D47: =SUM(H47:AA47) -> 123324.51 | H47: =+MAX($E$46,H46*H45) -> 2900.5678 | I47: =+MAX($E$46,I46*I45) -> 3146.8631 | J47: =+MAX($E$46,J46*J45) -> 3503.456 | K47: =+MAX($E$46,K46*K45) -> 3975.3692 | L47: =+MAX($E$46,L46*L45) -> 4322.3754 | M47: =+MAX($E$46,M46*M45) -> 4374.6436 | N47: =+MAX($E$46,N46*N45) -> 4517.1535 | O47: =+MAX($E$46,O46*O45) -> 4723.5009 | ... AA47: =+MAX($E$46,AA46*AA45) -> 10623.379
C49: Eligible for Bonus Royalty | D49: =+INPUTS!E31 -> 1250 | E49: =+INPUTS!$E$30 -> 2.82 | H49: =IF(AND(H$11>$D$49,H$19>$E$49),1,0) -> 0 | I49: =IF(AND(I$11>$D$49,I$19>$E$49),1,0) -> 0 | J49: =IF(AND(J$11>$D$49,J$19>$E$49),1,0) -> 0 | K49: =IF(AND(K$11>$D$49,K$19>$E$49),1,0) -> 0 | L49: =IF(AND(L$11>$D$49,L$19>$E$49),1,0) -> 0 | M49: =IF(AND(M$11>$D$49,M$19>$E$49),1,0) -> 0 | N49: =IF(AND(N$11>$D$49,N$19>$E$49),1,0) -> 0 | O49: =IF(AND(O$11>$D$49,O$19>$E$49),1,0) -> 0 | ... AA49: =IF(AND(AA$11>$D$49,AA$19>$E$49),1,0) -> 1
C50: Bonus Royalty | D50: =+INPUTS!$E$29 -> 0.9 | H50: =+H49*(H45*($D$50-$D$46)*((H$11-$D$49)/$D$49)) -> 0 | I50: =+I49*(I45*($D$50-$D$46)*((I$11-$D$49)/I$11)) -> 0 | J50: =+J49*(J45*($D$50-$D$46)*((J$11-$D$49)/J$11)) -> 0 | K50: =+K49*(K45*($D$50-$D$46)*((K$11-$D$49)/K$11)) -> 0 | L50: =+L49*(L45*($D$50-$D$46)*((L$11-$D$49)/L$11)) -> 0 | M50: =+M49*(M45*($D$50-$D$46)*((M$11-$D$49)/M$11)) -> 0 | N50: =+N49*(N45*($D$50-$D$46)*((N$11-$D$49)/N$11)) -> 0 | O50: =+O49*(O45*($D$50-$D$46)*((O$11-$D$49)/O$11)) -> 0 | P50: =+P49*(P45*($D$50-$D$46)*((P$11-$D$49)/P$11)) -> 0 | ... AA50: =+AA49*(AA45*($D$50-$D$46)*((AA$11-$D$49)/AA$11)) -> 506.28781
C52: Total Royalty | D52: =+SUM(H52:AA52) -> 125286.08 | H52: =+H47+H50 -> 2900.5678 | I52: =+I47+I50 -> 3146.8631 | J52: =+J47+J50 -> 3503.456 | K52: =+K47+K50 -> 3975.3692 | L52: =+L47+L50 -> 4322.3754 | M52: =+M47+M50 -> 4374.6436 | N52: =+N47+N50 -> 4517.1535 | O52: =+O47+O50 -> 4723.5009 | ... AA52: =+AA47+AA50 -> 11129.667
C53: Effective Royalty % | H53: =+H52/H45 -> 0.7 | I53: =+I52/I45 -> 0.7 | J53: =+J52/J45 -> 0.7 | K53: =+K52/K45 -> 0.7 | L53: =+L52/L45 -> 0.7 | M53: =+M52/M45 -> 0.7 | N53: =+N52/N45 -> 0.7 | O53: =+O52/O45 -> 0.7 | ... AA53: =+AA52/AA45 -> 0.73336052
B55: IRR Calc Below: | E55: =-E59+E38 -> 65452.06
C56: Cash Flow | D56: mult.
B57: =+INPUTS!E32/10^3*$D$57 -> 36.835 | C57: Capex | D57: 1 | E57: =SUM(G57:AA57) -> -36835 | G57: =-B57*85%*10^3 -> -31309.75 | H57: =-B57*10^3-G57 -> -5525.25
C58: (+) EBITDA | E58: =SUM(G58:AA58) -> 95763.745 | H58: =+H31-SUM(H38,H52) -> 4297.3482 | I58: =+I31-SUM(I38,I52) -> 4336.8943 | J58: =+J31-SUM(J38,J52) -> 4421.0655 | K58: =+K31-SUM(K38,K52) -> 4551.8987 | L58: =+L31-SUM(L38,L52) -> 4626.318 | M58: =+M31-SUM(M38,M52) -> 4571.4118 | N58: =+N31-SUM(N38,N52) -> 4552.0387 | O58: =+O31-SUM(O38,O52) -> 4556.7436 | ... AA58: =+AA31-SUM(AA38,AA52) -> 5257.8533
B59: 0.015 | C59: (-) Mtce Capex | E59: =SUM(G59:AA59) -> -12369.017 | J59: =+$B$59*SUM(G57:H57) -> -552.525 | K59: =J59*(1+INPUTS!$E$6) -> -566.33812 | L59: =K59*(1+INPUTS!$E$6) -> -580.49658 | M59: =L59*(1+INPUTS!$E$6) -> -595.00899 | N59: =M59*(1+INPUTS!$E$6) -> -609.88422 | O59: =N59*(1+INPUTS!$E$6) -> -625.13132 | P59: =O59*(1+INPUTS!$E$6) -> -640.75961 | Q59: =P59*(1+INPUTS!$E$6) -> -656.7786 | R59: =Q59*(1+INPUTS!$E$6) -> -673.19806 | ... AA59: =Z59*(1+INPUTS!$E$6) -> -840.73213
B60: 0.352 | C60: (+) ITC | E60: =SUM(G60:AA60) -> 12965.92 | H60: =$B$60*B57*10^3 -> 12965.92
C61: TOTAL | E61: =SUM(E57:E60) -> 59525.648 | G61: =SUM(G57:G60) -> -31309.75 | H61: =SUM(H57:H60) -> 11738.018 | I61: =SUM(I57:I60) -> 4336.8943 | J61: =SUM(J57:J60) -> 3868.5405 | K61: =SUM(K57:K60) -> 3985.5606 | L61: =SUM(L57:L60) -> 4045.8214 | M61: =SUM(M57:M60) -> 3976.4028 | N61: =SUM(N57:N60) -> 3942.1545 | ... AA61: =SUM(AA57:AA60) -> 4417.1212
C63: IRR | D63: =XIRR(G61:AA61,$G$9:$AA$9) -> 0.1511144
B66: City Self-Perform Worksheet Below:
C67: City's Self-perform Economics | E67: TOTAL | G67: =+G10 -> Year 0 | H67: =+H10 -> Year 1 | I67: =+I10 -> Year 2 | J67: =+J10 -> Year 3 | K67: =+K10 -> Year 4 | L67: =+L10 -> Year 5 | M67: =+M10 -> Year 6 | N67: =+N10 -> Year 7 | ... AA67: =+AA10 -> Year 20
C68: ='Bid Forms'!C5 -> 20- year Evaluative Value of the sale of RNG and EAs | E68: =SUM(G68:AA68) -> 334045.83 | G68: =+G31 -> 0 | H68: =+H31-H29 -> 11035.552 | I68: =+I31-I29 -> 11474.202 | J68: =+J31-J29 -> 12096.886 | K68: =+K31-K29 -> 12924.779 | L68: =+L31-L29 -> 13528.864 | M68: =+M31-M29 -> 13605.836 | N68: =+N31-N29 -> 13843.117 | O68: =+O31-O29 -> 14193.515 | ... AA68: =+AA31-AA29 -> 24424.883
C69: ="(-)"&'Bid Forms'!C9 -> (-)20-year Allowance for RIN Management | E69: =SUM(G69:AA69) -> -59912.961 | H69: =H29 -> -1994.1339 | I69: =I29 -> -2080.9333 | J69: =J29 -> -2194.1993 | K69: =K29 -> -2347.9297 | L69: =L29 -> -2456.2924 | M69: =M29 -> -2458.5952 | N69: =N29 -> -2492.2906 | O69: =O29 -> -2547.9062 | ... AA69: =AA29 -> -4350.8775
C70: ="(-)"&'Bid Forms'!C8 -> (-)20-year Allowance for Operations and Maintenance | E70: -45000 | H70: =-H38 -> -1843.5023 | I70: =-I38 -> -1909.5113 | J70: =-J38 -> -1978.1656 | K70: =-K38 -> -2049.581 | L70: =-L38 -> -2123.8786 | M70: =-M38 -> -2201.1855 | N70: =-N38 -> -2281.6342 | O70: =-O38 -> -2365.3639 | ... AA70: =-AA38 -> -3686.4855
C71: (=) EBITDA | E71: =SUM(E68:E70) -> 229132.86 | H71: =SUM(H68:H70) -> 7197.916 | I71: =SUM(I68:I70) -> 7483.7573 | J71: =SUM(J68:J70) -> 7924.5215 | K71: =SUM(K68:K70) -> 8527.2679 | L71: =SUM(L68:L70) -> 8948.6934 | M71: =SUM(M68:M70) -> 8946.0554 | N71: =SUM(N68:N70) -> 9069.1922 | O71: =SUM(O68:O70) -> 9280.2445 | ... AA71: =SUM(AA68:AA70) -> 16387.52
C72: (-) Capex | D72: 37 | E72: =SUM(G72:AA72) -> -37000 | G72: =-D72*1000 -> -37000
C73: (-) Mtce Capex | D73: 0.015 | E73: =SUM(G73:AA73) -> -13290.034 | H73: 0 | I73: =+$D$73*$G$72*H8 -> -555 | J73: =+$D$73*$G$72*I8 -> -568.875 | K73: =+$D$73*$G$72*J8 -> -583.09687 | L73: =+$D$73*$G$72*K8 -> -597.6743 | M73: =+$D$73*$G$72*L8 -> -612.61615 | N73: =+$D$73*$G$72*M8 -> -627.93156 | O73: =+$D$73*$G$72*N8 -> -643.62985 | P73: =+$D$73*$G$72*O8 -> -659.72059 | ... AA73: =+$D$73*$G$72*Z8 -> -865.61059
C74: (-) Interest | D74: 0.04 | E74: =SUM(G74:AA74) -> -29600 | H74: =$D$74*$G$72 -> -1480 | I74: =$D$74*$G$72 -> -1480 | J74: =$D$74*$G$72 -> -1480 | K74: =$D$74*$G$72 -> -1480 | L74: =$D$74*$G$72 -> -1480 | M74: =$D$74*$G$72 -> -1480 | N74: =$D$74*$G$72 -> -1480 | O74: =$D$74*$G$72 -> -1480 | ... AA74: =$D$74*$G$72 -> -1480
C75: Total Evaluative Contract Value to Metro Water Services | E75: =SUM(E71:E74) -> 149242.83 | G75: =SUM(G71:G74) -> -37000 | H75: =SUM(H71:H74) -> 5717.916 | I75: =SUM(I71:I74) -> 5448.7573 | J75: =SUM(J71:J74) -> 5875.6465 | K75: =SUM(K71:K74) -> 6464.171 | L75: =SUM(L71:L74) -> 6871.0191 | M75: =SUM(M71:M74) -> 6853.4392 | N75: =SUM(N71:N74) -> 6961.2607 | ... AA75: =SUM(AA71:AA74) -> 14041.909
B77: Sensitivities Below:
I79: Capex ($MM) | O79: 20-yr RNG Prod'n, K MMBtu
I80: =+I81*INPUTS!$E$32/10^3 -> 33.1515 | J80: =+J81*INPUTS!$E$32/10^3 -> 36.835 | K80: =+K81*INPUTS!$E$32/10^3 -> 39.751554 | L80: =+L81*INPUTS!$E$32/10^3 -> 44.202 | O80: =+O81*$E$17/10^3 -> 7294.5 | P80: =+P81*$E$17/10^3 -> 8105 | Q80: =+Q81*$E$17/10^3 -> 8915.5 | R80: =+R81*$E$17/10^3 -> 9939.5155
H81: =+D63 -> 0.1511144 | I81: 0.9 | J81: 1 | K81: =36.8/34.1 -> 1.0791789 | L81: 1.2 | N81: =+$D$63 -> 0.1511144 | O81: 0.9 | P81: 1 | Q81: 1.1 | R81: =8.1/6.605 -> 1.2263437
D82: 1 | G82: =+H82+INPUTS!$E$17 -> 1.89 | H82: -0.5 | I82: 0.14891647 | J82: 0.12976225 | K82: 0.11654599 | L82: 0.098913175 | M82: =+N82+INPUTS!$E$17 -> 1.89 | N82: -0.5 | O82: 0.12154996 | P82: 0.12976225 | Q82: 0.1377178 | R82: 0.14744803
D83: =+D82+5% -> 1.05 | G83: =+H83+INPUTS!$E$17 -> 2.14 | H83: -0.25 | I83: 0.16027824 | J83: 0.14051072 | K83: 0.12690397 | L83: 0.10879722 | M83: =+N83+INPUTS!$E$17 -> 2.14 | N83: -0.25 | O83: 0.13152506 | P83: 0.14051072 | Q83: 0.14922051 | R83: 0.15988153
D84: =+D83+5% -> 1.1 | G84: =+H84+INPUTS!$E$17 -> 2.39 | H84: 0 | I84: 0.1714941 | J84: 0.1511144 | K84: 0.13711665 | L84: 0.11853326 | M84: =+N84+INPUTS!$E$17 -> 2.39 | N84: 0 | O84: 0.14136239 | P84: 0.1511144 | Q84: 0.16057078 | R84: 0.17215241
D85: =+D84+5% -> 1.15 | G85: =+H85+INPUTS!$E$17 -> 2.64 | H85: 0.25 | I85: 0.18241888 | J85: 0.16141647 | K85: 0.14701923 | L85: 0.12794594 | M85: =+N85+INPUTS!$E$17 -> 2.64 | N85: 0.25 | O85: 0.15091775 | P85: 0.16141647 | Q85: 0.17160197 | R85: 0.18408481
D86: =+D85+5% -> 1.2 | G86: =+H86+INPUTS!$E$17 -> 2.89 | H86: 0.5 | I86: 0.19308921 | J86: 0.17145528 | K86: 0.15665147 | L86: 0.13707728 | M86: =+N86+INPUTS!$E$17 -> 2.8150215 | N86: 0.42502155 | O86: 0.15745834 | P86: 0.16847014 | Q86: 0.17915758 | R86: 0.19226196
D87: =+D86+5% -> 1.25 | G87: =+H87+INPUTS!$E$17 -> 3.14 | H87: 0.75 | I87: 0.20353531 | J87: 0.18126249 | K87: 0.1660461 | L87: 0.14596173 | M87: =+N87+INPUTS!$E$17 -> 3.14 | N87: 0.75 | O87: 0.1693153 | P87: 0.18126249 | Q87: 0.19286675 | R87: 0.20710861
D88: =+D87+5% -> 1.3
D89: =+D88+5% -> 1.35 | O89: 20-yr RNG Prod'n, K MMBtu
D90: =+D89+5% -> 1.4 | O90: =+O91*$E$17/10^3 -> 7294.5 | P90: =+P91*$E$17/10^3 -> 8105 | Q90: =+Q91*$E$17/10^3 -> 8915.5 | R90: =+R91*$E$17/10^3 -> 9939.5155
D91: =+D90+5% -> 1.45 | N91: =+D52/1000 -> 125.28608 | O91: 0.9 | P91: 1 | Q91: 1.1 | R91: =8.1/6.605 -> 1.2263437
D92: =+D91+5% -> 1.5 | N92: -0.5 | O92: 81.415722 | P92: 98.148792 | Q92: 114.88186 | R92: 136.02304
D93: =+D92+5% -> 1.55 | N93: -0.25 | O93: 93.70334 | P93: 111.81388 | Q93: 129.92441 | R93: 152.80593
D94: =+D93+5% -> 1.6 | N94: 0 | O94: 105.82832 | P94: 125.28608 | Q94: 144.74383 | R94: 169.32748
D95: =+D94+5% -> 1.65 | N95: 0.25 | O95: 117.9533 | P95: 138.75828 | Q95: 159.56325 | R95: 185.84903
D96: =+D95+5% -> 1.7 | N96: 0.47035284 | O96: 128.6404 | P96: 150.63283 | Q96: 172.62526 | R96: 200.41131
N97: 0.75 | O97: 142.20326 | P97: 165.70268 | Q97: 189.20209 | R97: 218.89212

Sheet Analysis
D1: =+Model!G9 -> 46447 | E1: =+Model!H9 -> 46873 | F1: =+Model!I9 -> 47238 | G1: =+Model!J9 -> 47603 | H1: =+Model!K9 -> 47968 | I1: =+Model!L9 -> 48334 | J1: =+Model!M9 -> 48699 | K1: =+Model!N9 -> 49064 | ... X1: =+Model!AA9 -> 53812
D2: 0 | E2: 1 | F2: 2 | G2: 3 | H2: 4 | I2: 5 | J2: 6 | K2: 7 | L2: 8 | M2: 9 | N2: 10 | O2: 11 | P2: 12 | Q2: 13 | R2: 14 | S2: 15 | T2: 16 | U2: 17 | V2: 18 | W2: 19 | X2: 20
C3: Bonus? | E3: =+Model!H49 -> 0 | F3: =+Model!I49 -> 0 | G3: =+Model!J49 -> 0 | H3: =+Model!K49 -> 0 | I3: =+Model!L49 -> 0 | J3: =+Model!M49 -> 0 | K3: =+Model!N49 -> 0 | L3: =+Model!O49 -> 0 | ... X3: =+Model!AA49 -> 1
C5: Biogas, scfm | E5: =+Model!H11 -> 950 | F5: =+Model!I11 -> 973.123 | G5: =+Model!J11 -> 996.80881 | H5: =+Model!K11 -> 1021.0711 | I5: =+Model!L11 -> 1045.924 | J5: =+Model!M11 -> 1071.3818 | K5: =+Model!N11 -> 1097.4592 | L5: =+Model!O11 -> 1124.1714 | ... X5: =+Model!AA11 -> 1500.2447
C6: RNG Production, MMBtu | E6: =+Model!H17 -> 319400.93 | F6: =+Model!I17 -> 327175.15 | G6: =+Model!J17 -> 335138.59 | H6: =+Model!K17 -> 343295.87 | I6: =+Model!L17 -> 351651.69 | J6: =+Model!M17 -> 360210.89 | K6: =+Model!N17 -> 368978.42 | L6: =+Model!O17 -> 377959.36 | ... X6: =+Model!AA17 -> 504399.55
B8: x | C8: Gross Offtake Revenue | E8: =+Model!H31 -> 9041.4183 | F8: =+Model!I31 -> 9393.2687 | G8: =+Model!J31 -> 9902.6871 | H8: =+Model!K31 -> 10576.849 | I8: =+Model!L31 -> 11072.572 | J8: =+Model!M31 -> 11147.241 | K8: =+Model!N31 -> 11350.826 | L8: =+Model!O31 -> 11645.608 | ... X8: =+Model!AA31 -> 20074.005
C10: (-) Capex Allowance | E10: =-Model!H42 -> 1841.75 | F10: =-Model!I42 -> 1841.75 | G10: =-Model!J42 -> 1841.75 | H10: =-Model!K42 -> 1841.75 | I10: =-Model!L42 -> 1841.75 | J10: =-Model!M42 -> 1841.75 | K10: =-Model!N42 -> 1841.75 | L10: =-Model!O42 -> 1841.75 | ... X10: =-Model!AA42 -> 1841.75
C11: (-) Capital Cost Financing Fee | D11: 0.5 | E11: =+$D$11*E10 -> 920.875 | F11: =+$D$11*F10 -> 920.875 | G11: =+$D$11*G10 -> 920.875 | H11: =+$D$11*H10 -> 920.875 | I11: =+$D$11*I10 -> 920.875 | J11: =+$D$11*J10 -> 920.875 | K11: =+$D$11*K10 -> 920.875 | L11: =+$D$11*L10 -> 920.875 | ... X11: =+$D$11*X10 -> 920.875 | Z11: =+D11/20 -> 0.025
B12: 1 | C12: (-) Opex and Maintenance Allowance | D12: 2595.5625 | E12: =CHOOSE($B$12,MIN($D$12,E25),$D$12,E$25) -> 1843.5023 | F12: =CHOOSE($B$12,MIN($D$12,F25),$D$12,F$25) -> 1909.5113 | G12: =CHOOSE($B$12,MIN($D$12,G25),$D$12,G$25) -> 1978.1656 | H12: =CHOOSE($B$12,MIN($D$12,H25),$D$12,H$25) -> 2049.581 | I12: =CHOOSE($B$12,MIN($D$12,I25),$D$12,I$25) -> 2123.8786 | J12: =CHOOSE($B$12,MIN($D$12,J25),$D$12,J$25) -> 2201.1855 | K12: =CHOOSE($B$12,MIN($D$12,K25),$D$12,K$25) -> 2281.6342 | L12: =CHOOSE($B$12,MIN($D$12,L25),$D$12,L$25) -> 2365.3639 | ... X12: =CHOOSE($B$12,MIN($D$12,X25),$D$12,X$25) -> 2595.5625
C13: Allowances TOTAL | E13: =SUM(E10:E12) -> 4606.1273 | F13: =SUM(F10:F12) -> 4672.1363 | G13: =SUM(G10:G12) -> 4740.7906 | H13: =SUM(H10:H12) -> 4812.206 | I13: =SUM(I10:I12) -> 4886.5036 | J13: =SUM(J10:J12) -> 4963.8105 | K13: =SUM(K10:K12) -> 5044.2592 | L13: =SUM(L10:L12) -> 5127.9889 | ... X13: =SUM(X10:X12) -> 5358.1875
C15: Net Offtake Revenue | E15: =+E8-E13 -> 4435.291 | F15: =+F8-F13 -> 4721.1323 | G15: =+G8-G13 -> 5161.8965 | H15: =+H8-H13 -> 5764.6429 | I15: =+I8-I13 -> 6186.0684 | J15: =+J8-J13 -> 6183.4304 | K15: =+K8-K13 -> 6306.5672 | L15: =+L8-L13 -> 6517.6195 | ... X15: =+X8-X13 -> 14715.818
C17: Base Royalty | D17: 0.7 | E17: =$D17*E15 -> 3104.7037 | F17: =$D17*F15 -> 3304.7926 | G17: =$D17*G15 -> 3613.3276 | H17: =$D17*H15 -> 4035.25 | I17: =$D17*I15 -> 4330.2479 | J17: =$D17*J15 -> 4328.4013 | K17: =$D17*K15 -> 4414.5971 | L17: =$D17*L15 -> 4562.3337 | ... X17: =$D17*X15 -> 10301.073
C18: Bonus Royalty | D18: =90%-D17 -> 0.2 | E18: =E3*E15*$D$18*((E5-1250)/E5) -> 0 | F18: =F3*F15*$D$18*((F5-1250)/F5) -> 0 | G18: =G3*G15*$D$18*((G5-1250)/G5) -> 0 | H18: =H3*H15*$D$18*((H5-1250)/H5) -> 0 | I18: =I3*I15*$D$18*((I5-1250)/I5) -> 0 | J18: =J3*J15*$D$18*((J5-1250)/J5) -> 0 | K18: =K3*K15*$D$18*((K5-1250)/K5) -> 0 | L18: =L3*L15*$D$18*((L5-1250)/L5) -> 0 | ... X18: =X3*X15*$D$18*((X5-1250)/X5) -> 490.92738
B19: x | C19: Total Royalty | E19: =SUM(E17:E18) -> 3104.7037 | F19: =SUM(F17:F18) -> 3304.7926 | G19: =SUM(G17:G18) -> 3613.3276 | H19: =SUM(H17:H18) -> 4035.25 | I19: =SUM(I17:I18) -> 4330.2479 | J19: =SUM(J17:J18) -> 4328.4013 | K19: =SUM(K17:K18) -> 4414.5971 | L19: =SUM(L17:L18) -> 4562.3337 | ... X19: =SUM(X17:X18) -> 10792
C21: Utilities | E21: =+Model!H34 -> 527.01154 | F21: =+Model!I34 -> 553.33497 | G21: =+Model!J34 -> 580.97323 | H21: =+Model!K34 -> 609.99197 | I21: =+Model!L34 -> 640.46015 | J21: =+Model!M34 -> 672.45017 | K21: =+Model!N34 -> 706.03805 | L21: =+Model!O34 -> 741.30359 | ... X21: =+Model!AA34 -> 1330.4914
C22: (+) Consumables / R&M | E22: =+Model!H35 -> 271.49079 | F22: =+Model!I35 -> 285.05135 | G22: =+Model!J35 -> 299.28924 | H22: =+Model!K35 -> 314.23829 | I22: =+Model!L35 -> 329.93402 | J22: =+Model!M35 -> 346.41373 | K22: =+Model!N35 -> 363.71657 | L22: =+Model!O35 -> 381.88367 | ... X22: =+Model!AA35 -> 685.40466
C23: (+) Asset Management | D23: =SUM(E23:X24)/SUM(E25:X25) -> 0.50287561 | E23: =+Model!H36 -> 200 | F23: =+Model!I36 -> 205 | G23: =+Model!J36 -> 210.125 | H23: =+Model!K36 -> 215.37812 | I23: =+Model!L36 -> 220.76258 | J23: =+Model!M36 -> 226.28164 | K23: =+Model!N36 -> 231.93868 | L23: =+Model!O36 -> 237.73715 | ... X23: =+Model!AA36 -> 319.73004
C24: (+) Fixed Expenses | E24: =+Model!H37 -> 845 | F24: =+Model!I37 -> 866.125 | G24: =+Model!J37 -> 887.77812 | H24: =+Model!K37 -> 909.97258 | I24: =+Model!L37 -> 932.72189 | J24: =+Model!M37 -> 956.03994 | K24: =+Model!N37 -> 979.94094 | L24: =+Model!O37 -> 1004.4395 | ... X24: =+Model!AA37 -> 1350.8594
B25: x | C25: TOTAL Opex | E25: =SUM(E21:E24) -> 1843.5023 | F25: =SUM(F21:F24) -> 1909.5113 | G25: =SUM(G21:G24) -> 1978.1656 | H25: =SUM(H21:H24) -> 2049.581 | I25: =SUM(I21:I24) -> 2123.8786 | J25: =SUM(J21:J24) -> 2201.1855 | K25: =SUM(K21:K24) -> 2281.6342 | L25: =SUM(L21:L24) -> 2365.3639 | ... X25: =SUM(X21:X24) -> 3686.4855
C27: EBITDA | E27: =+E8-E19-E25 -> 4093.2123 | F27: =+F8-F19-F25 -> 4178.9647 | G27: =+G8-G19-G25 -> 4311.194 | H27: =+H8-H19-H25 -> 4492.0179 | I27: =+I8-I19-I25 -> 4618.4455 | J27: =+J8-J19-J25 -> 4617.6541 | K27: =+K8-K19-K25 -> 4654.5952 | L27: =+L8-L19-L25 -> 4717.9109 | ... X27: =+X8-X19-X25 -> 5595.52
C28: Capex | D28: =+Model!G57 -> -31309.75 | E28: =+Model!H57 -> -5525.25 | F28: =+Model!I57 -> 0 | G28: =+Model!J57 -> 0 | H28: =+Model!K57 -> 0 | I28: =+Model!L57 -> 0 | J28: =+Model!M57 -> 0 | K28: =+Model!N57 -> 0 | ... X28: =+Model!AA57 -> 0
C29: ITC | D29: =+Model!G60 -> 0 | E29: =+Model!H60 -> 12965.92 | F29: =+Model!I60 -> 0 | G29: =+Model!J60 -> 0 | H29: =+Model!K60 -> 0 | I29: =+Model!L60 -> 0 | J29: =+Model!M60 -> 0 | K29: =+Model!N60 -> 0 | ... X29: =+Model!AA60 -> 0
C30: MTC Capex | E30: =Model!H59 -> 0 | F30: =Model!I59 -> 0 | G30: =Model!J59 -> -552.525 | H30: =Model!K59 -> -566.33812 | I30: =Model!L59 -> -580.49658 | J30: =Model!M59 -> -595.00899 | K30: =Model!N59 -> -609.88422 | L30: =Model!O59 -> -625.13132 | ... X30: =Model!AA59 -> -840.73213
C31: UL Cash Flow | D31: =SUM(D27:D30) -> -31309.75 | E31: =SUM(E27:E30) -> 11533.882 | F31: =SUM(F27:F30) -> 4178.9647 | G31: =SUM(G27:G30) -> 3758.669 | H31: =SUM(H27:H30) -> 3925.6797 | I31: =SUM(I27:I30) -> 4037.9489 | J31: =SUM(J27:J30) -> 4022.6451 | K31: =SUM(K27:K30) -> 4044.711 | ... X31: =SUM(X27:X30) -> 4754.7878
C33: UL IRR | D33: =+XIRR(D31:X31,$D$1:$X$1) -> 0.15261858
E35: =+$D$12-E25 -> 752.06017 | F35: =+$D$12-F25 -> 686.05118 | G35: =+$D$12-G25 -> 617.39691 | H35: =+$D$12-H25 -> 545.98154 | I35: =+$D$12-I25 -> 471.68386 | J35: =+$D$12-J25 -> 394.37702 | K35: =+$D$12-K25 -> 313.92825 | L35: =+$D$12-L25 -> 230.19862 | ... X35: =+$D$12-X25 -> -1090.923

Sheet Model (3)
C3: NTP Date | E3: 46203
H7: =YEAR(H9) -> 2028 | I7: =YEAR(I9) -> 2029 | J7: =YEAR(J9) -> 2030 | K7: =YEAR(K9) -> 2031 | L7: =YEAR(L9) -> 2032 | M7: =YEAR(M9) -> 2033 | N7: =YEAR(N9) -> 2034 | O7: =YEAR(O9) -> 2035 | ... AA7: =YEAR(AA9) -> 2047
H8: 1 | I8: =H8*(1+INPUTS!$E$6) -> 1.025 | J8: =I8*(1+INPUTS!$E$6) -> 1.050625 | K8: =J8*(1+INPUTS!$E$6) -> 1.0768906 | L8: =K8*(1+INPUTS!$E$6) -> 1.1038129 | M8: =L8*(1+INPUTS!$E$6) -> 1.1314082 | N8: =M8*(1+INPUTS!$E$6) -> 1.1596934 | O8: =N8*(1+INPUTS!$E$6) -> 1.1886858 | P8: =O8*(1+INPUTS!$E$6) -> 1.2184029 | ... AA8: =Z8*(1+INPUTS!$E$6) -> 1.5986502
G9: =+INPUTS!E38 -> 46447 | H9: =EOMONTH(INPUTS!E37,6) -> 46873 | I9: =EOMONTH(H9,12) -> 47238 | J9: =EOMONTH(I9,12) -> 47603 | K9: =EOMONTH(J9,12) -> 47968 | L9: =EOMONTH(K9,12) -> 48334 | M9: =EOMONTH(L9,12) -> 48699 | N9: =EOMONTH(M9,12) -> 49064 | O9: =EOMONTH(N9,12) -> 49429 | P9: =EOMONTH(O9,12) -> 49795 | ... AA9: =EOMONTH(Z9,12) -> 53812
C10: $ in '000, except noted | G10: Year 0 | H10: Year 1 | I10: Year 2 | J10: Year 3 | K10: Year 4 | L10: Year 5 | M10: Year 6 | N10: Year 7 | O10: Year 8 | P10: Year 9 | Q10: Year 10 | R10: Year 11 | S10: Year 12 | T10: Year 13 | U10: Year 14 | V10: Year 15 | W10: Year 16 | X10: Year 17 | Y10: Year 18 | Z10: Year 19 | AA10: Year 20
C11: Biogas | D11: scfm | H11: =INPUTS!E8 -> 950 | I11: =H11*(1+INPUTS!$E$9) -> 973.123 | J11: =I11*(1+INPUTS!$E$9) -> 996.80881 | K11: =J11*(1+INPUTS!$E$9) -> 1021.0711 | L11: =K11*(1+INPUTS!$E$9) -> 1045.924 | M11: =L11*(1+INPUTS!$E$9) -> 1071.3818 | N11: =M11*(1+INPUTS!$E$9) -> 1097.4592 | O11: =N11*(1+INPUTS!$E$9) -> 1124.1714 | P11: =O11*(1+INPUTS!$E$9) -> 1151.5337 | ... AA11: =Z11*(1+INPUTS!$E$9) -> 1500.2447
C12: Biogas | D12: scf/d | H12: =H11*(24*60) -> 1368000 | I12: =I11*(24*60) -> 1401297.1 | J12: =J11*(24*60) -> 1435404.7 | K12: =K11*(24*60) -> 1470342.4 | L12: =L11*(24*60) -> 1506130.6 | M12: =M11*(24*60) -> 1542789.8 | N12: =N11*(24*60) -> 1580341.3 | O12: =O11*(24*60) -> 1618806.8 | ... AA12: =AA11*(24*60) -> 2160352.4
C13: Theor. RNG | D13: MMBtu/d | E13: =INPUTS!$E$14 -> 666.68382 | H13: =$E$13*H12/10^6 -> 912.02347 | I13: =$E$13*I12/10^6 -> 934.22212 | J13: =$E$13*J12/10^6 -> 956.96108 | K13: =$E$13*K12/10^6 -> 980.25352 | L13: =$E$13*L12/10^6 -> 1004.1129 | M13: =$E$13*M12/10^6 -> 1028.553 | N13: =$E$13*N12/10^6 -> 1053.588 | O13: =$E$13*O12/10^6 -> 1079.2323 | ... AA13: =$E$13*AA12/10^6 -> 1440.272
C14: Theor. RNG | D14: MMBtu | E14: =SUM(H14:AA14) -> 8447257.2 | H14: =H13*365 -> 332888.57 | I14: =I13*365 -> 340991.07 | J14: =J13*365 -> 349290.8 | K14: =K13*365 -> 357792.53 | L14: =L13*365 -> 366501.2 | M14: =M13*365 -> 375421.84 | N14: =N13*365 -> 384559.61 | O14: =O13*365 -> 393919.79 | ... AA14: =AA13*365 -> 525699.29
C15: Uptime | H15: =INPUTS!$E$12 -> 0.98 | I15: =H15 -> 0.98 | J15: =I15 -> 0.98 | K15: =J15 -> 0.98 | L15: =K15 -> 0.98 | M15: =L15 -> 0.98 | N15: =M15 -> 0.98 | O15: =N15 -> 0.98 | P15: =O15 -> 0.98 | ... AA15: =Z15 -> 0.98
C16: Capture | D16: mult.--> | E16: 1 | H16: =INPUTS!$E$13 -> 0.97906432 | I16: =H16 -> 0.97906432 | J16: =I16 -> 0.97906432 | K16: =J16 -> 0.97906432 | L16: =K16 -> 0.97906432 | M16: =L16 -> 0.97906432 | N16: =M16 -> 0.97906432 | O16: =N16 -> 0.97906432 | P16: =O16 -> 0.97906432 | ... AA16: =Z16 -> 0.97906432
C17: Net RNG Production | D17: MMBtu | E17: =SUM(H17:AA17) -> 8105000 | H17: =PRODUCT(H14:H16)*$E$16 -> 319400.93 | I17: =PRODUCT(I14:I16)*$E$16 -> 327175.15 | J17: =PRODUCT(J14:J16)*$E$16 -> 335138.59 | K17: =PRODUCT(K14:K16)*$E$16 -> 343295.87 | L17: =PRODUCT(L14:L16)*$E$16 -> 351651.69 | M17: =PRODUCT(M14:M16)*$E$16 -> 360210.89 | N17: =PRODUCT(N14:N16)*$E$16 -> 368978.42 | O17: =PRODUCT(O14:O16)*$E$16 -> 377959.36 | ... AA17: =PRODUCT(AA14:AA16)*$E$16 -> 504399.55
C19: Ares Curve D3 RIN | D19: adder--> | E19: 0 | H19: =_xlfn.XLOOKUP(H7,'RIN Curves'!$G$18:$G$44,'RIN Curves'!$H$18:$H$44) -> 2.6619581 | I19: =_xlfn.XLOOKUP(I7,'RIN Curves'!$G$18:$G$44,'RIN Curves'!$H$18:$H$44) -> 2.7118204 | J19: =_xlfn.XLOOKUP(J7,'RIN Curves'!$G$18:$G$44,'RIN Curves'!$H$18:$H$44) -> 2.7914813 | K19: =_xlfn.XLOOKUP(K7,'RIN Curves'!$G$18:$G$44,'RIN Curves'!$H$18:$H$44) -> 2.9160811 | L19: =_xlfn.XLOOKUP(L7,'RIN Curves'!$G$18:$G$44,'RIN Curves'!$H$18:$H$44) -> 2.9781765 | M19: =_xlfn.XLOOKUP(M7,'RIN Curves'!$G$18:$G$44,'RIN Curves'!$H$18:$H$44) -> 2.9101359 | N19: =_xlfn.XLOOKUP(N7,'RIN Curves'!$G$18:$G$44,'RIN Curves'!$H$18:$H$44) -> 2.8799224 | O19: =_xlfn.XLOOKUP(O7,'RIN Curves'!$G$18:$G$44,'RIN Curves'!$H$18:$H$44) -> 2.8742294 | ... AA19: =_xlfn.XLOOKUP(AA7,'RIN Curves'!$G$18:$G$44,'RIN Curves'!$H$18:$H$44) -> 3.6777758
B20: =INPUTS!E16 -> 1 | C20: D3 RIN | D20: $/RIN | E20: =INPUTS!$E$17+$E$19 -> 2.39 | H20: =IF($B$20=0,E20,H19) -> 2.6619581 | I20: =IF($B$20=0,H20*(1+INPUTS!$E$18),I19) -> 2.7118204 | J20: =IF($B$20=0,I20*(1+INPUTS!$E$18),J19) -> 2.7914813 | K20: =IF($B$20=0,J20*(1+INPUTS!$E$18),K19) -> 2.9160811 | L20: =IF($B$20=0,K20*(1+INPUTS!$E$18),L19) -> 2.9781765 | M20: =IF($B$20=0,L20*(1+INPUTS!$E$18),M19) -> 2.9101359 | N20: =IF($B$20=0,M20*(1+INPUTS!$E$18),N19) -> 2.8799224 | O20: =IF($B$20=0,N20*(1+INPUTS!$E$18),O19) -> 2.8742294 | P20: =IF($B$20=0,O20*(1+INPUTS!$E$18),P19) -> 2.9338872 | ... AA20: =IF($B$20=0,Z20*(1+INPUTS!$E$18),AA19) -> 3.6777758
C21: D3 RIN | D21: $/MMBtu | H21: =H20*INPUTS!$E$41 -> 31.216783 | I21: =I20*INPUTS!$E$41 -> 31.801518 | J21: =J20*INPUTS!$E$41 -> 32.735701 | K21: =K20*INPUTS!$E$41 -> 34.196883 | L21: =L20*INPUTS!$E$41 -> 34.925076 | M21: =M20*INPUTS!$E$41 -> 34.127163 | N21: =N20*INPUTS!$E$41 -> 33.77285 | O21: =O20*INPUTS!$E$41 -> 33.706088 | ... AA21: =AA20*INPUTS!$E$41 -> 43.129276
C23: Nat. Gas | D23: $/MMBtu | E23: =INPUTS!E23 -> 0.03 | H23: =INPUTS!E22 -> 3.0390412 | I23: =+H23*(1+$E$23) -> 3.1302124 | J23: =+I23*(1+$E$23) -> 3.2241188 | K23: =+J23*(1+$E$23) -> 3.3208423 | L23: =+K23*(1+$E$23) -> 3.4204676 | M23: =+L23*(1+$E$23) -> 3.5230816 | N23: =+M23*(1+$E$23) -> 3.6287741 | O23: =+N23*(1+$E$23) -> 3.7376373 | P23: =+O23*(1+$E$23) -> 3.8497664 | ... AA23: =+Z23*(1+$E$23) -> 5.3289771
C24: (-) Wheel/hub cost | D24: $/MMBtu | H24: =-INPUTS!$E$24 -> -1 | I24: =H24 -> -1 | J24: =I24 -> -1 | K24: =J24 -> -1 | L24: =K24 -> -1 | M24: =L24 -> -1 | N24: =M24 -> -1 | O24: =N24 -> -1 | P24: =O24 -> -1 | ... AA24: =Z24 -> -1
C27: Offtake Revenue | E27: =E28+E30 -> 325330.87
C28: RIN Value | E28: =+SUM(H28:AA28) -> 299564.81 | H28: =+H21*H$17/10^3 -> 9970.6695 | I28: =+I21*I$17/10^3 -> 10404.666 | J28: =+J21*J$17/10^3 -> 10970.997 | K28: =+K21*K$17/10^3 -> 11739.648 | L28: =+L21*L$17/10^3 -> 12281.462 | M28: =+M21*M$17/10^3 -> 12292.976 | N28: =+N21*N$17/10^3 -> 12461.453 | O28: =+O21*O$17/10^3 -> 12739.531 | ... AA28: =+AA21*AA$17/10^3 -> 21754.387
B29: =INPUTS!E19 -> 0.2 | C29: (-) RIN Brokerage | E29: =+SUM(H29:AA29) -> -59912.961 | H29: =-$B$29*H28 -> -1994.1339 | I29: =-$B$29*I28 -> -2080.9333 | J29: =-$B$29*J28 -> -2194.1993 | K29: =-$B$29*K28 -> -2347.9297 | L29: =-$B$29*L28 -> -2456.2924 | M29: =-$B$29*M28 -> -2458.5952 | N29: =-$B$29*N28 -> -2492.2906 | O29: =-$B$29*O28 -> -2547.9062 | ... AA29: =-$B$29*AA28 -> -4350.8775
C30: (+) Nat Gas Value | E30: =+SUM(H30:AA30) -> 25766.061 | H30: =SUM(H23:H24)*H17/10^3 -> 651.27165 | I30: =SUM(I23:I24)*I17/10^3 -> 696.95256 | J30: =SUM(J23:J24)*J17/10^3 -> 745.38804 | K30: =SUM(K23:K24)*K17/10^3 -> 796.73558 | L30: =SUM(L23:L24)*L17/10^3 -> 851.16152 | M30: =SUM(M23:M24)*M17/10^3 -> 908.84148 | N30: =SUM(N23:N24)*N17/10^3 -> 969.96092 | O30: =SUM(O23:O24)*O17/10^3 -> 1034.7156 | ... AA30: =SUM(AA23:AA24)*AA17/10^3 -> 2183.5341
C31: Net Offtake Revenue | E31: =+SUM(H31:AA31) -> 265417.91 | H31: =SUM(H28:H30) -> 8627.8072 | I31: =SUM(I28:I30) -> 9020.6856 | J31: =SUM(J28:J30) -> 9522.1854 | K31: =SUM(K28:K30) -> 10188.454 | L31: =SUM(L28:L30) -> 10676.331 | M31: =SUM(M28:M30) -> 10743.222 | N31: =SUM(N28:N30) -> 10939.123 | O31: =SUM(O28:O30) -> 11226.341 | ... AA31: =SUM(AA28:AA30) -> 19587.044
C33: Operating Expenses
B34: 1.65 | C34: Utilities | E34: =SUM(H34:AA34) -> 17416.658 | H34: =+$B34*H$8*H$17/10^3 -> 527.01154 | I34: =+$B$34*I8*I17/10^3 -> 553.33497 | J34: =+$B$34*J8*J17/10^3 -> 580.97323 | K34: =+$B$34*K8*K17/10^3 -> 609.99197 | L34: =+$B$34*L8*L17/10^3 -> 640.46015 | M34: =+$B$34*M8*M17/10^3 -> 672.45017 | N34: =+$B$34*N8*N17/10^3 -> 706.03805 | O34: =+$B$34*O8*O17/10^3 -> 741.30359 | P34: =+$B$34*P8*P17/10^3 -> 778.3306 | ... AA34: =+$B$34*AA8*AA17/10^3 -> 1330.4914
B35: 0.8 | C35: (+) Consumables / R&M | E35: =SUM(H35:AA35) -> 8444.44 | H35: =+$B35*H$8*H$17/10^3 -> 255.52075 | I35: =+$B35*I$8*I$17/10^3 -> 268.28362 | J35: =+$B35*J$8*J$17/10^3 -> 281.68399 | K35: =+$B35*K$8*K$17/10^3 -> 295.75368 | L35: =+$B35*L$8*L$17/10^3 -> 310.52613 | M35: =+$B35*M$8*M$17/10^3 -> 326.03645 | N35: =+$B35*N$8*N$17/10^3 -> 342.32148 | O35: =+$B35*O$8*O$17/10^3 -> 359.41992 | ... AA35: =+$B35*AA$8*AA$17/10^3 -> 645.08674
B36: 200 | C36: (+) Asset Management | E36: =SUM(H36:AA36) -> 5108.9315 | H36: =+$B36*H$8 -> 200 | I36: =+$B36*I$8 -> 205 | J36: =+$B36*J$8 -> 210.125 | K36: =+$B36*K$8 -> 215.37812 | L36: =+$B36*L$8 -> 220.76258 | M36: =+$B36*M$8 -> 226.28164 | N36: =+$B36*N$8 -> 231.93868 | O36: =+$B36*O$8 -> 237.73715 | ... AA36: =+$B36*AA$8 -> 319.73004
B37: 850 | C37: (+) Fixed Expenses | E37: =SUM(H37:AA37) -> 21712.959 | H37: =+$B37*H$8 -> 850 | I37: =+$B37*I$8 -> 871.25 | J37: =+$B37*J$8 -> 893.03125 | K37: =+$B37*K$8 -> 915.35703 | L37: =+$B37*L$8 -> 938.24096 | M37: =+$B37*M$8 -> 961.69698 | N37: =+$B37*N$8 -> 985.73941 | O37: =+$B37*O$8 -> 1010.3829 | ... AA37: =+$B37*AA$8 -> 1358.8527
C38: TOTAL | E38: =SUM(H38:AA38) -> 52682.988 | H38: =SUM(H34:H37) -> 1832.5323 | I38: =SUM(I34:I37) -> 1897.8686 | J38: =SUM(J34:J37) -> 1965.8135 | K38: =SUM(K34:K37) -> 2036.4808 | L38: =SUM(L34:L37) -> 2109.9898 | M38: =SUM(M34:M37) -> 2186.4652 | N38: =SUM(N34:N37) -> 2266.0376 | O38: =SUM(O34:O37) -> 2348.8436 | ... AA38: =SUM(AA34:AA37) -> 3654.1608
E39: =E38*1000/E17 -> 6.5000602 | H39: =H38*1000/H17 -> 5.7374043 | I39: =I38*1000/I17 -> 5.8007724 | J39: =J38*1000/J17 -> 5.8656732 | K39: =K38*1000/K17 -> 5.9321448 | L39: =L38*1000/L17 -> 6.0002266 | M39: =M38*1000/M17 -> 6.0699587 | N39: =N38*1000/N17 -> 6.1413825 | O39: =O38*1000/O17 -> 6.21454 | ... AA39: =AA38*1000/AA17 -> 7.244576
C40: Royalty Calculation
C41: Offtake Revenue, net of brokerage | E41: =SUM(H41:AA41) -> 265417.91 | H41: =+H31 -> 8627.8072 | I41: =+I31 -> 9020.6856 | J41: =+J31 -> 9522.1854 | K41: =+K31 -> 10188.454 | L41: =+L31 -> 10676.331 | M41: =+M31 -> 10743.222 | N41: =+N31 -> 10939.123 | O41: =+O31 -> 11226.341 | ... AA41: =+AA31 -> 19587.044
C42: (-) Capex Allowance | D42: =+INPUTS!$E$32 -> 36835 | H42: =-$D$42/20 -> -1841.75 | I42: =-$D$42/20 -> -1841.75 | J42: =-$D$42/20 -> -1841.75 | K42: =-$D$42/20 -> -1841.75 | L42: =-$D$42/20 -> -1841.75 | M42: =-$D$42/20 -> -1841.75 | N42: =-$D$42/20 -> -1841.75 | O42: =-$D$42/20 -> -1841.75 | ... AA42: =-$D$42/20 -> -1841.75
C43: (-) Opex and Maintenance Allowance | D43: =+INPUTS!S25+INPUTS!S26 -> 65452.06 | H43: =-$D$43/20 -> -3272.603 | I43: =-$D$43/20 -> -3272.603 | J43: =-$D$43/20 -> -3272.603 | K43: =-$D$43/20 -> -3272.603 | L43: =-$D$43/20 -> -3272.603 | M43: =-$D$43/20 -> -3272.603 | N43: =-$D$43/20 -> -3272.603 | O43: =-$D$43/20 -> -3272.603 | ... AA43: =-$D$43/20 -> -3272.603
C44: Net Avail. For Royalty | H44: =SUM(H41:H43) -> 3513.4543 | I44: =SUM(I41:I43) -> 3906.3327 | J44: =SUM(J41:J43) -> 4407.8324 | K44: =SUM(K41:K43) -> 5074.1014 | L44: =SUM(L41:L43) -> 5561.9781 | M44: =SUM(M41:M43) -> 5628.8692 | N44: =SUM(N41:N43) -> 5824.7702 | O44: =SUM(O41:O43) -> 6111.9877 | ... AA44: =SUM(AA41:AA43) -> 14472.691
C45: (x) % Royalty | D45: 0.7 | E45: 2000 | H45: =$D$45 -> 0.7 | I45: =$D$45 -> 0.7 | J45: =$D$45 -> 0.7 | K45: =$D$45 -> 0.7 | L45: =$D$45 -> 0.7 | M45: =$D$45 -> 0.7 | N45: =$D$45 -> 0.7 | O45: =$D$45 -> 0.7 | ... AA45: =$D$45 -> 0.7
C46: Royalty Amount (a) | D46: =SUM(H46:AA46) -> 114191.59 | H46: =MAX($E$45,H44*H45) -> 2459.418 | I46: =MAX($E$45,I44*I45) -> 2734.4329 | J46: =MAX($E$45,J44*J45) -> 3085.4827 | K46: =MAX($E$45,K44*K45) -> 3551.871 | L46: =MAX($E$45,L44*L45) -> 3893.3847 | M46: =MAX($E$45,M44*M45) -> 3940.2084 | N46: =MAX($E$45,N44*N45) -> 4077.3392 | O46: =MAX($E$45,O44*O45) -> 4278.3914 | ... AA46: =MAX($E$45,AA44*AA45) -> 10130.884
B48: IRR Calc Below:
C49: Cash Flow | D49: mult.
B50: =+INPUTS!E32/10^3*$D$50 -> 36.835 | C50: Capex | D50: 1 | E50: =SUM(G50:AA50) -> -36835 | G50: =-B50*85%*10^3 -> -31309.75 | H50: =-B50*10^3-G50 -> -5525.25
C51: (+) EBITDA | E51: =SUM(G51:AA51) -> 98543.325 | H51: =+H31-SUM(H38,H46) -> 4335.857 | I51: =+I31-SUM(I38,I46) -> 4388.3842 | J51: =+J31-SUM(J38,J46) -> 4470.8892 | K51: =+K31-SUM(K38,K46) -> 4600.1026 | L51: =+L31-SUM(L38,L46) -> 4672.9566 | M51: =+M31-SUM(M38,M46) -> 4616.5485 | N51: =+N31-SUM(N38,N46) -> 4595.7464 | O51: =+O31-SUM(O38,O46) -> 4599.1057 | ... AA51: =+AA31-SUM(AA38,AA46) -> 5801.9995
B52: 0.015 | C52: (-) Mtce Capex | E52: =SUM(G52:AA52) -> -12369.017 | J52: =+$B$52*SUM(G50:H50) -> -552.525 | K52: =J52*(1+INPUTS!$E$6) -> -566.33812 | L52: =K52*(1+INPUTS!$E$6) -> -580.49658 | M52: =L52*(1+INPUTS!$E$6) -> -595.00899 | N52: =M52*(1+INPUTS!$E$6) -> -609.88422 | O52: =N52*(1+INPUTS!$E$6) -> -625.13132 | P52: =O52*(1+INPUTS!$E$6) -> -640.75961 | Q52: =P52*(1+INPUTS!$E$6) -> -656.7786 | R52: =Q52*(1+INPUTS!$E$6) -> -673.19806 | ... AA52: =Z52*(1+INPUTS!$E$6) -> -840.73213
B53: 0.35 | C53: (+) ITC | E53: =SUM(G53:AA53) -> 12892.25 | H53: =$B$53*B50*10^3 -> 12892.25
C54: TOTAL | E54: =SUM(E50:E53) -> 62231.558 | G54: =SUM(G50:G53) -> -31309.75 | H54: =SUM(H50:H53) -> 11702.857 | I54: =SUM(I50:I53) -> 4388.3842 | J54: =SUM(J50:J53) -> 3918.3642 | K54: =SUM(K50:K53) -> 4033.7645 | L54: =SUM(L50:L53) -> 4092.46 | M54: =SUM(M50:M53) -> 4021.5395 | N54: =SUM(N50:N53) -> 3985.8622 | ... AA54: =SUM(AA50:AA53) -> 4961.2673
C56: IRR | D56: =XIRR(G54:AA54,$G$9:$AA$9) -> 0.15351701
D58: K MMBtu | E58: 6605
B59: City Self-Perform Worksheet Below:
C60: City's Self-perform Economics | E60: TOTAL | G60: =+G10 -> Year 0 | H60: =+H10 -> Year 1 | I60: =+I10 -> Year 2 | J60: =+J10 -> Year 3 | K60: =+K10 -> Year 4 | L60: =+L10 -> Year 5 | M60: =+M10 -> Year 6 | N60: =+N10 -> Year 7 | ... AA60: =+AA10 -> Year 20
C61: ='Bid Forms'!C5 -> 20- year Evaluative Value of the sale of RNG and EAs | E61: =SUM(G61:AA61) -> 325330.87 | G61: =+G31 -> 0 | H61: =+H31-H29 -> 10621.941 | I61: =+I31-I29 -> 11101.619 | J61: =+J31-J29 -> 11716.385 | K61: =+K31-K29 -> 12536.384 | L61: =+L31-L29 -> 13132.623 | M61: =+M31-M29 -> 13201.817 | N61: =+N31-N29 -> 13431.414 | O61: =+O31-O29 -> 13774.247 | ... AA61: =+AA31-AA29 -> 23937.922
C62: ="(-)"&'Bid Forms'!C9 -> (-)20-year Allowance for RIN Management | E62: =SUM(G62:AA62) -> -59912.961 | H62: =H29 -> -1994.1339 | I62: =I29 -> -2080.9333 | J62: =J29 -> -2194.1993 | K62: =K29 -> -2347.9297 | L62: =L29 -> -2456.2924 | M62: =M29 -> -2458.5952 | N62: =N29 -> -2492.2906 | O62: =O29 -> -2547.9062 | ... AA62: =AA29 -> -4350.8775
C63: ="(-)"&'Bid Forms'!C8 -> (-)20-year Allowance for Operations and Maintenance | E63: -45000 | H63: =-H38 -> -1832.5323 | I63: =-I38 -> -1897.8686 | J63: =-J38 -> -1965.8135 | K63: =-K38 -> -2036.4808 | L63: =-L38 -> -2109.9898 | M63: =-M38 -> -2186.4652 | N63: =-N38 -> -2266.0376 | O63: =-O38 -> -2348.8436 | ... AA63: =-AA38 -> -3654.1608
C64: (=) EBITDA | E64: =SUM(E61:E63) -> 220417.91 | H64: =SUM(H61:H63) -> 6795.2749 | I64: =SUM(I61:I63) -> 7122.8171 | J64: =SUM(J61:J63) -> 7556.3719 | K64: =SUM(K61:K63) -> 8151.9735 | L64: =SUM(L61:L63) -> 8566.3413 | M64: =SUM(M61:M63) -> 8556.7569 | N64: =SUM(N61:N63) -> 8673.0856 | O64: =SUM(O61:O63) -> 8877.4971 | ... AA64: =SUM(AA61:AA63) -> 15932.883
C65: (-) Capex | D65: 37 | E65: =SUM(G65:AA65) -> -37000 | G65: =-D65*1000 -> -37000
C66: (-) Mtce Capex | D66: 0.015 | E66: =SUM(G66:AA66) -> -13290.034 | H66: 0 | I66: =+$D$66*$G$65*H8 -> -555 | J66: =+$D$66*$G$65*I8 -> -568.875 | K66: =+$D$66*$G$65*J8 -> -583.09687 | L66: =+$D$66*$G$65*K8 -> -597.6743 | M66: =+$D$66*$G$65*L8 -> -612.61615 | N66: =+$D$66*$G$65*M8 -> -627.93156 | O66: =+$D$66*$G$65*N8 -> -643.62985 | P66: =+$D$66*$G$65*O8 -> -659.72059 | ... AA66: =+$D$66*$G$65*Z8 -> -865.61059
C67: (-) Interest | D67: 0.04 | E67: =SUM(G67:AA67) -> -29600 | H67: =$D$67*$G$65 -> -1480 | I67: =$D$67*$G$65 -> -1480 | J67: =$D$67*$G$65 -> -1480 | K67: =$D$67*$G$65 -> -1480 | L67: =$D$67*$G$65 -> -1480 | M67: =$D$67*$G$65 -> -1480 | N67: =$D$67*$G$65 -> -1480 | O67: =$D$67*$G$65 -> -1480 | ... AA67: =$D$67*$G$65 -> -1480
C68: Total Evaluative Contract Value to Metro Water Services | E68: =SUM(E64:E67) -> 140527.87 | G68: =SUM(G64:G67) -> -37000 | H68: =SUM(H64:H67) -> 5315.2749 | I68: =SUM(I64:I67) -> 5087.8171 | J68: =SUM(J64:J67) -> 5507.4969 | K68: =SUM(K64:K67) -> 6088.8767 | L68: =SUM(L64:L67) -> 6488.667 | M68: =SUM(M64:M67) -> 6464.1407 | N68: =SUM(N64:N67) -> 6565.1541 | ... AA68: =SUM(AA64:AA67) -> 13587.273
I71: Capex ($MM) | O71: 20-yr RNG Prod'n, K MMBtu
B72: Sensitivities Below: | I72: =+I73*INPUTS!$E$32/10^3 -> 33.1515 | J72: =+J73*INPUTS!$E$32/10^3 -> 36.835 | K72: =+K73*INPUTS!$E$32/10^3 -> 39.751554 | L72: =+L73*INPUTS!$E$32/10^3 -> 44.202 | O72: =+O73*$E$17/10^3 -> 7294.5 | P72: =+P73*$E$17/10^3 -> 8105 | Q72: =+Q73*$E$17/10^3 -> 8915.5 | R72: =+R73*$E$17/10^3 -> 9939.5155
H73: =+D56 -> 0.15351701 | I73: 0.9 | J73: 1 | K73: =36.8/34.1 -> 1.0791789 | L73: 1.2 | N73: =+$D$56 -> 0.15351701 | O73: 0.9 | P73: 1 | Q73: 1.1 | R73: =8.1/6.605 -> 1.2263437
G74: =+H74+INPUTS!$E$17 -> 1.89 | H74: -0.5 | I74: 0.1738799 | J74: 0.15351701 | K74: 0.13954481 | L74: 0.12101501 | M74: =+N74+INPUTS!$E$17 -> 1.89 | N74: -0.5 | O74: 0.14340221 | P74: 0.15351701 | Q74: 0.16254315 | R74: 0.17359596
G75: =+H75+INPUTS!$E$17 -> 2.14 | H75: -0.25 | I75: 0.1738799 | J75: 0.15351701 | K75: 0.13954481 | L75: 0.12101501 | M75: =+N75+INPUTS!$E$17 -> 2.14 | N75: -0.25 | O75: 0.14340221 | P75: 0.15351701 | Q75: 0.16254315 | R75: 0.17359596
G76: =+H76+INPUTS!$E$17 -> 2.39 | H76: 0 | I76: 0.1738799 | J76: 0.15351701 | K76: 0.13954481 | L76: 0.12101501 | M76: =+N76+INPUTS!$E$17 -> 2.39 | N76: 0 | O76: 0.14340221 | P76: 0.15351701 | Q76: 0.16254315 | R76: 0.17359596
G77: =+H77+INPUTS!$E$17 -> 2.64 | H77: 0.25 | I77: 0.1738799 | J77: 0.15351701 | K77: 0.13954481 | L77: 0.12101501 | M77: =+N77+INPUTS!$E$17 -> 2.64 | N77: 0.25 | O77: 0.14340221 | P77: 0.15351701 | Q77: 0.16254315 | R77: 0.17359596
G78: =+H78+INPUTS!$E$17 -> 2.89 | H78: 0.5 | I78: 0.1738799 | J78: 0.15351701 | K78: 0.13954481 | L78: 0.12101501 | M78: =+N78+INPUTS!$E$17 -> 2.8534801 | N78: 0.46348008 | O78: 0.14340221 | P78: 0.15351701 | Q78: 0.16254315 | R78: 0.17359596
G79: =+H79+INPUTS!$E$17 -> 3.14 | H79: 0.75 | I79: 0.1738799 | J79: 0.15351701 | K79: 0.13954481 | L79: 0.12101501 | M79: =+N79+INPUTS!$E$17 -> 3.14 | N79: 0.75 | O79: 0.14340221 | P79: 0.15351701 | Q79: 0.16254315 | R79: 0.17359596
O81: 20-yr RNG Prod'n, K MMBtu
O82: =+O83*$E$17/10^3 -> 7294.5 | P82: =+P83*$E$17/10^3 -> 8105 | Q82: =+Q83*$E$17/10^3 -> 8915.5 | R82: =+R83*$E$17/10^3 -> 9939.5155
N83: =+#REF!/1000 -> #REF! | O83: 0.9 | P83: 1 | Q83: 1.1 | R83: =8.1/6.605 -> 1.2263437
M84: =+N84+INPUTS!$E$17 -> 1.89 | N84: -0.5 | O84: #REF! | P84: #REF! | Q84: #REF! | R84: #REF!
M85: =+N85+INPUTS!$E$17 -> 2.14 | N85: -0.25 | O85: #REF! | P85: #REF! | Q85: #REF! | R85: #REF!
M86: =+N86+INPUTS!$E$17 -> 2.39 | N86: 0 | O86: #REF! | P86: #REF! | Q86: #REF! | R86: #REF!
M87: =+N87+INPUTS!$E$17 -> 2.64 | N87: 0.25 | O87: #REF! | P87: #REF! | Q87: #REF! | R87: #REF!
M88: =+N88+INPUTS!$E$17 -> 2.8534801 | N88: 0.46348008 | O88: #REF! | P88: #REF! | Q88: #REF! | R88: #REF!
M89: =+N89+INPUTS!$E$17 -> 3.14 | N89: 0.75 | O89: #REF! | P89: #REF! | Q89: #REF! | R89: #REF!

Sheet Table1
E2: Generic | F2: Case 1 | G2: Case 4
C3: RNG Production | E3: 300 | F3: 330 | G3: 405.4 | P3: From | Q3: To | R3: City % | S3: Burnham %
C4: RIN Price | E4: 2.29 | F4: =+F5/11.727 -> 2.5181206 | G4: 2.82 | O4: 90% MWS Share | P4: =+Q5+1 -> #REF! | R4: 0.9 | S4: =1-R4 -> 0.1
C5: RIN EA | E5: =E4*11.727 -> 26.85483 | F5: 29.53 | G5: =G4*11.727 -> 33.07014 | O5: 70% MWS Share | P5: =Q6+1 -> 5899.75 | Q5: =+Model!#REF! -> #REF! | R5: 0.7 | S5: =1-R5 -> 0.3
C6: Nat Gas | E6: 3.3 | F6: 3.3 | G6: 5.13 | O6: Fixed Royalty to MWS | P6: =Q7+1 -> 4898.75 | Q6: =+P6+INPUTS!$E$26 -> 5898.75 | R6: 1 | S6: =1-R6 -> 0
C7: Brokerage | E7: =-20%*E5 -> -5.370966 | F7: =-20%*F5 -> -5.906 | G7: =-20%*G5 -> -6.614028 | O7: Burnham Allow. (Capex and OMM) | P7: 0 | Q7: =-SUM(Model!H42:H44) -> 4897.75 | R7: 0 | S7: =1-R7 -> 1
C8: Offtake Revenue | E8: =SUM(E5:E7)*E3 -> 7435.1592 | F8: =SUM(F5:F7)*F3 -> 8884.92 | G8: =SUM(G5:G7)*G3 -> 12805.01
H9: Annual Revenue Sharing ($K) | Z9: 20-Yr RNG Production, K MMBtu
Z10: =+Model!O90 -> 7294.5 | AA10: =+Model!P90 -> 8105 | AB10: =+Model!Q90 -> 8915.5 | AC10: =+Model!R90 -> 9939.5155
I11: Annual RNG Production, K MMBtu | Y11: =+Model!M92 -> 0 | Z11: =+Model!O92 -> 81.415722 | AA11: =+Model!P92 -> 98.148792 | AB11: =+Model!Q92 -> 114.88186 | AC11: =+Model!R92 -> 136.02304
H12: =MAX(2000,E8) -> 7435.1592 | I12: 175 | J12: =I12+25 -> 200 | K12: =J12+25 -> 225 | L12: =K12+25 -> 250 | M12: =L12+25 -> 275 | N12: =M12+25 -> 300 | O12: =N12+25 -> 325 | P12: =O12+25 -> 350 | Q12: =P12+25 -> 375 | ... V12: =U12+25 -> 500 | Y12: =+Model!M93 -> 0 | Z12: =+Model!O93 -> 93.70334 | AA12: =+Model!P93 -> 111.81388 | AB12: =+Model!Q93 -> 129.92441 | AC12: =+Model!R93 -> 152.80593
G13: EA, $/RIN | H13: 1.6 | I13: 3204.348 | J13: 3662.112 | K13: 4119.876 | L13: 4577.64 | M13: 5035.404 | N13: 5493.168 | O13: 5950.932 | P13: 6408.696 | Q13: 6866.46 | R13: 7324.224 | S13: 7781.988 | T13: 8239.752 | U13: 8697.516 | V13: 9155.28 | Y13: =+Model!M94 -> 0 | Z13: =+Model!O94 -> 105.82832 | AA13: =+Model!P94 -> 125.28608 | AB13: =+Model!Q94 -> 144.74383 | AC13: =+Model!R94 -> 169.32748
H14: =H13+0.1 -> 1.7 | I14: 3368.526 | J14: 3849.744 | K14: 4330.962 | L14: 4812.18 | M14: 5293.398 | N14: 5774.616 | O14: 6255.834 | P14: 6737.052 | Q14: 7218.27 | R14: 7699.488 | S14: 8180.706 | T14: 8661.924 | U14: 9143.142 | V14: 9624.36 | Y14: =+Model!M95 -> 0 | Z14: =+Model!O95 -> 117.9533 | AA14: =+Model!P95 -> 138.75828 | AB14: =+Model!Q95 -> 159.56325 | AC14: =+Model!R95 -> 185.84903
H15: =H14+0.1 -> 1.8 | I15: 3532.704 | J15: 4037.376 | K15: 4542.048 | L15: 5046.72 | M15: 5551.392 | N15: 6056.064 | O15: 6560.736 | P15: 7065.408 | Q15: 7570.08 | R15: 8074.752 | S15: 8579.424 | T15: 9084.096 | U15: 9588.768 | V15: 10093.44 | Y15: =+Model!M96 -> 0 | Z15: =+Model!O96 -> 128.6404 | AA15: =+Model!P96 -> 150.63283 | AB15: =+Model!Q96 -> 172.62526 | AC15: =+Model!R96 -> 200.41131
H16: =H15+0.1 -> 1.9 | I16: 3696.882 | J16: 4225.008 | K16: 4753.134 | L16: 5281.26 | M16: 5809.386 | N16: 6337.512 | O16: 6865.638 | P16: 7393.764 | Q16: 7921.89 | R16: 8450.016 | S16: 8978.142 | T16: 9506.268 | U16: 10034.394 | V16: 10562.52 | Y16: =+Model!M97 -> 0 | Z16: =+Model!O97 -> 142.20326 | AA16: =+Model!P97 -> 165.70268 | AB16: =+Model!Q97 -> 189.20209 | AC16: =+Model!R97 -> 218.89212
H17: =H16+0.1 -> 2 | I17: 3861.06 | J17: 4412.64 | K17: 4964.22 | L17: 5515.8 | M17: 6067.38 | N17: 6618.96 | O17: 7170.54 | P17: 7722.12 | Q17: 8273.7 | R17: 8825.28 | S17: 9376.86 | T17: 9928.44 | U17: 10480.02 | V17: 11031.6
H18: =H17+0.1 -> 2.1 | I18: 4025.238 | J18: 4600.272 | K18: 5175.306 | L18: 5750.34 | M18: 6325.374 | N18: 6900.408 | O18: 7475.442 | P18: 8050.476 | Q18: 8625.51 | R18: 9200.544 | S18: 9775.578 | T18: 10350.612 | U18: 10925.646 | V18: 11500.68
H19: =H18+0.1 -> 2.2 | I19: 4189.416 | J19: 4787.904 | K19: 5386.392 | L19: 5984.88 | M19: 6583.368 | N19: 7181.856 | O19: 7780.344 | P19: 8378.832 | Q19: 8977.32 | R19: 9575.808 | S19: 10174.296 | T19: 10772.784 | U19: 11371.272 | V19: 11969.76 | AA19: =+AA13/20 -> 6.2643038
H20: =H19+0.1 -> 2.3 | I20: 4353.594 | J20: 4975.536 | K20: 5597.478 | L20: 6219.42 | M20: 6841.362 | N20: 7463.304 | O20: 8085.246 | P20: 8707.188 | Q20: 9329.13 | R20: 9951.072 | S20: 10573.014 | T20: 11194.956 | U20: 11816.898 | V20: 12438.84
H21: =H20+0.1 -> 2.4 | I21: 4517.772 | J21: 5163.168 | K21: 5808.564 | L21: 6453.96 | M21: 7099.356 | N21: 7744.752 | O21: 8390.148 | P21: 9035.544 | Q21: 9680.94 | R21: 10326.336 | S21: 10971.732 | T21: 11617.128 | U21: 12262.524 | V21: 12907.92
H22: =H21+0.1 -> 2.5 | I22: 4681.95 | J22: 5350.8 | K22: 6019.65 | L22: 6688.5 | M22: 7357.35 | N22: 8026.2 | O22: 8695.05 | P22: 9363.9 | Q22: 10032.75 | R22: 10701.6 | S22: 11370.45 | T22: 12039.3 | U22: 12708.15 | V22: 13377
H23: =H22+0.1 -> 2.6 | I23: 4846.128 | J23: 5538.432 | K23: 6230.736 | L23: 6923.04 | M23: 7615.344 | N23: 8307.648 | O23: 8999.952 | P23: 9692.256 | Q23: 10384.56 | R23: 11076.864 | S23: 11769.168 | T23: 12461.472 | U23: 13153.776 | V23: 13846.08
H24: =H23+0.1 -> 2.7 | I24: 5010.306 | J24: 5726.064 | K24: 6441.822 | L24: 7157.58 | M24: 7873.338 | N24: 8589.096 | O24: 9304.854 | P24: 10020.612 | Q24: 10736.37 | R24: 11452.128 | S24: 12167.886 | T24: 12883.644 | U24: 13599.402 | V24: 14315.16
H25: =H24+0.1 -> 2.8 | I25: 5174.484 | J25: 5913.696 | K25: 6652.908 | L25: 7392.12 | M25: 8131.332 | N25: 8870.544 | O25: 9609.756 | P25: 10348.968 | Q25: 11088.18 | R25: 11827.392 | S25: 12566.604 | T25: 13305.816 | U25: 14045.028 | V25: 14784.24
H26: =H25+0.1 -> 2.9 | I26: 5338.662 | J26: 6101.328 | K26: 6863.994 | L26: 7626.66 | M26: 8389.326 | N26: 9151.992 | O26: 9914.658 | P26: 10677.324 | Q26: 11439.99 | R26: 12202.656 | S26: 12965.322 | T26: 13727.988 | U26: 14490.654 | V26: 15253.32
H27: =H26+0.1 -> 3 | I27: 5502.84 | J27: 6288.96 | K27: 7075.08 | L27: 7861.2 | M27: 8647.32 | N27: 9433.44 | O27: 10219.56 | P27: 11005.68 | Q27: 11791.8 | R27: 12577.92 | S27: 13364.04 | T27: 14150.16 | U27: 14936.28 | V27: 15722.4
H28: =H27+0.1 -> 3.1 | I28: 5667.018 | J28: 6476.592 | K28: 7286.166 | L28: 8095.74 | M28: 8905.314 | N28: 9714.888 | O28: 10524.462 | P28: 11334.036 | Q28: 12143.61 | R28: 12953.184 | S28: 13762.758 | T28: 14572.332 | U28: 15381.906 | V28: 16191.48
H29: =H28+0.1 -> 3.2 | I29: 5831.196 | J29: 6664.224 | K29: 7497.252 | L29: 8330.28 | M29: 9163.308 | N29: 9996.336 | O29: 10829.364 | P29: 11662.392 | Q29: 12495.42 | R29: 13328.448 | S29: 14161.476 | T29: 14994.504 | U29: 15827.532 | V29: 16660.56
H30: =H29+0.1 -> 3.3 | I30: 5995.374 | J30: 6851.856 | K30: 7708.338 | L30: 8564.82 | M30: 9421.302 | N30: 10277.784 | O30: 11134.266 | P30: 11990.748 | Q30: 12847.23 | R30: 13703.712 | S30: 14560.194 | T30: 15416.676 | U30: 16273.158 | V30: 17129.64
H31: =H30+0.1 -> 3.4 | I31: 6159.552 | J31: 7039.488 | K31: 7919.424 | L31: 8799.36 | M31: 9679.296 | N31: 10559.232 | O31: 11439.168 | P31: 12319.104 | Q31: 13199.04 | R31: 14078.976 | S31: 14958.912 | T31: 15838.848 | U31: 16718.784 | V31: 17598.72
... H33: =H32+0.1 -> 3.6 | I33: 6487.908 | J33: 7414.752 | K33: 8341.596 | L33: 9268.44 | M33: 10195.284 | N33: 11122.128 | O33: 12048.972 | P33: 12975.816 | Q33: 13902.66 | R33: 14829.504 | S33: 15756.348 | T33: 16683.192 | U33: 17610.036 | V33: 18536.88
E42: Royalty Calculation ($ in '000) | H42: {=_xlfn.SEQUENCE(1,20,1,1)} -> 1 | I42: 2 | J42: 3 | K42: 4 | L42: 5 | M42: 6 | N42: 7 | O42: 8 | P42: 9 | Q42: 10 | R42: 11 | S42: 12 | T42: 13 | U42: 14 | V42: 15 | W42: 16 | X42: 17 | Y42: 18 | Z42: 19 | AA42: 20 | AB42: TOTAL
E44: Biogas, scfm | H44: =+Model!H11 -> 950 | I44: =+Model!I11 -> 973.123 | J44: =+Model!J11 -> 996.80881 | K44: =+Model!K11 -> 1021.0711 | L44: =+Model!L11 -> 1045.924 | M44: =+Model!M11 -> 1071.3818 | N44: =+Model!N11 -> 1097.4592 | O44: =+Model!O11 -> 1124.1714 | ... AA44: =+Model!AA11 -> 1500.2447 | AB44: =AVERAGE(H44:AA44) -> 1205.3424
E45: RNG Production, K MMBtu | H45: =+Model!H17/1000 -> 319.40093 | I45: =+Model!I17/1000 -> 327.17515 | J45: =+Model!J17/1000 -> 335.13859 | K45: =+Model!K17/1000 -> 343.29587 | L45: =+Model!L17/1000 -> 351.65169 | M45: =+Model!M17/1000 -> 360.21089 | N45: =+Model!N17/1000 -> 368.97842 | O45: =+Model!O17/1000 -> 377.95936 | ... AA45: =+Model!AA17/1000 -> 504.39955 | AB45: =SUM(H45:AA45) -> 8105
E46: D3 RIN Price, $/RIN | H46: =+Model!H20 -> 2.6619581 | I46: =+Model!I20 -> 2.7118204 | J46: =+Model!J20 -> 2.7914813 | K46: =+Model!K20 -> 2.9160811 | L46: =+Model!L20 -> 2.9781765 | M46: =+Model!M20 -> 2.9101359 | N46: =+Model!N20 -> 2.8799224 | O46: =+Model!O20 -> 2.8742294 | ... AA46: =+Model!AA20 -> 3.6777758 | AB46: =AVERAGE(H46:AA46) -> 3.1120546
E48: EA RIN Sale | H48: =+Model!H28/1000 -> 9.9706695 | I48: =+Model!I28/1000 -> 10.404666 | J48: =+Model!J28/1000 -> 10.970997 | K48: =+Model!K28/1000 -> 11.739648 | L48: =+Model!L28/1000 -> 12.281462 | M48: =+Model!M28/1000 -> 12.292976 | N48: =+Model!N28/1000 -> 12.461453 | O48: =+Model!O28/1000 -> 12.739531 | ... AA48: =+Model!AA28/1000 -> 21.754387 | AB48: =SUM(H48:AA48) -> 299.56481
E49: (-) RIN Managament | H49: =+Model!H29/1000 -> -1.9941339 | I49: =+Model!I29/1000 -> -2.0809333 | J49: =+Model!J29/1000 -> -2.1941993 | K49: =+Model!K29/1000 -> -2.3479297 | L49: =+Model!L29/1000 -> -2.4562924 | M49: =+Model!M29/1000 -> -2.4585952 | N49: =+Model!N29/1000 -> -2.4922906 | O49: =+Model!O29/1000 -> -2.5479062 | ... AA49: =+Model!AA29/1000 -> -4.3508775 | AB49: =SUM(H49:AA49) -> -59.912961
E50: (+) Nat. Gas Sale | H50: =+Model!H30/1000 -> 1.0648827 | I50: =+Model!I30/1000 -> 1.0695356 | J50: =+Model!J30/1000 -> 1.1258897 | K50: =+Model!K30/1000 -> 1.1851301 | L50: =+Model!L30/1000 -> 1.2474025 | M50: =+Model!M30/1000 -> 1.3128602 | N50: =+Model!N30/1000 -> 1.3816642 | O50: =+Model!O30/1000 -> 1.4539834 | ... AA50: =+Model!AA30/1000 -> 2.6704954 | AB50: =SUM(H50:AA50) -> 34.481019
E51: =+Model!C41 -> Offtake Revenue, net of brokerage | H51: =+Model!H41/10^3 -> 9.0414183 | I51: =+Model!I41/10^3 -> 9.3932687 | J51: =+Model!J41/10^3 -> 9.9026871 | K51: =+Model!K41/10^3 -> 10.576849 | L51: =+Model!L41/10^3 -> 11.072572 | M51: =+Model!M41/10^3 -> 11.147241 | N51: =+Model!N41/10^3 -> 11.350826 | O51: =+Model!O41/10^3 -> 11.645608 | ... AA51: =+Model!AA41/10^3 -> 20.074005 | AB51: =SUM(H51:AA51) -> 274.13286
E52: =+Model!C42 -> (-) Capex Allowance | H52: =+Model!H42/10^3 -> -1.84175 | I52: =+Model!I42/10^3 -> -1.84175 | J52: =+Model!J42/10^3 -> -1.84175 | K52: =+Model!K42/10^3 -> -1.84175 | L52: =+Model!L42/10^3 -> -1.84175 | M52: =+Model!M42/10^3 -> -1.84175 | N52: =+Model!N42/10^3 -> -1.84175 | O52: =+Model!O42/10^3 -> -1.84175 | ... AA52: =+Model!AA42/10^3 -> -1.84175 | AB52: =SUM(H52:AA52) -> -36.835
E53: =+Model!C44 -> (-) Opex and Maintenance Allowance | H53: =+Model!H44/10^3 -> -2.5955625 | I53: =+Model!I44/10^3 -> -2.5955625 | J53: =+Model!J44/10^3 -> -2.5955625 | K53: =+Model!K44/10^3 -> -2.5955625 | L53: =+Model!L44/10^3 -> -2.5955625 | M53: =+Model!M44/10^3 -> -2.5955625 | N53: =+Model!N44/10^3 -> -2.5955625 | O53: =+Model!O44/10^3 -> -2.5955625 | ... AA53: =+Model!AA44/10^3 -> -2.5955625 | AB53: =SUM(H53:AA53) -> -51.91125
E54: Amount Avail. For Royalty | H54: =SUM(H51:H53) -> 4.6041058 | I54: =SUM(I51:I53) -> 4.9559562 | J54: =SUM(J51:J53) -> 5.4653746 | K54: =SUM(K51:K53) -> 6.1395363 | L54: =SUM(L51:L53) -> 6.6352596 | M54: =SUM(M51:M53) -> 6.7099284 | N54: =SUM(N51:N53) -> 6.913514 | O54: =SUM(O51:O53) -> 7.2082959 | ... AB54: =SUM(AB51:AB53) -> 185.38661
E55: % Royalty | H55: =+H56/H54 -> 0.7 | I55: =+I56/I54 -> 0.7 | J55: =+J56/J54 -> 0.7 | K55: =+K56/K54 -> 0.7 | L55: =+L56/L54 -> 0.7 | M55: =+M56/M54 -> 0.7 | N55: =+N56/N54 -> 0.7 | O55: =+O56/O54 -> 0.7 | ... AB55: =+AB56/AB54 -> 0.7
E56: MWS Royalty (subject to Fixed Royalty) | H56: =MAX(2,70%*H54) -> 3.2228741 | I56: =MAX(2,70%*I54) -> 3.4691693 | J56: =MAX(2,70%*J54) -> 3.8257622 | K56: =MAX(2,70%*K54) -> 4.2976754 | L56: =MAX(2,70%*L54) -> 4.6446817 | M56: =MAX(2,70%*M54) -> 4.6969499 | N56: =MAX(2,70%*N54) -> 4.8394598 | O56: =MAX(2,70%*O54) -> 5.0458071 | ... AA56: =MAX(2,70%*AA54) -> 10.945685 | AB56: =SUM(H56:AA56) -> 129.77063
E57: Fixed Royalty | H57: 2 | I57: 2 | J57: 2 | K57: 2 | L57: 2 | M57: 2 | N57: 2 | O57: 2 | P57: 2 | Q57: 2 | R57: 2 | S57: 2 | T57: 2 | U57: 2 | V57: 2 | W57: 2 | X57: 2 | Y57: 2 | Z57: 2 | AA57: 2 | AB57: =SUM(H57:AA57) -> 40
E58: Variable Royalty | H58: =H56-H57 -> 1.2228741 | I58: =I56-I57 -> 1.4691693 | J58: =J56-J57 -> 1.8257622 | K58: =K56-K57 -> 2.2976754 | L58: =L56-L57 -> 2.6446817 | M58: =M56-M57 -> 2.6969499 | N58: =N56-N57 -> 2.8394598 | O58: =O56-O57 -> 3.0458071 | ... AA58: =AA56-AA57 -> 8.945685 | AB58: =SUM(H58:AA58) -> 89.77063
E61: Royalty Calculation ($ in '000) | H61: 1 | I61: 5 | J61: 10 | K61: 15 | L61: 20 | M61: TOTAL
E63: Biogas, scfm | H63: =_xlfn.XLOOKUP(H$61,$H$42:$AB$42,$H44:$AB44) -> 950 | I63: =_xlfn.XLOOKUP(I$61,$H$42:$AB$42,$H44:$AB44) -> 1045.924 | J63: =_xlfn.XLOOKUP(J$61,$H$42:$AB$42,$H44:$AB44) -> 1179.5621 | K63: =_xlfn.XLOOKUP(K$61,$H$42:$AB$42,$H44:$AB44) -> 1330.2751 | L63: =_xlfn.XLOOKUP(L$61,$H$42:$AB$42,$H44:$AB44) -> 1500.2447 | M63: =_xlfn.XLOOKUP(M$61,$H$42:$AB$42,$H44:$AB44) -> 1205.3424
E64: RNG Production, K MMBtu | H64: =_xlfn.XLOOKUP(H$61,$H$42:$AB$42,$H45:$AB45) -> 319.40093 | I64: =_xlfn.XLOOKUP(I$61,$H$42:$AB$42,$H45:$AB45) -> 351.65169 | J64: =_xlfn.XLOOKUP(J$61,$H$42:$AB$42,$H45:$AB45) -> 396.58234 | K64: =_xlfn.XLOOKUP(K$61,$H$42:$AB$42,$H45:$AB45) -> 447.25379 | L64: =_xlfn.XLOOKUP(L$61,$H$42:$AB$42,$H45:$AB45) -> 504.39955 | M64: =_xlfn.XLOOKUP(M$61,$H$42:$AB$42,$H45:$AB45) -> 8105
E65: D3 RIN Price, $/RIN | H65: =_xlfn.XLOOKUP(H$61,$H$42:$AB$42,$H46:$AB46) -> 2.6619581 | I65: =_xlfn.XLOOKUP(I$61,$H$42:$AB$42,$H46:$AB46) -> 2.9781765 | J65: =_xlfn.XLOOKUP(J$61,$H$42:$AB$42,$H46:$AB46) -> 2.9947832 | K65: =_xlfn.XLOOKUP(K$61,$H$42:$AB$42,$H46:$AB46) -> 3.318756 | L65: =_xlfn.XLOOKUP(L$61,$H$42:$AB$42,$H46:$AB46) -> 3.6777758 | M65: =_xlfn.XLOOKUP(M$61,$H$42:$AB$42,$H46:$AB46) -> 3.1120546
E67: EA RIN Sale | H67: =_xlfn.XLOOKUP(H$61,$H$42:$AB$42,$H48:$AB48) -> 9.9706695 | I67: =_xlfn.XLOOKUP(I$61,$H$42:$AB$42,$H48:$AB48) -> 12.281462 | J67: =_xlfn.XLOOKUP(J$61,$H$42:$AB$42,$H48:$AB48) -> 13.927901 | K67: =_xlfn.XLOOKUP(K$61,$H$42:$AB$42,$H48:$AB48) -> 17.406693 | L67: =_xlfn.XLOOKUP(L$61,$H$42:$AB$42,$H48:$AB48) -> 21.754387 | M67: =_xlfn.XLOOKUP(M$61,$H$42:$AB$42,$H48:$AB48) -> 299.56481
E68: (-) RIN Managament | H68: =_xlfn.XLOOKUP(H$61,$H$42:$AB$42,$H49:$AB49) -> -1.9941339 | I68: =_xlfn.XLOOKUP(I$61,$H$42:$AB$42,$H49:$AB49) -> -2.4562924 | J68: =_xlfn.XLOOKUP(J$61,$H$42:$AB$42,$H49:$AB49) -> -2.7855803 | K68: =_xlfn.XLOOKUP(K$61,$H$42:$AB$42,$H49:$AB49) -> -3.4813386 | L68: =_xlfn.XLOOKUP(L$61,$H$42:$AB$42,$H49:$AB49) -> -4.3508775 | M68: =_xlfn.XLOOKUP(M$61,$H$42:$AB$42,$H49:$AB49) -> -59.912961
E69: (+) Nat. Gas Sale | H69: =_xlfn.XLOOKUP(H$61,$H$42:$AB$42,$H50:$AB50) -> 1.0648827 | I69: =_xlfn.XLOOKUP(I$61,$H$42:$AB$42,$H50:$AB50) -> 1.2474025 | J69: =_xlfn.XLOOKUP(J$61,$H$42:$AB$42,$H50:$AB50) -> 1.6098864 | K69: =_xlfn.XLOOKUP(K$61,$H$42:$AB$42,$H50:$AB50) -> 2.0747349 | L69: =_xlfn.XLOOKUP(L$61,$H$42:$AB$42,$H50:$AB50) -> 2.6704954 | M69: =_xlfn.XLOOKUP(M$61,$H$42:$AB$42,$H50:$AB50) -> 34.481019
E70: Net Offtake Revenue | H70: =_xlfn.XLOOKUP(H$61,$H$42:$AB$42,$H51:$AB51) -> 9.0414183 | I70: =_xlfn.XLOOKUP(I$61,$H$42:$AB$42,$H51:$AB51) -> 11.072572 | J70: =_xlfn.XLOOKUP(J$61,$H$42:$AB$42,$H51:$AB51) -> 12.752207 | K70: =_xlfn.XLOOKUP(K$61,$H$42:$AB$42,$H51:$AB51) -> 16.000089 | L70: =_xlfn.XLOOKUP(L$61,$H$42:$AB$42,$H51:$AB51) -> 20.074005 | M70: =_xlfn.XLOOKUP(M$61,$H$42:$AB$42,$H51:$AB51) -> 274.13286
E71: (-) Capex Allowance | H71: =_xlfn.XLOOKUP(H$61,$H$42:$AB$42,$H52:$AB52) -> -1.84175 | I71: =_xlfn.XLOOKUP(I$61,$H$42:$AB$42,$H52:$AB52) -> -1.84175 | J71: =_xlfn.XLOOKUP(J$61,$H$42:$AB$42,$H52:$AB52) -> -1.84175 | K71: =_xlfn.XLOOKUP(K$61,$H$42:$AB$42,$H52:$AB52) -> -1.84175 | L71: =_xlfn.XLOOKUP(L$61,$H$42:$AB$42,$H52:$AB52) -> -1.84175 | M71: =_xlfn.XLOOKUP(M$61,$H$42:$AB$42,$H52:$AB52) -> -36.835
E72: (-) Opex and Maintenance Allowance | H72: =_xlfn.XLOOKUP(H$61,$H$42:$AB$42,$H53:$AB53) -> -2.5955625 | I72: =_xlfn.XLOOKUP(I$61,$H$42:$AB$42,$H53:$AB53) -> -2.5955625 | J72: =_xlfn.XLOOKUP(J$61,$H$42:$AB$42,$H53:$AB53) -> -2.5955625 | K72: =_xlfn.XLOOKUP(K$61,$H$42:$AB$42,$H53:$AB53) -> -2.5955625 | L72: =_xlfn.XLOOKUP(L$61,$H$42:$AB$42,$H53:$AB53) -> -2.5955625 | M72: =_xlfn.XLOOKUP(M$61,$H$42:$AB$42,$H53:$AB53) -> -51.91125
E73: Amount Avail. For Royalty | H73: =SUM(H70:H72) -> 4.6041058 | I73: =SUM(I70:I72) -> 6.6352596 | J73: =SUM(J70:J72) -> 8.314895 | K73: =SUM(K70:K72) -> 11.562777 | L73: =SUM(L70:L72) -> 15.636693 | M73: =SUM(M70:M72) -> 185.38661
E74: % Royalty | H74: =_xlfn.XLOOKUP(H$61,$H$42:$AB$42,$H55:$AB55) -> 0.7 | I74: =_xlfn.XLOOKUP(I$61,$H$42:$AB$42,$H55:$AB55) -> 0.7 | J74: =_xlfn.XLOOKUP(J$61,$H$42:$AB$42,$H55:$AB55) -> 0.7 | K74: =_xlfn.XLOOKUP(K$61,$H$42:$AB$42,$H55:$AB55) -> 0.7 | L74: =_xlfn.XLOOKUP(L$61,$H$42:$AB$42,$H55:$AB55) -> 0.7 | M74: =_xlfn.XLOOKUP(M$61,$H$42:$AB$42,$H55:$AB55) -> 0.7
E75: MWS Royalty (subject to Fixed Royalty) | H75: =_xlfn.XLOOKUP(H$61,$H$42:$AB$42,$H56:$AB56) -> 3.2228741 | I75: =_xlfn.XLOOKUP(I$61,$H$42:$AB$42,$H56:$AB56) -> 4.6446817 | J75: =_xlfn.XLOOKUP(J$61,$H$42:$AB$42,$H56:$AB56) -> 5.8204265 | K75: =_xlfn.XLOOKUP(K$61,$H$42:$AB$42,$H56:$AB56) -> 8.0939438 | L75: =_xlfn.XLOOKUP(L$61,$H$42:$AB$42,$H56:$AB56) -> 10.945685 | M75: =_xlfn.XLOOKUP(M$61,$H$42:$AB$42,$H56:$AB56) -> 129.77063
E76: Fixed Royalty | H76: =_xlfn.XLOOKUP(H$61,$H$42:$AB$42,$H57:$AB57) -> 2 | I76: =_xlfn.XLOOKUP(I$61,$H$42:$AB$42,$H57:$AB57) -> 2 | J76: =_xlfn.XLOOKUP(J$61,$H$42:$AB$42,$H57:$AB57) -> 2 | K76: =_xlfn.XLOOKUP(K$61,$H$42:$AB$42,$H57:$AB57) -> 2 | L76: =_xlfn.XLOOKUP(L$61,$H$42:$AB$42,$H57:$AB57) -> 2 | M76: =_xlfn.XLOOKUP(M$61,$H$42:$AB$42,$H57:$AB57) -> 40
E77: Variable Royalty | H77: =_xlfn.XLOOKUP(H$61,$H$42:$AB$42,$H58:$AB58) -> 1.2228741 | I77: =_xlfn.XLOOKUP(I$61,$H$42:$AB$42,$H58:$AB58) -> 2.6446817 | J77: =_xlfn.XLOOKUP(J$61,$H$42:$AB$42,$H58:$AB58) -> 3.8204265 | K77: =_xlfn.XLOOKUP(K$61,$H$42:$AB$42,$H58:$AB58) -> 6.0939438 | L77: =_xlfn.XLOOKUP(L$61,$H$42:$AB$42,$H58:$AB58) -> 8.945685 | M77: =_xlfn.XLOOKUP(M$61,$H$42:$AB$42,$H58:$AB58) -> 89.77063
E80: Royalty Calculation ($ in '000) | H80: {=_xlfn.SEQUENCE(1,20,1,1)} -> 1 | I80: 2 | J80: 3 | K80: 4 | L80: 5 | M80: 6 | N80: 7 | O80: 8 | P80: 9 | Q80: 10 | R80: 11 | S80: 12 | T80: 13 | U80: 14 | V80: 15 | W80: 16 | X80: 17 | Y80: 18 | Z80: 19 | AA80: 20 | AB80: TOTAL
E82: Biogas, scfm | H82: =+Model!H11 -> 950 | I82: =+Model!I11 -> 973.123 | J82: =+Model!J11 -> 996.80881 | K82: =+Model!K11 -> 1021.0711 | L82: =+Model!L11 -> 1045.924 | M82: =+Model!M11 -> 1071.3818 | N82: =+Model!N11 -> 1097.4592 | O82: =+Model!O11 -> 1124.1714 | ... AA82: =+Model!AA11 -> 1500.2447 | AB82: =AVERAGE(H82:AA82) -> 1205.3424
E83: RNG Production, K MMBtu | H83: =+Model!H17/1000 -> 319.40093 | I83: =+Model!I17/1000 -> 327.17515 | J83: =+Model!J17/1000 -> 335.13859 | K83: =+Model!K17/1000 -> 343.29587 | L83: =+Model!L17/1000 -> 351.65169 | M83: =+Model!M17/1000 -> 360.21089 | N83: =+Model!N17/1000 -> 368.97842 | O83: =+Model!O17/1000 -> 377.95936 | ... AA83: =+Model!AA17/1000 -> 504.39955 | AB83: =SUM(H83:AA83) -> 8105
E84: D3 RIN Price, $/RIN | H84: =+Model!H20 -> 2.6619581 | I84: =+Model!I20 -> 2.7118204 | J84: =+Model!J20 -> 2.7914813 | K84: =+Model!K20 -> 2.9160811 | L84: =+Model!L20 -> 2.9781765 | M84: =+Model!M20 -> 2.9101359 | N84: =+Model!N20 -> 2.8799224 | O84: =+Model!O20 -> 2.8742294 | ... AA84: =+Model!AA20 -> 3.6777758 | AB84: =AVERAGE(H84:AA84) -> 3.1120546
E86: EA RIN Sale | H86: =+Model!H28/1000 -> 9.9706695 | I86: =+Model!I28/1000 -> 10.404666 | J86: =+Model!J28/1000 -> 10.970997 | K86: =+Model!K28/1000 -> 11.739648 | L86: =+Model!L28/1000 -> 12.281462 | M86: =+Model!M28/1000 -> 12.292976 | N86: =+Model!N28/1000 -> 12.461453 | O86: =+Model!O28/1000 -> 12.739531 | ... AA86: =+Model!AA28/1000 -> 21.754387 | AB86: =SUM(H86:AA86) -> 299.56481
E87: (-) RIN Managament | H87: =+Model!H29/1000 -> -1.9941339 | I87: =+Model!I29/1000 -> -2.0809333 | J87: =+Model!J29/1000 -> -2.1941993 | K87: =+Model!K29/1000 -> -2.3479297 | L87: =+Model!L29/1000 -> -2.4562924 | M87: =+Model!M29/1000 -> -2.4585952 | N87: =+Model!N29/1000 -> -2.4922906 | O87: =+Model!O29/1000 -> -2.5479062 | ... AA87: =+Model!AA29/1000 -> -4.3508775 | AB87: =SUM(H87:AA87) -> -59.912961
E88: (+) Nat. Gas Sale | H88: =+Model!H30/1000 -> 1.0648827 | I88: =+Model!I30/1000 -> 1.0695356 | J88: =+Model!J30/1000 -> 1.1258897 | K88: =+Model!K30/1000 -> 1.1851301 | L88: =+Model!L30/1000 -> 1.2474025 | M88: =+Model!M30/1000 -> 1.3128602 | N88: =+Model!N30/1000 -> 1.3816642 | O88: =+Model!O30/1000 -> 1.4539834 | ... AA88: =+Model!AA30/1000 -> 2.6704954 | AB88: =SUM(H88:AA88) -> 34.481019
E89: Offtake Revenue, net of brokerage | H89: =SUM(H86:H88) -> 9.0414183 | I89: =SUM(I86:I88) -> 9.3932687 | J89: =SUM(J86:J88) -> 9.9026871 | K89: =SUM(K86:K88) -> 10.576849 | L89: =SUM(L86:L88) -> 11.072572 | M89: =SUM(M86:M88) -> 11.147241 | N89: =SUM(N86:N88) -> 11.350826 | O89: =SUM(O86:O88) -> 11.645608 | ... AA89: =SUM(AA86:AA88) -> 20.074005 | AB89: =SUM(H89:AA89) -> 274.13286
E91: Net Offtake Revenue (< $14MM) | H91: =+MIN(H89,14) -> 9.0414183 | I91: =+MIN(I89,14) -> 9.3932687 | J91: =+MIN(J89,14) -> 9.9026871 | K91: =+MIN(K89,14) -> 10.576849 | L91: =+MIN(L89,14) -> 11.072572 | M91: =+MIN(M89,14) -> 11.147241 | N91: =+MIN(N89,14) -> 11.350826 | O91: =+MIN(O89,14) -> 11.645608 | ... AA91: =+MIN(AA89,14) -> 14 | AB91: =SUM(H91:AA91) -> 248.37713
E92: (-) Capex Allowance | H92: =+Model!H42/1000 -> -1.84175 | I92: =+Model!I42/1000 -> -1.84175 | J92: =+Model!J42/1000 -> -1.84175 | K92: =+Model!K42/1000 -> -1.84175 | L92: =+Model!L42/1000 -> -1.84175 | M92: =+Model!M42/1000 -> -1.84175 | N92: =+Model!N42/1000 -> -1.84175 | O92: =+Model!O42/1000 -> -1.84175 | ... AA92: =+Model!AA42/1000 -> -1.84175 | AB92: =SUM(H92:AA92) -> -36.835
E93: (-) Opex and Maintenance Allowance | H93: =+Model!H44/1000 -> -2.5955625 | I93: =+Model!I44/1000 -> -2.5955625 | J93: =+Model!J44/1000 -> -2.5955625 | K93: =+Model!K44/1000 -> -2.5955625 | L93: =+Model!L44/1000 -> -2.5955625 | M93: =+Model!M44/1000 -> -2.5955625 | N93: =+Model!N44/1000 -> -2.5955625 | O93: =+Model!O44/1000 -> -2.5955625 | ... AA93: =+Model!AA44/1000 -> -2.5955625 | AB93: =SUM(H93:AA93) -> -51.91125
E94: Amount Avail. For Royalty | H94: =SUM(H91:H93) -> 4.6041058 | I94: =SUM(I91:I93) -> 4.9559562 | J94: =SUM(J91:J93) -> 5.4653746 | K94: =SUM(K91:K93) -> 6.1395363 | L94: =SUM(L91:L93) -> 6.6352596 | M94: =SUM(M91:M93) -> 6.7099284 | N94: =SUM(N91:N93) -> 6.913514 | O94: =SUM(O91:O93) -> 7.2082959 | ... AB94: =SUM(AB91:AB93) -> 159.63088
E95: % Royalty | H95: =+H96/H94 -> 0.7 | I95: =+I96/I94 -> 0.7 | J95: =+J96/J94 -> 0.7 | K95: =+K96/K94 -> 0.7 | L95: =+L96/L94 -> 0.7 | M95: =+M96/M94 -> 0.7 | N95: =+N96/N94 -> 0.7 | O95: =+O96/O94 -> 0.7 | ... AB95: =+AB96/AB94 -> 0.7
E96: MWS Royalty - 70% Split | H96: =MAX(2,70%*H94) -> 3.2228741 | I96: =MAX(2,70%*I94) -> 3.4691693 | J96: =MAX(2,70%*J94) -> 3.8257622 | K96: =MAX(2,70%*K94) -> 4.2976754 | L96: =MAX(2,70%*L94) -> 4.6446817 | M96: =MAX(2,70%*M94) -> 4.6969499 | N96: =MAX(2,70%*N94) -> 4.8394598 | O96: =MAX(2,70%*O94) -> 5.0458071 | ... AA96: =MAX(2,70%*AA94) -> 6.6938813 | AB96: =SUM(H96:AA96) -> 111.74161
E97: Fixed Royalty | H97: 2 | I97: 2 | J97: 2 | K97: 2 | L97: 2 | M97: 2 | N97: 2 | O97: 2 | P97: 2 | Q97: 2 | R97: 2 | S97: 2 | T97: 2 | U97: 2 | V97: 2 | W97: 2 | X97: 2 | Y97: 2 | Z97: 2 | AA97: 2 | AB97: =SUM(H97:AA97) -> 40
E98: Variable Royalty | H98: =H96-H97 -> 1.2228741 | I98: =I96-I97 -> 1.4691693 | J98: =J96-J97 -> 1.8257622 | K98: =K96-K97 -> 2.2976754 | L98: =L96-L97 -> 2.6446817 | M98: =M96-M97 -> 2.6969499 | N98: =N96-N97 -> 2.8394598 | O98: =O96-O97 -> 3.0458071 | ... AA98: =AA96-AA97 -> 4.6938813 | AB98: =SUM(H98:AA98) -> 71.741614
E100: Net Offtake Revenue (>$14MM) | H100: =MAX(0,H89-14) -> 0 | I100: =MAX(0,I89-14) -> 0 | J100: =MAX(0,J89-14) -> 0 | K100: =MAX(0,K89-14) -> 0 | L100: =MAX(0,L89-14) -> 0 | M100: =MAX(0,M89-14) -> 0 | N100: =MAX(0,N89-14) -> 0 | O100: =MAX(0,O89-14) -> 0 | ... AA100: =MAX(0,AA89-14) -> 6.0740054 | AB100: =SUM(H100:AA100) -> 25.755738
E101: MWS Royalty - 90% Split | H101: =0.9*H100 -> 0 | I101: =0.9*I100 -> 0 | J101: =0.9*J100 -> 0 | K101: =0.9*K100 -> 0 | L101: =0.9*L100 -> 0 | M101: =0.9*M100 -> 0 | N101: =0.9*N100 -> 0 | O101: =0.9*O100 -> 0 | ... AA101: =0.9*AA100 -> 5.4666049 | AB101: =SUM(H101:AA101) -> 23.180164
E103: Royalty Calculation ($ in '000) | H103: 1 | I103: 5 | J103: 10 | K103: 15 | L103: 20 | M103: TOTAL
E105: Biogas, scfm | H105: =_xlfn.XLOOKUP(H$61,$H$42:$AB$42,$H82:$AB82) -> 950 | I105: =_xlfn.XLOOKUP(I$61,$H$42:$AB$42,$H82:$AB82) -> 1045.924 | J105: =_xlfn.XLOOKUP(J$61,$H$42:$AB$42,$H82:$AB82) -> 1179.5621 | K105: =_xlfn.XLOOKUP(K$61,$H$42:$AB$42,$H82:$AB82) -> 1330.2751 | L105: =_xlfn.XLOOKUP(L$61,$H$42:$AB$42,$H82:$AB82) -> 1500.2447 | M105: =_xlfn.XLOOKUP(M$61,$H$42:$AB$42,$H82:$AB82) -> 1205.3424
E106: RNG Production, K MMBtu | H106: =_xlfn.XLOOKUP(H$61,$H$42:$AB$42,$H83:$AB83) -> 319.40093 | I106: =_xlfn.XLOOKUP(I$61,$H$42:$AB$42,$H83:$AB83) -> 351.65169 | J106: =_xlfn.XLOOKUP(J$61,$H$42:$AB$42,$H83:$AB83) -> 396.58234 | K106: =_xlfn.XLOOKUP(K$61,$H$42:$AB$42,$H83:$AB83) -> 447.25379 | L106: =_xlfn.XLOOKUP(L$61,$H$42:$AB$42,$H83:$AB83) -> 504.39955 | M106: =_xlfn.XLOOKUP(M$61,$H$42:$AB$42,$H83:$AB83) -> 8105
E107: D3 RIN Price, $/RIN | H107: =_xlfn.XLOOKUP(H$61,$H$42:$AB$42,$H84:$AB84) -> 2.6619581 | I107: =_xlfn.XLOOKUP(I$61,$H$42:$AB$42,$H84:$AB84) -> 2.9781765 | J107: =_xlfn.XLOOKUP(J$61,$H$42:$AB$42,$H84:$AB84) -> 2.9947832 | K107: =_xlfn.XLOOKUP(K$61,$H$42:$AB$42,$H84:$AB84) -> 3.318756 | L107: =_xlfn.XLOOKUP(L$61,$H$42:$AB$42,$H84:$AB84) -> 3.6777758 | M107: =_xlfn.XLOOKUP(M$61,$H$42:$AB$42,$H84:$AB84) -> 3.1120546
E109: EA RIN Sale | H109: =_xlfn.XLOOKUP(H$61,$H$42:$AB$42,$H86:$AB86) -> 9.9706695 | I109: =_xlfn.XLOOKUP(I$61,$H$42:$AB$42,$H86:$AB86) -> 12.281462 | J109: =_xlfn.XLOOKUP(J$61,$H$42:$AB$42,$H86:$AB86) -> 13.927901 | K109: =_xlfn.XLOOKUP(K$61,$H$42:$AB$42,$H86:$AB86) -> 17.406693 | L109: =_xlfn.XLOOKUP(L$61,$H$42:$AB$42,$H86:$AB86) -> 21.754387 | M109: =_xlfn.XLOOKUP(M$61,$H$42:$AB$42,$H86:$AB86) -> 299.56481
E110: (-) RIN Managament | H110: =_xlfn.XLOOKUP(H$61,$H$42:$AB$42,$H87:$AB87) -> -1.9941339 | I110: =_xlfn.XLOOKUP(I$61,$H$42:$AB$42,$H87:$AB87) -> -2.4562924 | J110: =_xlfn.XLOOKUP(J$61,$H$42:$AB$42,$H87:$AB87) -> -2.7855803 | K110: =_xlfn.XLOOKUP(K$61,$H$42:$AB$42,$H87:$AB87) -> -3.4813386 | L110: =_xlfn.XLOOKUP(L$61,$H$42:$AB$42,$H87:$AB87) -> -4.3508775 | M110: =_xlfn.XLOOKUP(M$61,$H$42:$AB$42,$H87:$AB87) -> -59.912961
E111: (+) Nat. Gas Sale | H111: =_xlfn.XLOOKUP(H$61,$H$42:$AB$42,$H88:$AB88) -> 1.0648827 | I111: =_xlfn.XLOOKUP(I$61,$H$42:$AB$42,$H88:$AB88) -> 1.2474025 | J111: =_xlfn.XLOOKUP(J$61,$H$42:$AB$42,$H88:$AB88) -> 1.6098864 | K111: =_xlfn.XLOOKUP(K$61,$H$42:$AB$42,$H88:$AB88) -> 2.0747349 | L111: =_xlfn.XLOOKUP(L$61,$H$42:$AB$42,$H88:$AB88) -> 2.6704954 | M111: =_xlfn.XLOOKUP(M$61,$H$42:$AB$42,$H88:$AB88) -> 34.481019
E112: Net Offtake Revenue | H112: =SUM(H109:H111) -> 9.0414183 | I112: =SUM(I109:I111) -> 11.072572 | J112: =SUM(J109:J111) -> 12.752207 | K112: =SUM(K109:K111) -> 16.000089 | L112: =SUM(L109:L111) -> 20.074005 | M112: =SUM(M109:M111) -> 274.13286
E113: (1) Net Offtake Revenue (< $14MM) | H113: =_xlfn.XLOOKUP(H$61,$H$42:$AB$42,$H91:$AB91) -> 9.0414183 | I113: =_xlfn.XLOOKUP(I$61,$H$42:$AB$42,$H91:$AB91) -> 11.072572 | J113: =_xlfn.XLOOKUP(J$61,$H$42:$AB$42,$H91:$AB91) -> 12.752207 | K113: =_xlfn.XLOOKUP(K$61,$H$42:$AB$42,$H91:$AB91) -> 14 | L113: =_xlfn.XLOOKUP(L$61,$H$42:$AB$42,$H91:$AB91) -> 14 | M113: =_xlfn.XLOOKUP(M$61,$H$42:$AB$42,$H91:$AB91) -> 248.37713
E114: (-) Capex Allowance | H114: =_xlfn.XLOOKUP(H$61,$H$42:$AB$42,$H92:$AB92) -> -1.84175 | I114: =_xlfn.XLOOKUP(I$61,$H$42:$AB$42,$H92:$AB92) -> -1.84175 | J114: =_xlfn.XLOOKUP(J$61,$H$42:$AB$42,$H92:$AB92) -> -1.84175 | K114: =_xlfn.XLOOKUP(K$61,$H$42:$AB$42,$H92:$AB92) -> -1.84175 | L114: =_xlfn.XLOOKUP(L$61,$H$42:$AB$42,$H92:$AB92) -> -1.84175 | M114: =_xlfn.XLOOKUP(M$61,$H$42:$AB$42,$H92:$AB92) -> -36.835
E115: (-) Opex and Maintenance Allowance | H115: =_xlfn.XLOOKUP(H$61,$H$42:$AB$42,$H93:$AB93) -> -2.5955625 | I115: =_xlfn.XLOOKUP(I$61,$H$42:$AB$42,$H93:$AB93) -> -2.5955625 | J115: =_xlfn.XLOOKUP(J$61,$H$42:$AB$42,$H93:$AB93) -> -2.5955625 | K115: =_xlfn.XLOOKUP(K$61,$H$42:$AB$42,$H93:$AB93) -> -2.5955625 | L115: =_xlfn.XLOOKUP(L$61,$H$42:$AB$42,$H93:$AB93) -> -2.5955625 | M115: =_xlfn.XLOOKUP(M$61,$H$42:$AB$42,$H93:$AB93) -> -51.91125
E116: Amount Avail. For Royalty | H116: =SUM(H113:H115) -> 4.6041058 | I116: =SUM(I113:I115) -> 6.6352596 | J116: =SUM(J113:J115) -> 8.314895 | K116: =SUM(K113:K115) -> 9.5626875 | L116: =SUM(L113:L115) -> 9.5626875 | M116: =SUM(M113:M115) -> 159.63088
E117: % Royalty | H117: =_xlfn.XLOOKUP(H$61,$H$42:$AB$42,$H95:$AB95) -> 0.7 | I117: =_xlfn.XLOOKUP(I$61,$H$42:$AB$42,$H95:$AB95) -> 0.7 | J117: =_xlfn.XLOOKUP(J$61,$H$42:$AB$42,$H95:$AB95) -> 0.7 | K117: =_xlfn.XLOOKUP(K$61,$H$42:$AB$42,$H95:$AB95) -> 0.7 | L117: =_xlfn.XLOOKUP(L$61,$H$42:$AB$42,$H95:$AB95) -> 0.7 | M117: =_xlfn.XLOOKUP(M$61,$H$42:$AB$42,$H95:$AB95) -> 0.7
E118: MWS Royalty - 70% Split | H118: =_xlfn.XLOOKUP(H$61,$H$42:$AB$42,$H96:$AB96) -> 3.2228741 | I118: =_xlfn.XLOOKUP(I$61,$H$42:$AB$42,$H96:$AB96) -> 4.6446817 | J118: =_xlfn.XLOOKUP(J$61,$H$42:$AB$42,$H96:$AB96) -> 5.8204265 | K118: =_xlfn.XLOOKUP(K$61,$H$42:$AB$42,$H96:$AB96) -> 6.6938813 | L118: =_xlfn.XLOOKUP(L$61,$H$42:$AB$42,$H96:$AB96) -> 6.6938813 | M118: =_xlfn.XLOOKUP(M$61,$H$42:$AB$42,$H96:$AB96) -> 111.74161
E119: Fixed Royalty | H119: =_xlfn.XLOOKUP(H$61,$H$42:$AB$42,$H97:$AB97) -> 2 | I119: =_xlfn.XLOOKUP(I$61,$H$42:$AB$42,$H97:$AB97) -> 2 | J119: =_xlfn.XLOOKUP(J$61,$H$42:$AB$42,$H97:$AB97) -> 2 | K119: =_xlfn.XLOOKUP(K$61,$H$42:$AB$42,$H97:$AB97) -> 2 | L119: =_xlfn.XLOOKUP(L$61,$H$42:$AB$42,$H97:$AB97) -> 2 | M119: =_xlfn.XLOOKUP(M$61,$H$42:$AB$42,$H97:$AB97) -> 40
E120: Variable Royalty | H120: =_xlfn.XLOOKUP(H$61,$H$42:$AB$42,$H98:$AB98) -> 1.2228741 | I120: =_xlfn.XLOOKUP(I$61,$H$42:$AB$42,$H98:$AB98) -> 2.6446817 | J120: =_xlfn.XLOOKUP(J$61,$H$42:$AB$42,$H98:$AB98) -> 3.8204265 | K120: =_xlfn.XLOOKUP(K$61,$H$42:$AB$42,$H98:$AB98) -> 4.6938813 | L120: =_xlfn.XLOOKUP(L$61,$H$42:$AB$42,$H98:$AB98) -> 4.6938813 | M120: =_xlfn.XLOOKUP(M$61,$H$42:$AB$42,$H98:$AB98) -> 71.741614
E122: (2) Net Offtake Revenue above $14MM | H122: =_xlfn.XLOOKUP(H$61,$H$42:$AB$42,$H100:$AB100) -> 0 | I122: =_xlfn.XLOOKUP(I$61,$H$42:$AB$42,$H100:$AB100) -> 0 | J122: =_xlfn.XLOOKUP(J$61,$H$42:$AB$42,$H100:$AB100) -> 0 | K122: =_xlfn.XLOOKUP(K$61,$H$42:$AB$42,$H100:$AB100) -> 2.0000894 | L122: =_xlfn.XLOOKUP(L$61,$H$42:$AB$42,$H100:$AB100) -> 6.0740054 | M122: =_xlfn.XLOOKUP(M$61,$H$42:$AB$42,$H100:$AB100) -> 25.755738
E123: MWS Royalty - 90% Split | H123: =_xlfn.XLOOKUP(H$61,$H$42:$AB$42,$H101:$AB101) -> 0 | I123: =_xlfn.XLOOKUP(I$61,$H$42:$AB$42,$H101:$AB101) -> 0 | J123: =_xlfn.XLOOKUP(J$61,$H$42:$AB$42,$H101:$AB101) -> 0 | K123: =_xlfn.XLOOKUP(K$61,$H$42:$AB$42,$H101:$AB101) -> 1.8000805 | L123: =_xlfn.XLOOKUP(L$61,$H$42:$AB$42,$H101:$AB101) -> 5.4666049 | M123: =_xlfn.XLOOKUP(M$61,$H$42:$AB$42,$H101:$AB101) -> 23.180164 | N123: =+P123-O123 -> 5.1511476 | O123: =+M122*0.7 -> 18.029017 | P123: =+M122*0.9 -> 23.180164
E125: Total MWS Royalty | H125: =+H118+H123 -> 3.2228741 | I125: =+I118+I123 -> 4.6446817 | J125: =+J118+J123 -> 5.8204265 | K125: =+K118+K123 -> 8.4939617 | L125: =+L118+L123 -> 12.160486 | M125: =+M118+M123 -> 134.92178

Sheet data-->

Sheet Bid Forms
B1: Revised Bid Form - NOT OUR PROPOSAL | H1: Original Bid Form
B3: Company Name: | D3: Burnham RNG, LLC
B4: Line Item Number | C4: Description | E4: Unit | F4: Extended amount
B5: 1 | C5: 20- year Evaluative Value of the sale of RNG and EAs | D5: 219100000 | E5: $ | F5: =D5 -> 219100000 | I5: =170.5/0.8 -> 213.125
B6: 2 | C6: Capital Cost Allowance | D6: =+INPUTS!S24*1000 -> 36835000 | E6: $ | F6: =D6 -> 36835000
B7: 3 | C7: Capital Cost Financing Fee | D7: 0 | E7: % | F7: =D6*D7 -> 0
B8: 4 | C8: 20-year Allowance for Operations and Maintenance | D8: =+ROUND(SUM(INPUTS!S25:S26)/100,0)*10^5-F7 -> 65500000 | E8: $ | F8: =D8 -> 65500000
B9: 5 | C9: 20-year Allowance for RIN Management | D9: 0.2 | E9: % | F9: =F5*D9 -> 43820000
B10: 6 | C10: 20 year Evaluative Net Proceeds | D10: =D5-F6-F7-F8-F9 -> 72945000 | E10: $ | F10: =D10 -> 72945000
B11: 7 | C11: Percentage of Net Proceeds offered for Royalty Payments | D11: =+D12/D10 -> #REF! | E11: % | F11: =F10*D11 -> #REF!
B12: 8 | C12: 20-year value of Fixed Royalty Payments | D12: =+ROUND(Model!#REF!/100,0)*10^5 -> #REF! | E12: $ | F12: 40000000
B13: 9 | C13: 20-year value of Variable Royalty Payment (cannot be less than zero). | F13: =IF((F10*D11-F12)<0,0,(F10*D11-F12)) -> #REF!
B14: Total Evaluative Contract Value to Metro Water Services | E14: =F12+F13 -> #REF!
B15: This form is for evaluation of proposals. Actual Variable Royalty Payment will be determined using actual Capital Cost, Actual O&M Cost, actual Third Party Fees, and actual value of sales of RNG and Environment Attributes.
B16: Basis for 20 year evaluative value. These amounts are for evaluative purposes only and are not guaranteed by MWS nor Burnham RNG, LLC. 6,605,287 DTH of Biogas. 850 cfm year 0 increasing 2.5%/year upto 1,500 cfm year 20 600 BTU/CF Biogas 90% uptime of RNG Facility 97% capture of Methane by RNG Facility $2.39/rin year 0 and escalated 1% per year $3.20/DTH less $1.00/DTH wheel tax year 0. Methane value escalated at 3%/year.
B21: Company Name: | D21: Burnham RNG, LLC
B22: Line Item Number | C22: Description | E22: Unit | F22: Extended amount
B23: 1 | C23: 20- year Evaluative Value of the sale of RNG and EAs | D23: 219100000 | E23: $ | F23: =D23 -> 219100000 | I23: RIN EA | J23: =+Model!E28 -> 299564.81
B24: 2 | C24: Capital Cost Allowance | D24: =+D6 -> 36835000 | E24: $ | F24: =D24 -> 36835000 | I24: Nat. Gas | J24: =+Model!E30 -> 34481.019
B25: 3 | C25: Capital Cost Financing Fee | D25: 0.25 | E25: % | F25: =D24*D25 -> 9208750 | I25: RIN Brokerage | J25: =0.2*J23 -> 59912.961
B26: 4 | C26: 20-year Allowance for Operations and Maintenance | D26: =61120000-F25 -> 51911250 | E26: $ | F26: =D26 -> 51911250 | H26: =+F26/1000 -> 51911.25
B27: 5 | C27: 20-year Allowance for RIN Management | D27: 0.2 | E27: % | F27: =+J25*1000 -> 59912961
B28: 6 | C28: 20 year Evaluative Net Proceeds | D28: =D23-F24-F25-F26-F27 -> 61232039 | E28: $ | F28: =D28 -> 61232039
B29: 7 | C29: Percentage of Net Proceeds offered for Royalty Payments | D29: 0.7 | E29: % | F29: =F28*D29 -> 42862427
B30: 8 | C30: 20-year value of Fixed Royalty Payments | D30: =+D28*D29 -> 42862427 | E30: $ | F30: 40000000
B31: 9 | C31: 20-year value of Variable Royalty Payment ( > 0 ) | F31: =IF((F28*D29-F30)<0,0,(F28*D29-F30)) -> 2862427.1
B32: Total Evaluative Contract Value to Metro Water Services | E32: =F30+F31 -> 42862427
B33: This form is for evaluation of proposals. Actual Variable Royalty Payment will be determined using actual Capital Cost, Actual O&M Cost, actual Third Party Fees, and actual value of sales of RNG and Environment Attributes.
D36: $MM | J36: =+F23/10^6 -> 219.1
C37: 20- year Evaluative Value of the sale of RNG and EAs | D37: 219.1 | J37: =-F27/10^6 -> -59.912961
C38: 20-year Allowance for RIN Management | D38: =-J25/1000 -> -59.912961 | J38: =SUM(J36:J37) -> 159.18704
C39: 20- year Evaluative Value RNG and EAs after brokerage | D39: =SUM(D37:D38) -> 159.18704 | J39: =-F24/10^6 -> -36.835
C40: (-) Previous Evaluative Value of RNG and EAs | D40: -170.5 | J40: =-F26/10^6 -> -51.91125
C41: Incremental Offtake Value | D41: =+SUM(D39:D40) -> -11.312961 | J41: =SUM(J38:J40) -> 70.440789
C42: Previous Sharing Pct | D42: 0.45 | J42: -40
C43: Incremental Royalty Expected | D43: =+D42*D41 -> -5.0908326 | J43: =-D45-J42 -> -8.0091674
C44: (+) Previous Total Evaluative Contract Value to MWS | D44: 53.1
C45: Updated Total Evaluative Contract Value to MWS | D45: =SUM(D43:D44) -> 48.009167
J55: =J36 -> 219.1
J56: =J37 -> -59.912961
J57: =SUM(J55:J56) -> 159.18704
J58: =J42 -> -40
J59: =J39 -> -36.835
J60: =J40 -> -51.91125
J61: =SUM(J57:J60) -> 30.440789
J62: =J43 -> -8.0091674
J63: =+SUM(J61:J62) -> 22.431621

Sheet HenryHub
B1: Updated | C1: 46052
B3: Period | C3: Price | D3: Year | E3: Real time data retrieval (right click the table and click 'Refresh')
B4: Mar '26 | C4: 4.37 | D4: 2026
B5: Apr '26 | C5: 4.041 | D5: 2026
B6: May '26 | C6: 4.022 | D6: 2026
B7: Jun '26 | C7: 4.17 | D7: 2026
B8: Jul '26 | C8: 4.352 | D8: 2026
B9: Aug '26 | C9: 4.383 | D9: 2026
B10: Sep '26 | C10: 4.346 | D10: 2026
B11: Oct '26 | C11: 4.399 | D11: 2026
B12: Nov '26 | C12: 4.577 | D12: 2026
B13: Dec '26 | C13: 5.086 | D13: 2026
B14: Jan '27 | C14: 5.397 | D14: 2027
B15: Feb '27 | C15: 4.794 | D15: 2027
... B20: &QNG&C29 | C20: 3.619 | D20: 2029
B23: Source: | C23: https://pricing.ems.schneider-electric.com/cme/ngco/default.aspx
C27: NYMEX (HHub) | D27: Basis | E27: Tenn City Gate
B28: 2026 | C28: =AVERAGEIFS(HenryHub[Price],HenryHub[Year],B28) -> 4.3746 | D28: 0.65 | E28: =C28+D28 -> 5.0246
B29: =+B28+1 -> 2027 | C29: =AVERAGEIFS(HenryHub[Price],HenryHub[Year],B29) -> 4.2616 | D29: =+D28 -> 0.65 | E29: =C29+D29 -> 4.9116
B30: =+B29+1 -> 2028 | C30: =AVERAGEIFS(HenryHub[Price],HenryHub[Year],B30) -> 3.684 | D30: =+D29 -> 0.65 | E30: =C30+D30 -> 4.334
B31: =+B30+1 -> 2029 | C31: =AVERAGEIFS(HenryHub[Price],HenryHub[Year],B31) -> 3.619 | D31: =+D30 -> 0.65 | E31: =C31+D31 -> 4.269
B32: =+B31+1 -> 2030 | C32: =+C31*(1+$A$33) -> 3.709475 | D32: =+D31 -> 0.65 | E32: =C32+D32 -> 4.359475
A33: =+INPUTS!$E$6 -> 0.025 | B33: =+B32+1 -> 2031 | C33: =+C32*(1+$A$33) -> 3.8022119 | D33: =+D32 -> 0.65 | E33: =C33+D33 -> 4.4522119
B34: =+B33+1 -> 2032 | C34: =+C33*(1+$A$33) -> 3.8972672 | D34: =+D33 -> 0.65 | E34: =C34+D34 -> 4.5472672
B35: =+B34+1 -> 2033 | C35: =+C34*(1+$A$33) -> 3.9946989 | D35: =+D34 -> 0.65 | E35: =C35+D35 -> 4.6446989
B36: =+B35+1 -> 2034 | C36: =+C35*(1+$A$33) -> 4.0945663 | D36: =+D35 -> 0.65 | E36: =C36+D36 -> 4.7445663
B37: =+B36+1 -> 2035 | C37: =+C36*(1+$A$33) -> 4.1969305 | D37: =+D36 -> 0.65 | E37: =C37+D37 -> 4.8469305
B38: =+B37+1 -> 2036 | C38: =+C37*(1+$A$33) -> 4.3018537 | D38: =+D37 -> 0.65 | E38: =C38+D38 -> 4.9518537
B39: =+B38+1 -> 2037 | C39: =+C38*(1+$A$33) -> 4.4094001 | D39: =+D38 -> 0.65 | E39: =C39+D39 -> 5.0594001
B40: =+B39+1 -> 2038 | C40: =+C39*(1+$A$33) -> 4.5196351 | D40: =+D39 -> 0.65 | E40: =C40+D40 -> 5.1696351
B41: =+B40+1 -> 2039 | C41: =+C40*(1+$A$33) -> 4.632626 | D41: =+D40 -> 0.65 | E41: =C41+D41 -> 5.282626
B42: =+B41+1 -> 2040 | C42: =+C41*(1+$A$33) -> 4.7484416 | D42: =+D41 -> 0.65 | E42: =C42+D42 -> 5.3984416
B43: =+B42+1 -> 2041 | C43: =+C42*(1+$A$33) -> 4.8671527 | D43: =+D42 -> 0.65 | E43: =C43+D43 -> 5.5171527
B44: =+B43+1 -> 2042 | C44: =+C43*(1+$A$33) -> 4.9888315 | D44: =+D43 -> 0.65 | E44: =C44+D44 -> 5.6388315
B45: =+B44+1 -> 2043 | C45: =+C44*(1+$A$33) -> 5.1135523 | D45: =+D44 -> 0.65 | E45: =C45+D45 -> 5.7635523
... B52: =+B51+1 -> 2050 | C52: =+C51*(1+$A$33) -> 6.0784067 | D52: =+D51 -> 0.65 | E52: =C52+D52 -> 6.7284067

Sheet RIN Curves
I1: =+INPUTS!E18 -> 0.01 | K1: =+(J18/J6)^(1/12)-1 -> 0.10499923 | L1: 0.25 | M1: =+K1*L1 -> 0.026249808
D2: Sagepoint D3 RIN Price Case | H2: Ares | I2: =TEXT(I21, "$0.00")&" esc. @ "&TEXT(I1,"0.0%") -> $2.39 esc. @ 1.0% | J2: Historical | K2: ="Hist Extrapolated @ "&TEXT(M1,"0.0%")&" ( "&TEXT(L1,"0%")&" of 2013-2025 CAGR)" -> Hist Extrapolated @ 2.6% ( 25% of 2013-2025 CAGR)
D3: Dynamic | G3: Year | H3: D3 RIN
G5: 2013
G6: 2013 | J6: 0.735
G7: 2014 | J7: 0.94537037
G8: 2015 | J8: 1.1598291
G9: 2016 | J9: 2.0779231
G10: 2017 | J10: 2.449469
G11: 2018 | J11: 1.8759259
G12: 2019 | J12: 1.4938525
G13: 2020 | J13: 2.1900714
G14: 2021 | J14: 2.7803571
G15: 2022 | J15: 2.7842568
G16: 2023 | J16: 2.7536207
G17: 2024 | J17: 2.8623016
B18: 45322 | C18: $/RIN | D18: 3.23884 | E18: =YEAR(B18) -> 2024 | G18: 2025 | H18: =AVERAGEIFS($D$18:$D$341,$E$18:$E$341,$G18) -> 2.3404618 | J18: 2.4357407
B19: =EOMONTH(B18,1) -> 45351 | C19: $/RIN | D19: 3.23884 | E19: =YEAR(B19) -> 2024 | G19: =+G18+1 -> 2026 | H19: =AVERAGEIFS($D$18:$D$341,$E$18:$E$341,$G19) -> 2.4896873
B20: =EOMONTH(B19,1) -> 45382 | C20: $/RIN | D20: 3.23884 | E20: =YEAR(B20) -> 2024 | G20: =+G19+1 -> 2027 | H20: =AVERAGEIFS($D$18:$D$341,$E$18:$E$341,$G20) -> 2.6040894
B21: =EOMONTH(B20,1) -> 45412 | C21: $/RIN | D21: 3.23884 | E21: =YEAR(B21) -> 2024 | G21: =+G20+1 -> 2028 | H21: =AVERAGEIFS($D$18:$D$341,$E$18:$E$341,$G21) -> 2.6619581 | I21: =INPUTS!G17 -> 2.39 | K21: =+J18*(1+$K$1*$L$1) -> 2.4996785
B22: =EOMONTH(B21,1) -> 45443 | C22: $/RIN | D22: 3.23884 | E22: =YEAR(B22) -> 2024 | G22: =+G21+1 -> 2029 | H22: =AVERAGEIFS($D$18:$D$341,$E$18:$E$341,$G22) -> 2.7118204 | I22: =I21*(1+INPUTS!$E$18) -> 2.4139 | K22: =+K21*(1+$K$1*$L$1) -> 2.5652945
B23: =EOMONTH(B22,1) -> 45473 | C23: $/RIN | D23: 3.23884 | E23: =YEAR(B23) -> 2024 | G23: =+G22+1 -> 2030 | H23: =AVERAGEIFS($D$18:$D$341,$E$18:$E$341,$G23) -> 2.7914813 | I23: =I22*(1+INPUTS!$E$18) -> 2.438039 | K23: =+K22*(1+$K$1*$L$1) -> 2.632633
B24: =EOMONTH(B23,1) -> 45504 | C24: $/RIN | D24: 3.23884 | E24: =YEAR(B24) -> 2024 | G24: =+G23+1 -> 2031 | H24: =AVERAGEIFS($D$18:$D$341,$E$18:$E$341,$G24) -> 2.9160811 | I24: =I23*(1+INPUTS!$E$18) -> 2.4624194 | K24: =+K23*(1+$K$1*$L$1) -> 2.7017392
B25: =EOMONTH(B24,1) -> 45535 | C25: $/RIN | D25: 3.23884 | E25: =YEAR(B25) -> 2024 | G25: =+G24+1 -> 2032 | H25: =AVERAGEIFS($D$18:$D$341,$E$18:$E$341,$G25) -> 2.9781765 | I25: =I24*(1+INPUTS!$E$18) -> 2.4870436 | K25: =+K24*(1+$K$1*$L$1) -> 2.7726593
B26: =EOMONTH(B25,1) -> 45565 | C26: $/RIN | D26: 3.23884 | E26: =YEAR(B26) -> 2024 | G26: =+G25+1 -> 2033 | H26: =AVERAGEIFS($D$18:$D$341,$E$18:$E$341,$G26) -> 2.9101359 | I26: =I25*(1+INPUTS!$E$18) -> 2.511914 | K26: =+K25*(1+$K$1*$L$1) -> 2.8454411
B27: =EOMONTH(B26,1) -> 45596 | C27: $/RIN | D27: 3.23884 | E27: =YEAR(B27) -> 2024 | G27: =+G26+1 -> 2034 | H27: =AVERAGEIFS($D$18:$D$341,$E$18:$E$341,$G27) -> 2.8799224 | I27: =I26*(1+INPUTS!$E$18) -> 2.5370332 | K27: =+K26*(1+$K$1*$L$1) -> 2.9201333
B28: =EOMONTH(B27,1) -> 45626 | C28: $/RIN | D28: 3.23884 | E28: =YEAR(B28) -> 2024 | G28: =+G27+1 -> 2035 | H28: =AVERAGEIFS($D$18:$D$341,$E$18:$E$341,$G28) -> 2.8742294 | I28: =I27*(1+INPUTS!$E$18) -> 2.5624035 | K28: =+K27*(1+$K$1*$L$1) -> 2.9967863
B29: =EOMONTH(B28,1) -> 45657 | C29: $/RIN | D29: 3.23884 | E29: =YEAR(B29) -> 2024 | G29: =+G28+1 -> 2036 | H29: =AVERAGEIFS($D$18:$D$341,$E$18:$E$341,$G29) -> 2.9338872 | I29: =I28*(1+INPUTS!$E$18) -> 2.5880275 | K29: =+K28*(1+$K$1*$L$1) -> 3.0754514
B30: =EOMONTH(B29,1) -> 45688 | C30: $/RIN | D30: =_xlfn.XLOOKUP(E30,'D3 Forecast Stratas Dec25'!$I$4:$AH$4,'D3 Forecast Stratas Dec25'!$I$6:$AH$6,0) -> 2.3404618 | E30: =YEAR(B30) -> 2025 | G30: =+G29+1 -> 2037 | H30: =AVERAGEIFS($D$18:$D$341,$E$18:$E$341,$G30) -> 2.9947832 | I30: =I29*(1+INPUTS!$E$18) -> 2.6139078 | K30: =+K29*(1+$K$1*$L$1) -> 3.1561814
B31: =EOMONTH(B30,1) -> 45716 | C31: $/RIN | D31: =_xlfn.XLOOKUP(E31,'D3 Forecast Stratas Dec25'!$I$4:$AH$4,'D3 Forecast Stratas Dec25'!$I$6:$AH$6,0) -> 2.3404618 | E31: =YEAR(B31) -> 2025 | G31: =+G30+1 -> 2038 | H31: =AVERAGEIFS($D$18:$D$341,$E$18:$E$341,$G31) -> 3.0569433 | I31: =I30*(1+INPUTS!$E$18) -> 2.6400469 | K31: =+K30*(1+$K$1*$L$1) -> 3.2390305
B32: =EOMONTH(B31,1) -> 45747 | C32: $/RIN | D32: =_xlfn.XLOOKUP(E32,'D3 Forecast Stratas Dec25'!$I$4:$AH$4,'D3 Forecast Stratas Dec25'!$I$6:$AH$6,0) -> 2.3404618 | E32: =YEAR(B32) -> 2025 | G32: =+G31+1 -> 2039 | H32: =AVERAGEIFS($D$18:$D$341,$E$18:$E$341,$G32) -> 3.1203935 | I32: =I31*(1+INPUTS!$E$18) -> 2.6664473 | K32: =+K31*(1+$K$1*$L$1) -> 3.3240544
B33: =EOMONTH(B32,1) -> 45777 | C33: $/RIN | D33: =_xlfn.XLOOKUP(E33,'D3 Forecast Stratas Dec25'!$I$4:$AH$4,'D3 Forecast Stratas Dec25'!$I$6:$AH$6,0) -> 2.3404618 | E33: =YEAR(B33) -> 2025 | G33: =+G32+1 -> 2040 | H33: =AVERAGEIFS($D$18:$D$341,$E$18:$E$341,$G33) -> 3.1851607 | I33: =I32*(1+INPUTS!$E$18) -> 2.6931118 | K33: =+K32*(1+$K$1*$L$1) -> 3.4113102
B34: =EOMONTH(B33,1) -> 45808 | C34: $/RIN | D34: =_xlfn.XLOOKUP(E34,'D3 Forecast Stratas Dec25'!$I$4:$AH$4,'D3 Forecast Stratas Dec25'!$I$6:$AH$6,0) -> 2.3404618 | E34: =YEAR(B34) -> 2025 | G34: =+G33+1 -> 2041 | H34: =AVERAGEIFS($D$18:$D$341,$E$18:$E$341,$G34) -> 3.2512722 | I34: =I33*(1+INPUTS!$E$18) -> 2.7200429 | K34: =+K33*(1+$K$1*$L$1) -> 3.5008565
B35: =EOMONTH(B34,1) -> 45838 | C35: $/RIN | D35: =_xlfn.XLOOKUP(E35,'D3 Forecast Stratas Dec25'!$I$4:$AH$4,'D3 Forecast Stratas Dec25'!$I$6:$AH$6,0) -> 2.3404618 | E35: =YEAR(B35) -> 2025 | G35: =+G34+1 -> 2042 | H35: =AVERAGEIFS($D$18:$D$341,$E$18:$E$341,$G35) -> 3.318756 | I35: =I34*(1+INPUTS!$E$18) -> 2.7472434 | K35: =+K34*(1+$K$1*$L$1) -> 3.5927533
B36: =EOMONTH(B35,1) -> 45869 | C36: $/RIN | D36: =_xlfn.XLOOKUP(E36,'D3 Forecast Stratas Dec25'!$I$4:$AH$4,'D3 Forecast Stratas Dec25'!$I$6:$AH$6,0) -> 2.3404618 | E36: =YEAR(B36) -> 2025 | G36: =+G35+1 -> 2043 | H36: =AVERAGEIFS($D$18:$D$341,$E$18:$E$341,$G36) -> 3.3876404 | I36: =I35*(1+INPUTS!$E$18) -> 2.7747158 | K36: =+K35*(1+$K$1*$L$1) -> 3.6870624
B37: =EOMONTH(B36,1) -> 45900 | C37: $/RIN | D37: =_xlfn.XLOOKUP(E37,'D3 Forecast Stratas Dec25'!$I$4:$AH$4,'D3 Forecast Stratas Dec25'!$I$6:$AH$6,0) -> 2.3404618 | E37: =YEAR(B37) -> 2025 | G37: =+G36+1 -> 2044 | H37: =AVERAGEIFS($D$18:$D$341,$E$18:$E$341,$G37) -> 3.4579546 | I37: =I36*(1+INPUTS!$E$18) -> 2.802463 | K37: =+K36*(1+$K$1*$L$1) -> 3.7838471
B38: =EOMONTH(B37,1) -> 45930 | C38: $/RIN | D38: =_xlfn.XLOOKUP(E38,'D3 Forecast Stratas Dec25'!$I$4:$AH$4,'D3 Forecast Stratas Dec25'!$I$6:$AH$6,0) -> 2.3404618 | E38: =YEAR(B38) -> 2025 | G38: =+G37+1 -> 2045 | H38: =AVERAGEIFS($D$18:$D$341,$E$18:$E$341,$G38) -> 3.5297283 | I38: =I37*(1+INPUTS!$E$18) -> 2.8304876 | K38: =+K37*(1+$K$1*$L$1) -> 3.8831723
B39: =EOMONTH(B38,1) -> 45961 | C39: $/RIN | D39: =_xlfn.XLOOKUP(E39,'D3 Forecast Stratas Dec25'!$I$4:$AH$4,'D3 Forecast Stratas Dec25'!$I$6:$AH$6,0) -> 2.3404618 | E39: =YEAR(B39) -> 2025 | G39: =+G38+1 -> 2046 | H39: =AVERAGEIFS($D$18:$D$341,$E$18:$E$341,$G39) -> 3.6029917 | I39: =I38*(1+INPUTS!$E$18) -> 2.8587925 | K39: =+K38*(1+$K$1*$L$1) -> 3.9851048
B40: =EOMONTH(B39,1) -> 45991 | C40: $/RIN | D40: =_xlfn.XLOOKUP(E40,'D3 Forecast Stratas Dec25'!$I$4:$AH$4,'D3 Forecast Stratas Dec25'!$I$6:$AH$6,0) -> 2.3404618 | E40: =YEAR(B40) -> 2025 | G40: =+G39+1 -> 2047 | H40: =AVERAGEIFS($D$18:$D$341,$E$18:$E$341,$G40) -> 3.6777758 | I40: =I39*(1+INPUTS!$E$18) -> 2.8873804 | K40: =+K39*(1+$K$1*$L$1) -> 4.0897131
B41: =EOMONTH(B40,1) -> 46022 | C41: $/RIN | D41: =_xlfn.XLOOKUP(E41,'D3 Forecast Stratas Dec25'!$I$4:$AH$4,'D3 Forecast Stratas Dec25'!$I$6:$AH$6,0) -> 2.3404618 | E41: =YEAR(B41) -> 2025 | G41: =+G40+1 -> 2048 | H41: =AVERAGEIFS($D$18:$D$341,$E$18:$E$341,$G41) -> 3.7541121 | I41: =I40*(1+INPUTS!$E$18) -> 2.9162542 | K41: =+K40*(1+$K$1*$L$1) -> 4.1970673
... B44: =EOMONTH(B43,1) -> 46112 | C44: $/RIN | D44: =_xlfn.XLOOKUP(E44,'D3 Forecast Stratas Dec25'!$I$4:$AH$4,'D3 Forecast Stratas Dec25'!$I$6:$AH$6,0) -> 2.4896873 | E44: =YEAR(B44) -> 2026 | G44: =+G43+1 -> 2051 | H44: =AVERAGEIFS($D$18:$D$341,$E$18:$E$341,$G44) -> #DIV/0! | I44: =I43*(1+INPUTS!$E$18) -> 3.0046196 | K44: =+K43*(1+$K$1*$L$1) -> 4.5363358
B45: =EOMONTH(B44,1) -> 46142 | C45: $/RIN | D45: =_xlfn.XLOOKUP(E45,'D3 Forecast Stratas Dec25'!$I$4:$AH$4,'D3 Forecast Stratas Dec25'!$I$6:$AH$6,0) -> 2.4896873 | E45: =YEAR(B45) -> 2026
B46: =EOMONTH(B45,1) -> 46173 | C46: $/RIN | D46: =_xlfn.XLOOKUP(E46,'D3 Forecast Stratas Dec25'!$I$4:$AH$4,'D3 Forecast Stratas Dec25'!$I$6:$AH$6,0) -> 2.4896873 | E46: =YEAR(B46) -> 2026
B47: =EOMONTH(B46,1) -> 46203 | C47: $/RIN | D47: =_xlfn.XLOOKUP(E47,'D3 Forecast Stratas Dec25'!$I$4:$AH$4,'D3 Forecast Stratas Dec25'!$I$6:$AH$6,0) -> 2.4896873 | E47: =YEAR(B47) -> 2026
B48: =EOMONTH(B47,1) -> 46234 | C48: $/RIN | D48: =_xlfn.XLOOKUP(E48,'D3 Forecast Stratas Dec25'!$I$4:$AH$4,'D3 Forecast Stratas Dec25'!$I$6:$AH$6,0) -> 2.4896873 | E48: =YEAR(B48) -> 2026
B49: =EOMONTH(B48,1) -> 46265 | C49: $/RIN | D49: =_xlfn.XLOOKUP(E49,'D3 Forecast Stratas Dec25'!$I$4:$AH$4,'D3 Forecast Stratas Dec25'!$I$6:$AH$6,0) -> 2.4896873 | E49: =YEAR(B49) -> 2026
B50: =EOMONTH(B49,1) -> 46295 | C50: $/RIN | D50: =_xlfn.XLOOKUP(E50,'D3 Forecast Stratas Dec25'!$I$4:$AH$4,'D3 Forecast Stratas Dec25'!$I$6:$AH$6,0) -> 2.4896873 | E50: =YEAR(B50) -> 2026
B51: =EOMONTH(B50,1) -> 46326 | C51: $/RIN | D51: =_xlfn.XLOOKUP(E51,'D3 Forecast Stratas Dec25'!$I$4:$AH$4,'D3 Forecast Stratas Dec25'!$I$6:$AH$6,0) -> 2.4896873 | E51: =YEAR(B51) -> 2026
B52: =EOMONTH(B51,1) -> 46356 | C52: $/RIN | D52: =_xlfn.XLOOKUP(E52,'D3 Forecast Stratas Dec25'!$I$4:$AH$4,'D3 Forecast Stratas Dec25'!$I$6:$AH$6,0) -> 2.4896873 | E52: =YEAR(B52) -> 2026
B53: =EOMONTH(B52,1) -> 46387 | C53: $/RIN | D53: =_xlfn.XLOOKUP(E53,'D3 Forecast Stratas Dec25'!$I$4:$AH$4,'D3 Forecast Stratas Dec25'!$I$6:$AH$6,0) -> 2.4896873 | E53: =YEAR(B53) -> 2026
B54: =EOMONTH(B53,1) -> 46418 | C54: $/RIN | D54: =_xlfn.XLOOKUP(E54,'D3 Forecast Stratas Dec25'!$I$4:$AH$4,'D3 Forecast Stratas Dec25'!$I$6:$AH$6,0) -> 2.6040894 | E54: =YEAR(B54) -> 2027
B55: =EOMONTH(B54,1) -> 46446 | C55: $/RIN | D55: =_xlfn.XLOOKUP(E55,'D3 Forecast Stratas Dec25'!$I$4:$AH$4,'D3 Forecast Stratas Dec25'!$I$6:$AH$6,0) -> 2.6040894 | E55: =YEAR(B55) -> 2027
B56: =EOMONTH(B55,1) -> 46477 | C56: $/RIN | D56: =_xlfn.XLOOKUP(E56,'D3 Forecast Stratas Dec25'!$I$4:$AH$4,'D3 Forecast Stratas Dec25'!$I$6:$AH$6,0) -> 2.6040894 | E56: =YEAR(B56) -> 2027
... B341: =EOMONTH(B340,1) -> 55153 | C341: $/RIN | D341: =_xlfn.XLOOKUP(E341,'D3 Forecast Stratas Dec25'!$I$4:$AH$4,'D3 Forecast Stratas Dec25'!$I$6:$AH$6,0) -> 3.9115709 | E341: =YEAR(B341) -> 2050

Sheet D3 RIN 2013-2025
A3: Row Labels | B3: Average of RIN Price
A4: 2013 | B4: 0.735
A5: 2014 | B5: 0.94537037
A6: 2015 | B6: 1.1598291
A7: 2016 | B7: 2.0779231
A8: 2017 | B8: 2.449469
A9: 2018 | B9: 1.8759259
A10: 2019 | B10: 1.4938525
A11: 2020 | B11: 2.1900714
A12: 2021 | B12: 2.7803571
A13: 2022 | B13: 2.7842568
A14: 2023 | B14: 2.7536207
A15: 2024 | B15: 2.8623016
A16: 2025 | B16: 2.4357407
A17: Grand Total | B17: 2.216465

Sheet D3 Forecast Stratas Dec25
I1: =AVERAGE(I6:S6) -> 2.7416403
I2: 2.62
I4: =YEAR(I5) -> 2025 | J4: =YEAR(J5) -> 2026 | K4: =YEAR(K5) -> 2027 | L4: =YEAR(L5) -> 2028 | M4: =YEAR(M5) -> 2029 | N4: =YEAR(N5) -> 2030 | O4: =YEAR(O5) -> 2031 | P4: =YEAR(P5) -> 2032 | ... S4: =YEAR(S5) -> 2035 | T4: =+S4+1 -> 2036 | U4: =+T4+1 -> 2037 | V4: =+U4+1 -> 2038 | W4: =+V4+1 -> 2039 | X4: =+W4+1 -> 2040 | Y4: =+X4+1 -> 2041 | Z4: =+Y4+1 -> 2042 | AA4: =+Z4+1 -> 2043 | ... AH4: =+AG4+1 -> 2050
A5: Label | B5: 43101 | C5: 43466 | D5: 43831 | E5: 44197 | F5: 44562 | G5: 44927 | H5: 45292 | I5: 45658 | J5: 46023 | K5: 46388 | L5: 46753 | M5: 47119 | N5: 47484 | O5: 47849 | P5: 48214 | Q5: 48580 | R5: 48945 | S5: 49310
B6: 2.3372915 | C6: 1.2864744 | D6: 1.3293615 | E6: 2.6946563 | F6: 3.061316 | G6: 2.5342778 | H6: 3.1019847 | I6: 2.3404618 | J6: 2.4896873 | K6: 2.6040894 | L6: 2.6619581 | M6: 2.7118204 | N6: 2.7914813 | O6: 2.9160811 | P6: 2.9781765 | Q6: 2.9101359 | R6: 2.8799224 | S6: 2.8742294 | T6: =+S6*(1+$B$10) -> 2.9338872 | U6: =+T6*(1+$B$10) -> 2.9947832 | V6: =+U6*(1+$B$10) -> 3.0569433 | W6: =+V6*(1+$B$10) -> 3.1203935 | X6: =+W6*(1+$B$10) -> 3.1851607 | Y6: =+X6*(1+$B$10) -> 3.2512722 | Z6: =+Y6*(1+$B$10) -> 3.318756 | AA6: =+Z6*(1+$B$10) -> 3.3876404 | ... AH6: =+AG6*(1+$B$10) -> 3.9115709
A7: D3 RIN Price Optimistic | B7: 2.3372915 | C7: 1.2864744 | D7: 1.3293615 | E7: 2.6946563 | F7: 3.061316 | G7: 2.5342778 | H7: 3.1019847 | I7: 2.3404618 | J7: 2.8536238 | K7: 3.2024789 | L7: 3.4086328 | M7: 3.5523553 | N7: 3.6744411 | O7: 3.7043814 | P7: 3.7236784 | Q7: 3.7103197 | R7: 3.6865552 | S7: 3.6670509
A8: D3 RIN Price Pessimistic | B8: 2.3372915 | C8: 1.2864744 | D8: 1.3293615 | E8: 2.6946563 | F8: 3.061316 | G8: 2.5342778 | H8: 3.1019847 | I8: 2.3404618 | J8: 1.8833333 | K8: 1.6514506 | L8: 1.6793211 | M8: 1.7045109 | N8: 1.7556462 | O8: 1.8024954 | P8: 1.7598587 | Q8: 1.6844132 | R8: 1.6557108 | S8: 1.6216562
A10: D3 RIN Price Base Case | B10: =(S6/I6)^(1/10)-1 -> 0.020756104 | C10: <-- CAGR (2025 - 2035)

Sheet Misc. Tables
C1: =+C2/20 -> 13.5
C2: 270
D3: =+D4-D5 -> 102943.77
D4: =+'Bid Forms'!J23 -> 299564.81
D5: =+D9*D7 -> 196621.04
B7: 0.06 | C7: RNG Production | D7: 6605.4959 | E7: 7600 | F7: 8105 | G7: 8500 | H7: 9000
B8: 0.07 | C8: RIN Prices | D8: 2.5382689 | E8: 3 | F8: 3 | G8: 3.25 | H8: 3.75
C9: RIN Prices, $/MMBtu | D9: =D8*11.727 -> 29.76628 | E9: =E8*11.727 -> 35.181 | F9: =F8*11.727 -> 35.181 | G9: =G8*11.727 -> 38.11275 | H9: =H8*11.727 -> 43.97625
B10: 0.015 | C10: Nat Gas | D10: 3.932891 | E10: 3.5 | F10: =E10*(1+$B10) -> 3.5525 | G10: 3.65 | H10: =G10*(1+$B10) -> 3.70475
C11: (-) Brokerage | D11: =-0.2*D9 -> -5.953256 | E11: =-0.2*E9 -> -7.0362 | F11: =-0.2*F9 -> -7.0362 | G11: =-0.2*G9 -> -7.62255 | H11: =-0.2*H9 -> -8.79525
C12: Gross Offtake | D12: =D7*SUM(D9:D10) -> 222599.74 | E12: =E7*SUM(E9:E10) -> 293975.6 | F12: =F7*SUM(F9:F10) -> 313935.02 | G12: =G7*SUM(G9:G10) -> 354983.38 | H12: =H7*SUM(H9:H10) -> 429129
C13: Brokerage | D13: =+D11*D7 -> -39324.208 | E13: =+E11*E7 -> -53475.12 | F13: =+F11*F7 -> -57028.401 | G13: =+G11*G7 -> -64791.675 | H13: =+H11*H7 -> -79157.25
J14: MWS Total Evaluative Contract Value ($MM) - 70% Royalty
K15: 20-yr TOTAL RNG Production
J16: =+D35 -> 66.170494 | K16: 6000 | L16: =+K16+250 -> 6250 | M16: 6605.4999 | N16: =+M16+250 -> 6855.4999 | O16: =+N16+250 -> 7105.4999 | P16: =+O16+250 -> 7355.4999 | Q16: =+P16+250 -> 7605.4999 | R16: =+Q16+250 -> 7855.4999 | S16: =+R16+250 -> 8105.4999 | T16: =+S16+250 -> 8355.4999 | U16: =+T16+250 -> 8605.4999 | V16: =+U16+250 -> 8855.4999
C17: RNG Production, K MMBtu | D17: =+D7 -> 6605.4959 | E17: =+E7 -> 7600 | F17: =+F7 -> 8105 | G17: =+G7 -> 8500 | H17: =+H7 -> 9000 | J17: 1.7 | K17: 21.380391 | L17: 24.859673 | M17: 29.80721 | N17: 33.286492 | O17: 36.765774 | P17: 40.245056 | Q17: 43.724338 | R17: 47.20362 | S17: 50.682902 | T17: 54.162184 | U17: 57.641466 | V17: 61.120748
C18: Avg. D3 RIN, $/RIN | D18: =+D8 -> 2.5382689 | E18: =+E8 -> 3 | F18: =+F8 -> 3 | G18: =+G8 -> 3.25 | H18: =+H8 -> 3.75 | J18: =+J17+0.2 -> 1.9 | K18: 29.260935 | L18: 33.068573 | M18: 38.483033 | N18: 42.29067 | O18: 46.098308 | P18: 49.905946 | Q18: 53.713584 | R18: 57.521222 | S18: 61.32886 | T18: 65.136498 | U18: 68.944136 | V18: 72.751774
C19: $ in millions | J19: =+J18+0.2 -> 2.1 | K19: 37.141479 | L19: 41.277473 | M19: 47.158855 | N19: 51.294849 | O19: 55.430842 | P19: 59.566836 | Q19: 63.70283 | R19: 67.838824 | S19: 71.974818 | T19: 76.110812 | U19: 80.246806 | V19: 84.3828
C20: 20- year Evaluative Value of the sale of RNG and EAs | D20: =+D12/1000 -> 222.59974 | E20: =+E12/1000 -> 293.9756 | F20: =+F12/1000 -> 313.93502 | G20: =+G12/1000 -> 354.98338 | H20: =+H12/1000 -> 429.129 | J20: =+J19+0.2 -> 2.3 | K20: 45.022023 | L20: 49.486373 | M20: 55.834677 | N20: 60.299027 | O20: 64.763377 | P20: 69.227726 | Q20: 73.692076 | R20: 78.156426 | S20: 82.620776 | T20: 87.085126 | U20: 91.549476 | V20: 96.013826
C21: (-) 20-year Allowance for RIN Management | D21: =D13/1000 -> -39.324208 | E21: =E13/1000 -> -53.47512 | F21: =F13/1000 -> -57.028401 | G21: =G13/1000 -> -64.791675 | H21: =H13/1000 -> -79.15725 | J21: 2.54499 | K21: 54.675295 | L21: 59.541865 | M21: 66.462125 | N21: 71.328695 | O21: 76.195264 | P21: 81.061834 | Q21: 85.928403 | R21: 90.794973 | S21: 95.661543 | T21: 100.52811 | U21: 105.39468 | V21: 110.26125
C22: Net Offtake Revenue (1) + (2) | D22: =SUM(D20:D21) -> 183.27553 | E22: =SUM(E20:E21) -> 240.50048 | F22: =SUM(F20:F21) -> 256.90662 | G22: =SUM(G20:G21) -> 290.1917 | H22: =SUM(H20:H21) -> 349.97175 | J22: =+J21+0.2 -> 2.74499 | K22: 62.555839 | L22: 67.750765 | M22: 75.137947 | N22: 80.332873 | O22: 85.527798 | P22: 90.722724 | Q22: 95.917649 | R22: 101.11258 | S22: 106.3075 | T22: 111.50243 | U22: 116.69735 | V22: 121.89228
J23: 2.82 | K23: 65.511437 | L23: 70.829513 | M23: 78.391814 | N23: 83.70989 | O23: 89.027965 | P23: 94.346041 | Q23: 99.664116 | R23: 104.98219 | S23: 110.30027 | T23: 115.61834 | U23: 120.93642 | V23: 126.25449
C24: Royalty Under 70% Royalty (1) | D24: =+MIN($C$2,D22) -> 183.27553 | E24: =+MIN($C$2,E22) -> 240.50048 | F24: =+MIN($C$2,F22) -> 256.90662 | G24: =+MIN($C$2,G22) -> 270 | H24: =+MIN($C$2,H22) -> 270 | J24: 3 | K24: 72.603927 | L24: 78.217523 | M24: 86.200054 | N24: 91.81365 | O24: 97.427246 | P24: 103.04084 | Q24: 108.65444 | R24: 114.26803 | S24: 119.88163 | T24: 125.49523 | U24: 131.10882 | V24: 136.72242
C25: (-) Capital Cost Allowance | D25: =-INPUTS!S24/1000 -> -36.835 | E25: =+D25 -> -36.835 | F25: =+E25 -> -36.835 | G25: =+F25 -> -36.835 | H25: =+G25 -> -36.835 | J25: =+J24+0.2 -> 3.2 | K25: 80.484471 | L25: 86.426423 | M25: 94.875876 | N25: 100.81783 | O25: 106.75978 | P25: 112.70173 | Q25: 118.64368 | R25: 124.58564 | S25: 130.52759 | T25: 136.46954 | U25: 142.41149 | V25: 148.35344
C26: (-) Capital Cost Financing Fee | D26: 0 | E26: 0 | F26: 0 | G26: 0 | H26: 0 | J26: =+J25+0.2 -> 3.4 | K26: 88.365015 | L26: 94.635323 | M26: 103.5517 | N26: 109.82201 | O26: 116.09231 | P26: 122.36262 | Q26: 128.63293 | R26: 134.90324 | S26: 141.17355 | T26: 147.44385 | U26: 153.71416 | V26: 159.98447
C27: (-) Allowance for Operations and Maintenance | D27: =-Model!D44/1000 -> -51.91125 | E27: =+D27 -> -51.91125 | F27: -65 | G27: =+F27 -> -65 | H27: =+G27 -> -65 | J27: =+J26+0.2 -> 3.6 | K27: 96.245559 | L27: 102.84422 | M27: 112.22752 | N27: 118.82618 | O27: 125.42485 | P27: 132.02351 | Q27: 138.62218 | R27: 145.22084 | S27: 151.8195 | T27: 158.41817 | U27: 165.01683 | V27: 171.6155
C28: Available Royalty - 70% Sharing | D28: =SUM(D24:D27) -> 94.529277 | E28: =SUM(E24:E27) -> 151.75423 | F28: =SUM(F24:F27) -> 155.07162 | G28: =SUM(G24:G27) -> 168.165 | H28: =SUM(H24:H27) -> 168.165 | J28: =+J27+0.2 -> 3.8 | K28: 104.1261 | L28: 111.05312 | M28: 120.90334 | N28: 127.83036 | O28: 134.75738 | P28: 141.6844 | Q28: 148.61142 | R28: 155.53844 | S28: 162.46546 | T28: 169.39248 | U28: 176.3195 | V28: 183.24652
C29: Royalty Payment (70%) | D29: =0.7*D28 -> 66.170494 | E29: =0.7*E28 -> 106.22796 | F29: =0.7*F28 -> 108.55013 | G29: =0.7*G28 -> 117.7155 | H29: =0.7*H28 -> 117.7155
J30: MWS Total Royalty ($MM) - 70% (up to $270MM) and 90% (above $270MM Net Offtake Revenue)
C31: Royalty Under 90% Royalty (2) | D31: =+D22-D24 -> 0 | E31: =+E22-E24 -> 0 | F31: =+F22-F24 -> 0 | G31: =+G22-G24 -> 20.1917 | H31: =+H22-H24 -> 79.97175 | K31: 20-yr TOTAL RNG Production
C32: Royalty Payment (90%) | D32: =0.9*D31 -> 0 | E32: =0.9*E31 -> 0 | F32: =0.9*F31 -> 0 | G32: =0.9*G31 -> 18.17253 | H32: =0.9*H31 -> 71.974575 | J32: =+D34 -> 66.170494 | K32: 6000 | L32: =+K32+250 -> 6250 | M32: 6605.4959 | N32: =+M32+250 -> 6855.4959 | O32: =+N32+250 -> 7105.4959 | P32: =+O32+250 -> 7355.4959 | Q32: =+P32+250 -> 7605.4959 | R32: =+Q32+250 -> 7855.4959 | S32: =+R32+250 -> 8105.4959 | T32: =+S32+250 -> 8355.4959 | U32: =+T32+250 -> 8605.4959 | V32: =+U32+250 -> 8855.4959
J33: 1.7 | K33: 21.380391 | L33: 24.859673 | M33: 29.807155 | N33: 33.286437 | O33: 36.765719 | P33: 40.245001 | Q33: 43.724283 | R33: 47.203565 | S33: 50.682847 | T33: 54.162129 | U33: 57.641411 | V33: 61.120692
C34: TOTAL ROYALTY to MWS | D34: =+D29+D32 -> 66.170494 | E34: =+E29+E32 -> 106.22796 | F34: =+F29+F32 -> 108.55013 | G34: =+G29+G32 -> 135.88803 | H34: =+H29+H32 -> 189.69007 | J34: =+J33+0.2 -> 1.9 | K34: 29.260935 | L34: 33.068573 | M34: 38.482972 | N34: 42.29061 | O34: 46.098248 | P34: 49.905886 | Q34: 53.713524 | R34: 57.521162 | S34: 61.3288 | T34: 65.136438 | U34: 68.944075 | V34: 72.751713
C35: TOTAL ROYALTY to MWS w/o 90% Tier | D35: =+D29+D31*0.7 -> 66.170494 | E35: =+E29+E31*0.7 -> 106.22796 | F35: =+F29+F31*0.7 -> 108.55013 | G35: =+G29+G31*0.7 -> 131.84969 | H35: =+H29+H31*0.7 -> 173.69572 | J35: =+J34+0.2 -> 2.1 | K35: 37.141479 | L35: 41.277473 | M35: 47.158789 | N35: 51.294783 | O35: 55.430777 | P35: 59.566771 | Q35: 63.702765 | R35: 67.838759 | S35: 71.974752 | T35: 76.110746 | U35: 80.24674 | V35: 84.382734
C36: Benefit of 90% Split | D36: =+D34-D35 -> 0 | E36: =+E34-E35 -> 0 | F36: =+F34-F35 -> 0 | G36: =+G34-G35 -> 4.03834 | H36: =+H34-H35 -> 15.99435 | J36: =+J35+0.2 -> 2.3 | K36: 45.022023 | L36: 49.486373 | M36: 55.834606 | N36: 60.298956 | O36: 64.763306 | P36: 69.227656 | Q36: 73.692006 | R36: 78.156355 | S36: 82.620705 | T36: 87.085055 | U36: 91.549405 | V36: 96.013755
C37: % Benefit | F37: =+F36/F35 -> 0 | G37: =+G36/G35 -> 0.030628362 | H37: =+H36/H35 -> 0.092082577 | J37: 2.5382689 | K37: 54.410467 | L37: 59.266002 | M37: 66.170494 | N37: 71.026029 | O37: 75.881564 | P37: 80.737099 | Q37: 85.592635 | R37: 90.44817 | S37: 95.303705 | T37: 100.15924 | U37: 105.01477 | V37: 109.87031
J38: =+J37+0.2 -> 2.7382689 | K38: 62.291011 | L38: 67.474902 | M38: 74.846311 | N38: 80.030202 | O38: 85.214093 | P38: 90.397984 | Q38: 95.581875 | R38: 100.76577 | S38: 105.94966 | T38: 111.13355 | U38: 116.31744 | V38: 121.50133
J39: 2.82 | K39: 65.511437 | L39: 70.829513 | M39: 78.39173 | N39: 83.709805 | O39: 89.027881 | P39: 94.345956 | Q39: 99.664032 | R39: 104.98211 | S39: 110.30018 | T39: 115.61826 | U39: 120.93633 | V39: 126.25441
J40: 3 | K40: 72.603927 | L40: 78.217523 | M40: 86.199965 | N40: 91.813561 | O40: 97.427157 | P40: 103.04075 | Q40: 108.65435 | R40: 114.26794 | S40: 119.88154 | T40: 125.49514 | U40: 132.31762 | V40: 139.5351
J41: =+J40+0.2 -> 3.2 | K41: 80.484471 | L41: 86.426423 | M41: 94.875782 | N41: 100.81773 | O41: 106.75969 | P41: 112.70164 | Q41: 118.64359 | R41: 124.58554 | S41: 131.57031 | T41: 139.20997 | U41: 146.84962 | V41: 154.48927
C42: Net Revenue | D42: =+D22 -> 183.27553 | E42: =+E22 -> 240.50048 | F42: =+F22 -> 256.90662 | G42: =+G22 -> 290.1917 | H42: =+H22 -> 349.97175 | J42: =+J41+0.2 -> 3.4 | K42: 88.365015 | L42: 94.635323 | M42: 103.5516 | N42: 109.82191 | O42: 116.09221 | P42: 122.36252 | Q42: 129.13432 | R42: 137.19614 | S42: 145.25797 | T42: 153.31979 | U42: 161.38162 | V42: 169.44344
C43: (-) Capital Cost Allowance | D43: =+D25 -> -36.835 | E43: =+E25 -> -36.835 | F43: =+F25 -> -36.835 | G43: =+G25 -> -36.835 | J43: =+J42+0.2 -> 3.6 | K43: 96.245559 | L43: 102.84422 | M43: 112.22742 | N43: 118.82608 | O43: 125.42474 | P43: 133.49363 | Q43: 141.97763 | R43: 150.46162 | S43: 158.94562 | T43: 167.42962 | U43: 175.91361 | V43: 184.39761
C44: (-) Capital Cost Financing Fee | D44: =+D26 -> 0 | E44: =+E26 -> 0 | F44: =+F26 -> 0 | G44: =+G26 -> 0 | J44: =+J43+0.2 -> 3.8 | K44: 104.1261 | L44: 111.05312 | M44: 120.90323 | N44: 128.10243 | O44: 137.0086 | P44: 145.91477 | Q44: 154.82094 | R44: 163.72711 | S44: 172.63327 | T44: 181.53944 | U44: 190.44561 | V44: 199.35178
C45: (-) Allowance for Operations and Maintenance | D45: =+D27 -> -51.91125 | E45: =+E27 -> -51.91125 | F45: =+F27 -> -65 | G45: =+G27 -> -65 | H45: =+H27 -> -65
C46: Net Proceeds Available | D46: =+SUM(D42:D45) -> 94.529277 | E46: =+SUM(E42:E45) -> 151.75423 | F46: =+SUM(F42:F45) -> 155.07162 | G46: =+SUM(G42:G45) -> 188.3567 | H46: =+SUM(H42:H45) -> 284.97175 | V46: 188.7
C47: MWS 70% Share | D47: =+D29 -> 66.170494 | E47: =+E29 -> 106.22796 | F47: =+F29 -> 108.55013 | G47: =+G29 -> 117.7155 | H47: =+H29 -> 117.7155 | V47: 173.5
C48: MWS 90% Share | D48: =+D32 -> 0 | E48: =+E32 -> 0 | F48: =+F32 -> 0 | G48: =+G32 -> 18.17253 | H48: =+H32 -> 71.974575 | V48: =+V46-V47 -> 15.2
C49: BRNG Share | D49: =+D46-D47-D48 -> 28.358783 | E49: =+E46-E47-E48 -> 45.526269 | F49: =+F46-F47-F48 -> 46.521485 | G49: =+G46-G47-G48 -> 52.46867 | H49: =+H46-H47-H48 -> 95.281675 | L49: 219.1 | V49: =+V48/V47 -> 0.087608069
L50: =-0.2*L49 -> -43.82
C51: Gross Offtake | D51: =+G20 -> 354.98338
C52: (-) RIN Brokerage | D52: =+G21 -> -64.791675
D53: =SUM(D51:D52) -> 290.1917
D54: 270
D55: =+G25 -> -36.835
D56: =0.25*D55 -> -9.20875
D57: =+G27-D56 -> -55.79125
D58: =SUM(D54:D57) -> 168.165
D59: -40
D60: =-G29-D59 -> -77.7155
D61: =SUM(D58:D60) -> 50.4495
D62: =+D53-D54 -> 20.1917
D63: =-G32 -> -18.17253
D64: =+SUM(D62:D63) -> 2.01917
D67: =+D60+D63 -> -95.88803
E72: Offtake Revenue excl. brokerage | F72: =G20 -> 354.98338
E73: Brokerage (20%) | F73: =G21 -> -64.791675
E74: Offtake Rev., net of brokerage | F74: =SUM(F72:F73) -> 290.1917
E75: Capital Cost Allowance | F75: =G25 -> -36.835
E76: Capital Cost Financing Fee | F76: =25%*F75 -> -9.20875
E77: Allowance for OMM | F77: =G27-F76 -> -55.79125
E78: Avail. For Royalty | F78: =+SUM(F74:F77) -> 188.3567
E79: MWS Fixed Royalty | F79: -40
E80: Tier 1 Split 70% to MWS | F80: =-G29-F79 -> -77.7155
E81: Tier 2 Split 90% to MWS | F81: =-G32 -> -18.17253
E82: Burnham Residual | F82: =SUM(F78:F81) -> 52.46867
